Workbook

Sheet Assumption
A2: Option Selection
A3: Operating Scenario | C3: 1
D4: Projected
D5: 2025 | E5: =D5+1 -> 2026 | F5: =E5+1 -> 2027 | G5: =F5+1 -> 2028 | H5: =G5+1 -> 2029 | I5: =H5+1 -> 2030 | J5: =I5+1 -> 2031 | K5: =J5+1 -> 2032 | L5: =K5+1 -> 2033 | M5: =L5+1 -> 2034
A8: Total Revenue Growth | D8: =CHOOSE($C$3,D9,D10,D11) -> 0.32 | E8: =CHOOSE($C$3,E9,E10,E11) -> 0.3 | F8: =CHOOSE($C$3,F9,F10,F11) -> 0.27 | G8: =CHOOSE($C$3,G9,G10,G11) -> 0.24 | H8: =CHOOSE($C$3,H9,H10,H11) -> 0.22 | I8: =CHOOSE($C$3,I9,I10,I11) -> 0.2 | J8: =CHOOSE($C$3,J9,J10,J11) -> 0.2 | K8: =CHOOSE($C$3,K9,K10,K11) -> 0.18 | ... M8: =CHOOSE($C$3,M9,M10,M11) -> 0.18
A9: Base | D9: 0.32 | E9: 0.3 | F9: 0.27 | G9: 0.24 | H9: 0.22 | I9: 0.2 | J9: 0.2 | K9: 0.18 | L9: 0.18 | M9: 0.18
A10: Bull | D10: 0.325 | E10: 0.3 | F10: 0.28 | G10: 0.26 | H10: 0.25 | I10: 0.23 | J10: 0.22 | K10: 0.2 | L10: 0.18 | M10: 0.18
A11: Bear | D11: 0.28 | E11: 0.26 | F11: 0.23 | G11: 0.2 | H11: 0.17 | I11: 0.16 | J11: 0.14 | K11: 0.14 | L11: 0.12 | M11: 0.12
A13: Gross Margin | D13: =1-D14 -> 0.8325 | E13: =1-E14 -> 0.835 | F13: =1-F14 -> 0.835 | G13: =1-G14 -> 0.8375 | H13: =1-H14 -> 0.8375 | I13: =1-I14 -> 0.8375 | J13: =1-J14 -> 0.8375 | K13: =1-K14 -> 0.8375 | ... M13: =1-M14 -> 0.8375
A14: COGS | D14: {=INDEX(D15:D17,$C$3)} -> 0.1675 | E14: {=INDEX(E15:E17,$C$3)} -> 0.165 | F14: {=INDEX(F15:F17,$C$3)} -> 0.165 | G14: {=INDEX(G15:G17,$C$3)} -> 0.1625 | H14: {=INDEX(H15:H17,$C$3)} -> 0.1625 | I14: {=INDEX(I15:I17,$C$3)} -> 0.1625 | J14: {=INDEX(J15:J17,$C$3)} -> 0.1625 | K14: {=INDEX(K15:K17,$C$3)} -> 0.1625 | ... M14: {=INDEX(M15:M17,$C$3)} -> 0.1625
A15: Base | D15: 0.1675 | E15: 0.165 | F15: 0.165 | G15: 0.1625 | H15: 0.1625 | I15: 0.1625 | J15: 0.1625 | K15: 0.1625 | L15: 0.1625 | M15: 0.1625
A16: Bull | D16: 0.1625 | E16: 0.1625 | F16: 0.16 | G16: 0.16 | H16: 0.16 | I16: 0.16 | J16: 0.16 | K16: 0.16 | L16: 0.16 | M16: 0.16
A17: Bear | D17: 0.185 | E17: 0.18 | F17: 0.18 | G17: 0.1775 | H17: 0.1775 | I17: 0.175 | J17: 0.175 | K17: 0.175 | L17: 0.175 | M17: 0.175
A20: Operating Expense
A22: SG&A | D22: {=INDEX(D23:D25,$C$3)} -> 0.2075 | E22: {=INDEX(E23:E25,$C$3)} -> 0.2075 | F22: {=INDEX(F23:F25,$C$3)} -> 0.2075 | G22: {=INDEX(G23:G25,$C$3)} -> 0.205 | H22: {=INDEX(H23:H25,$C$3)} -> 0.205 | I22: {=INDEX(I23:I25,$C$3)} -> 0.2025 | J22: {=INDEX(J23:J25,$C$3)} -> 0.2025 | K22: {=INDEX(K23:K25,$C$3)} -> 0.2025 | ... M22: {=INDEX(M23:M25,$C$3)} -> 0.2025
A23: Base | D23: 0.2075 | E23: 0.2075 | F23: 0.2075 | G23: 0.205 | H23: 0.205 | I23: 0.2025 | J23: 0.2025 | K23: 0.2025 | L23: 0.2025 | M23: 0.2025
A24: Bull | D24: 0.205 | E24: 0.205 | F24: 0.2025 | G24: 0.2 | H24: 0.2 | I24: 0.2 | J24: 0.2 | K24: 0.2 | L24: 0.2 | M24: 0.2
A25: Bear | D25: 0.2175 | E25: 0.215 | F25: 0.2125 | G25: 0.21 | H25: 0.2075 | I25: 0.2075 | J25: 0.2075 | K25: 0.2075 | L25: 0.2075 | M25: 0.2075
A27: R&D | D27: {=INDEX(D28:D30,$C$3)} -> 0.265 | E27: {=INDEX(E28:E30,$C$3)} -> 0.265 | F27: {=INDEX(F28:F30,$C$3)} -> 0.265 | G27: {=INDEX(G28:G30,$C$3)} -> 0.2625 | H27: {=INDEX(H28:H30,$C$3)} -> 0.2625 | I27: {=INDEX(I28:I30,$C$3)} -> 0.2625 | J27: {=INDEX(J28:J30,$C$3)} -> 0.2625 | K27: {=INDEX(K28:K30,$C$3)} -> 0.2625 | ... M27: {=INDEX(M28:M30,$C$3)} -> 0.2625
A28: Base | D28: 0.265 | E28: 0.265 | F28: 0.265 | G28: 0.2625 | H28: 0.2625 | I28: 0.2625 | J28: 0.2625 | K28: 0.2625 | L28: 0.2625 | M28: 0.2625
A29: Bull | D29: 0.2625 | E29: 0.2625 | F29: 0.2625 | G29: 0.26 | H29: 0.26 | I29: 0.26 | J29: 0.26 | K29: 0.26 | L29: 0.26 | M29: 0.26
A30: Bear | D30: 0.2725 | E30: 0.2725 | F30: 0.2675 | G30: 0.2675 | H30: 0.2675 | I30: 0.265 | J30: 0.265 | K30: 0.265 | L30: 0.265 | M30: 0.265
A33: Capex | D33: {=INDEX(D34:D36,$C$3)} -> 0.12 | E33: {=INDEX(E34:E36,$C$3)} -> 0.12 | F33: {=INDEX(F34:F36,$C$3)} -> 0.12 | G33: {=INDEX(G34:G36,$C$3)} -> 0.1175 | H33: {=INDEX(H34:H36,$C$3)} -> 0.1175 | I33: {=INDEX(I34:I36,$C$3)} -> 0.115 | J33: {=INDEX(J34:J36,$C$3)} -> 0.115 | K33: {=INDEX(K34:K36,$C$3)} -> 0.115 | ... M33: {=INDEX(M34:M36,$C$3)} -> 0.115
A34: Base | D34: 0.12 | E34: 0.12 | F34: 0.12 | G34: 0.1175 | H34: 0.1175 | I34: 0.115 | J34: 0.115 | K34: 0.115 | L34: 0.115 | M34: 0.115
A35: Bull | D35: 0.1175 | E35: 0.1175 | F35: 0.1175 | G35: 0.115 | H35: 0.115 | I35: 0.1125 | J35: 0.1125 | K35: 0.1125 | L35: 0.1125 | M35: 0.1125
A36: Bear | D36: 0.125 | E36: 0.1225 | F36: 0.1225 | G36: 0.12 | H36: 0.12 | I36: 0.1175 | J36: 0.1175 | K36: 0.1175 | L36: 0.1175 | M36: 0.1175
A38: Other Income | D38: {=INDEX(D39:D41,$C$3)} -> 0 | E38: 0 | F38: {=INDEX(F39:F41,$C$3)} -> 0 | G38: {=INDEX(G39:G41,$C$3)} -> 0 | H38: {=INDEX(H39:H41,$C$3)} -> 0 | I38: {=INDEX(I39:I41,$C$3)} -> 0 | J38: {=INDEX(J39:J41,$C$3)} -> 0 | K38: {=INDEX(K39:K41,$C$3)} -> 0 | L38: {=INDEX(L39:L41,$C$3)} -> 0 | M38: {=INDEX(M39:M41,$C$3)} -> 0
A39: Base | D39: 0 | E39: 0 | F39: 0 | G39: 0 | H39: 0 | I39: 0 | J39: 0 | K39: 0 | L39: 0 | M39: 0
A40: Bull | D40: 0 | E40: 0 | F40: 0 | G40: 0 | H40: 0 | I40: 0 | J40: 0 | K40: 0 | L40: 0 | M40: 0
A41: Bear | D41: 0 | E41: 0 | F41: 0 | G41: 0 | H41: 0 | I41: 0 | J41: 0 | K41: 0 | L41: 0 | M41: 0

Sheet DCF
A1: Eli Lilly
A2: Discounted Cash Flow Analysis
A3: For the Years Ended December 31
A4: Millions of Dollars
N5: Terminal
B6: =2023 -> 2023 | C6: =+B6+1 -> 2024 | D6: =+C6+1 -> 2025 | E6: =+D6+1 -> 2026 | F6: =+E6+1 -> 2027 | G6: =+F6+1 -> 2028 | H6: =+G6+1 -> 2029 | I6: =+H6+1 -> 2030 | J6: =+I6+1 -> 2031 | ... M6: =+L6+1 -> 2034 | N6: Value
B7: -------------- | C7: -------------- | D7: -------------- | E7: -------------- | F7: -------------- | G7: -------------- | H7: -------------- | I7: -------------- | J7: -------------- | K7: -------------- | L7: -------------- | M7: -------------- | N7: --------------
A8: Revenue | B8: 34124.2 | C8: 45042.7 | D8: =C8*(1+D57) -> 59456.364 | E8: =D8*(1+E57) -> 77293.273 | F8: =E8*(1+F57) -> 98162.457 | G8: =F8*(1+G57) -> 121721.45 | H8: =G8*(1+H57) -> 148500.16 | I8: =H8*(1+I57) -> 178200.2 | J8: =I8*(1+J57) -> 213840.24 | K8: =J8*(1+K57) -> 252331.48 | ... M8: =L8*(1+M57) -> 351346.35
A9: Cost of Goods Sold | B9: 6576 | C9: 7865.1 | D9: =D8*D58 -> 9958.941 | E9: =E8*E58 -> 12753.39 | F9: =F8*F58 -> 16196.805 | G9: =G8*G58 -> 19779.735 | H9: =H8*H58 -> 24131.277 | I9: =I8*I58 -> 28957.532 | J9: =J8*J58 -> 34749.039 | K9: =K8*K58 -> 41003.866 | ... M9: =M8*M58 -> 57093.782
B10: -------------- | C10: -------------- | D10: -------------- | E10: -------------- | F10: -------------- | G10: -------------- | H10: -------------- | I10: -------------- | J10: -------------- | K10: -------------- | L10: -------------- | M10: --------------
A11: Gross Margin | B11: =+B8-B9 -> 27548.2 | C11: =+C8-C9 -> 37177.6 | D11: =D8-D9 -> 49497.423 | E11: =E8-E9 -> 64539.883 | F11: =F8-F9 -> 81965.652 | G11: =G8-G9 -> 101941.71 | H11: =H8-H9 -> 124368.89 | I11: =I8-I9 -> 149242.67 | J11: =J8-J9 -> 179091.2 | K11: =K8-K9 -> 211327.61 | ... M11: =M8-M9 -> 294252.57
A13: Operating Expenses:
A14: SG&A | B14: 7403.1 | C14: 8593.8 | D14: =D8*D63 -> 12337.196 | E14: =E8*E63 -> 16038.354 | F14: =F8*F63 -> 20368.71 | G14: =G8*G63 -> 24952.897 | H14: =H8*H63 -> 30442.534 | I14: =I8*I63 -> 36085.54 | J14: =J8*J63 -> 43302.648 | K14: =K8*K63 -> 51097.125 | ... M14: =M8*M63 -> 71147.636
A15: R&D | B15: 9313.4 | C15: 10990.6 | D15: =D8*D64 -> 15755.936 | E15: =E8*E64 -> 20482.717 | F15: =F8*F64 -> 26013.051 | G15: =G8*G64 -> 31951.88 | H15: =H8*H64 -> 38981.293 | I15: =I8*I64 -> 46777.552 | J15: =J8*J64 -> 56133.062 | K15: =K8*K64 -> 66237.014 | ... M15: =M8*M64 -> 92228.418
A16: Lease | B16: 171.2 | C16: 209.6 | D16: 221.2 | E16: 189.1 | F16: 172.2 | G16: 130.3 | H16: 108.6 | I16: 65.1 | J16: 65.1 | K16: 65.1 | L16: 65.1 | M16: 65.1
B17: -------------- | C17: -------------- | D17: -------------- | E17: -------------- | F17: -------------- | G17: -------------- | H17: -------------- | I17: -------------- | J17: -------------- | K17: -------------- | L17: -------------- | M17: --------------
A18: Total Operating Expenses | B18: =SUM(B14:B17) -> 16887.7 | C18: =SUM(C14:C17) -> 19794 | D18: =SUM(D14:D16) -> 28314.332 | E18: =SUM(E14:E16) -> 36710.172 | F18: =SUM(F14:F16) -> 46553.961 | G18: =SUM(G14:G16) -> 57035.076 | H18: =SUM(H14:H16) -> 69532.427 | I18: =SUM(I14:I16) -> 82928.192 | J18: =SUM(J14:J16) -> 99500.81 | K18: =SUM(K14:K16) -> 117399.24 | ... M18: =SUM(M14:M16) -> 163441.15
B19: -------------- | C19: -------------- | D19: -------------- | E19: -------------- | F19: -------------- | G19: -------------- | H19: -------------- | I19: -------------- | J19: -------------- | K19: -------------- | L19: -------------- | M19: --------------
A20: Operating Income | B20: =+B11-B18 -> 10660.5 | C20: =+C11-C18 -> 17383.6 | D20: =D11-D18 -> 21183.091 | E20: =E11-E18 -> 27829.712 | F20: =F11-F18 -> 35411.691 | G20: =G11-G18 -> 44906.635 | H20: =H11-H18 -> 54836.461 | I20: =I11-I18 -> 66314.474 | J20: =J11-J18 -> 79590.388 | K20: =K11-K18 -> 93928.376 | ... M20: =M11-M18 -> 130811.42
A22: Other Income/(Expense) | B22: =+B8*B71 -> 0 | C22: =+C8*C71 -> 0 | D22: =D71*D8 -> 0 | E22: =E71*E8 -> 0 | F22: =F71*F8 -> 0 | G22: =G71*G8 -> 0 | H22: =H71*H8 -> 0 | I22: =I71*I8 -> 0 | J22: =J71*J8 -> 0 | K22: =K71*K8 -> 0 | ... M22: =M71*M8 -> 0
B23: -------------- | C23: -------------- | D23: -------------- | E23: -------------- | F23: -------------- | G23: -------------- | H23: -------------- | I23: -------------- | J23: -------------- | K23: -------------- | L23: -------------- | M23: --------------
A24: Pretax Income | B24: =+B20+SUM(B22:B23) -> 10660.5 | C24: =+C20+SUM(C22:C23) -> 17383.6 | D24: =SUM(D20:D22) -> 21183.091 | E24: =SUM(E20:E22) -> 27829.712 | F24: =SUM(F20:F22) -> 35411.691 | G24: =SUM(G20:G22) -> 44906.635 | H24: =SUM(H20:H22) -> 54836.461 | I24: =SUM(I20:I22) -> 66314.474 | J24: =SUM(J20:J22) -> 79590.388 | K24: =SUM(K20:K22) -> 93928.376 | ... M24: =SUM(M20:M22) -> 130811.42
A25: Income Taxes | B25: =+B24*B74 -> 1471.149 | C25: =+C24*C74 -> 2868.294 | D25: =D24*D74 -> 3389.2946 | E25: =E24*E74 -> 4452.7538 | F25: =F24*F74 -> 5665.8705 | G25: =G24*G74 -> 7185.0616 | H25: =H24*H74 -> 8773.8338 | I25: =I24*I74 -> 10610.316 | J25: =J24*J74 -> 12734.462 | K25: =K24*K74 -> 15028.54 | ... M25: =M24*M74 -> 20929.827
B26: -------------- | C26: -------------- | D26: -------------- | E26: -------------- | F26: -------------- | G26: -------------- | H26: -------------- | I26: -------------- | J26: -------------- | K26: -------------- | L26: -------------- | M26: --------------
A27: Net Income | B27: =+B24-B25 -> 9189.351 | C27: =+C24-C25 -> 14515.306 | D27: =D24-D25 -> 17793.796 | E27: =E24-E25 -> 23376.958 | F27: =F24-F25 -> 29745.82 | G27: =G24-G25 -> 37721.574 | H27: =H24-H25 -> 46062.627 | I27: =I24-I25 -> 55704.158 | J27: =J24-J25 -> 66855.926 | K27: =K24-K25 -> 78899.836 | ... M27: =M24-M25 -> 109881.59
A29: + Depreciation & Amortization | B29: =B117 -> 1527.3 | C29: =C117 -> 1766.6 | D29: =D117 -> 2101.5598 | E29: =E117 -> 2409.3447 | F29: =F117 -> 2825.9017 | G29: =G117 -> 3338.6698 | H29: =H117 -> 3969.8978 | I29: =I117 -> 4767.7959 | ... M29: =M117 -> 9687.5432
A30: - Capital Expenditures | B30: -3450 | C30: -5060 | D30: =-D8*D80 -> -7134.7637 | E30: =-E8*E80 -> -9275.1928 | F30: =-F8*F80 -> -11779.495 | G30: =-G8*G80 -> -14302.27 | H30: =-H8*H80 -> -17448.769 | I30: =-I8*I80 -> -20493.023 | J30: =-J8*J80 -> -24591.627 | K30: =-K8*K80 -> -29018.12 | ... M30: =-M8*M80 -> -40404.831
A31: - Working Capital Additions | B31: -2228.9 | C31: -4077.5 | D31: =(C8-D8)*$B$82 -> -2738.5962 | E31: =(D8-E8)*$B$82 -> -3389.0127 | F31: =(E8-F8)*$B$82 -> -3965.1449 | G31: =(F8-G8)*$B$82 -> -4476.208 | H31: =(G8-H8)*$B$82 -> -5087.9565 | I31: =(H8-I8)*$B$82 -> -5643.0063 | J31: =(I8-J8)*$B$82 -> -6771.6075 | K31: =(J8-K8)*$B$82 -> -7313.3361 | ... M31: =(L8-M8)*$B$82 -> -10183.089
B32: -------------- | C32: -------------- | D32: -------------- | E32: -------------- | F32: -------------- | G32: -------------- | H32: -------------- | I32: -------------- | J32: -------------- | K32: -------------- | L32: -------------- | M32: --------------
A33: Free Cash Flow | B33: =+B27+SUM(B29:B32) -> 5037.751 | C33: =+C27+SUM(C29:C32) -> 7144.406 | D33: =(D27+SUM(D29:D31))*0.75 -> 7516.4973 | E33: =E27+SUM(E29:E31) -> 13122.097 | F33: =F27+SUM(F29:F31) -> 16827.082 | G33: =G27+SUM(G29:G31) -> 22281.765 | H33: =H27+SUM(H29:H31) -> 27495.799 | I33: =I27+SUM(I29:I31) -> 34335.925 | J33: =J27+SUM(J29:J31) -> 41191.53 | K33: =K27+SUM(K29:K31) -> 49375.32 | L33: =L27+SUM(L29:L31) -> 58364.504 | M33: =M27+SUM(M29:M31) -> 68981.213 | N33: =M27*(1-0.01/0.1846)/(B92-0.01) -> 1517169.9
A34: Present Value Factor | D34: =1/(1+$B$92)^(D93/12) -> 0.99059785 | E34: =1/(1+$B$92)^(E93/12) -> 0.94489659 | F34: =1/(1+$B$92)^(F93/12) -> 0.87611946 | G34: =1/(1+$B$92)^(G93/12) -> 0.81234848 | H34: =1/(1+$B$92)^(H93/12) -> 0.75321927 | I34: =1/(1+$B$92)^(I93/12) -> 0.69839394 | J34: =1/(1+$B$92)^(J93/12) -> 0.64755925 | K34: =1/(1+$B$92)^(K93/12) -> 0.60042471 | ... N34: =1/(1+$B$92)^(N93/12) -> 0.49705697
D35: -------------- | E35: -------------- | F35: -------------- | G35: -------------- | H35: -------------- | I35: -------------- | J35: -------------- | K35: -------------- | L35: -------------- | M35: -------------- | N35: --------------
A36: PV Free Cash Flow | D36: =D33*D34 -> 7445.8261 | E36: =E33*E34 -> 12399.025 | F36: =+F33*F34 -> 14742.534 | G36: =+G33*G34 -> 18100.558 | H36: =+H33*H34 -> 20710.366 | I36: =+I33*I34 -> 23980.002 | J36: =+J33*J34 -> 26673.956 | K36: =+K33*K34 -> 29646.162 | L36: =+L33*L34 -> 32492.745 | M36: =+M33*M34 -> 35607.991 | N36: =+N33*N34 -> 754119.89
D37: --------------
A38: Value of Firm | D38: =SUM(D36:N36) -> 975919.05
A39: Less: Debt Outstanding | D39: -34910.6
A40: Plus: Cash | D40: 3433.5
D41: --------------
A42: Equity Value | D42: =SUM(D38:D40) -> 944441.95
A43: Shares Outstanding | D43: 902.5
D44: --------------
A45: Value Per Share | D45: =D42/D43 -> 1046.4731
D46: ========
A48: Share Price (2/12/25) | D48: 820
A50: Eli Lilly
A51: Discounted Cash Flow Analysis
A52: For the Years Ended
A53: Assumptions
B55: =2023 -> 2023 | C55: =+B55+1 -> 2024 | D55: =+C55+1 -> 2025 | E55: =+D55+1 -> 2026 | F55: =+E55+1 -> 2027 | G55: =+F55+1 -> 2028 | H55: =+G55+1 -> 2029 | I55: =+H55+1 -> 2030 | J55: =+I55+1 -> 2031 | ... M55: =+L55+1 -> 2034
B56: -------------- | C56: -------------- | D56: -------------- | E56: -------------- | F56: -------------- | G56: -------------- | H56: -------------- | I56: -------------- | J56: -------------- | K56: -------------- | L56: -------------- | M56: --------------
A57: Revenue Growth | B57: 0.2 | C57: =+C8/B8-1 -> 0.31996354 | D57: =Assumption!D8 -> 0.32 | E57: =Assumption!E8 -> 0.3 | F57: =Assumption!F8 -> 0.27 | G57: =Assumption!G8 -> 0.24 | H57: =Assumption!H8 -> 0.22 | I57: =Assumption!I8 -> 0.2 | J57: =Assumption!J8 -> 0.2 | K57: =Assumption!K8 -> 0.18 | ... M57: =Assumption!M8 -> 0.18
A58: Cost of Goods Sold | B58: =+B9/B8 -> 0.19270781 | C58: =+C9/C8 -> 0.17461431 | D58: =Assumption!D14 -> 0.1675 | E58: =Assumption!E14 -> 0.165 | F58: =Assumption!F14 -> 0.165 | G58: =Assumption!G14 -> 0.1625 | H58: =Assumption!H14 -> 0.1625 | I58: =Assumption!I14 -> 0.1625 | J58: =Assumption!J14 -> 0.1625 | K58: =Assumption!K14 -> 0.1625 | ... M58: =Assumption!M14 -> 0.1625
B59: -------------- | C59: -------------- | D59: -------------- | E59: -------------- | F59: -------------- | G59: -------------- | H59: -------------- | I59: -------------- | J59: -------------- | K59: -------------- | L59: -------------- | M59: --------------
A60: Gross Margin | B60: =+B11/B8 -> 0.80729219 | C60: =+C11/C8 -> 0.82538569 | D60: =Assumption!D13 -> 0.8325 | E60: =Assumption!E13 -> 0.835 | F60: =Assumption!F13 -> 0.835 | G60: =Assumption!G13 -> 0.8375 | H60: =Assumption!H13 -> 0.8375 | I60: =Assumption!I13 -> 0.8375 | J60: =Assumption!J13 -> 0.8375 | K60: =Assumption!K13 -> 0.8375 | ... M60: =Assumption!M13 -> 0.8375
A62: Operating Expenses:
A63: SG&A | B63: =B14/B8 -> 0.21694575 | C63: =C14/C8 -> 0.19079229 | D63: =Assumption!D22 -> 0.2075 | E63: =Assumption!E22 -> 0.2075 | F63: =Assumption!F22 -> 0.2075 | G63: =Assumption!G22 -> 0.205 | H63: =Assumption!H22 -> 0.205 | I63: =Assumption!I22 -> 0.2025 | J63: =Assumption!J22 -> 0.2025 | K63: =Assumption!K22 -> 0.2025 | ... M63: =Assumption!M22 -> 0.2025
A64: R&D | B64: =B15/B8 -> 0.27292654 | C64: =C15/C8 -> 0.24400402 | D64: =Assumption!D27 -> 0.265 | E64: =Assumption!E27 -> 0.265 | F64: =Assumption!F27 -> 0.265 | G64: =Assumption!G27 -> 0.2625 | H64: =Assumption!H27 -> 0.2625 | I64: =Assumption!I27 -> 0.2625 | J64: =Assumption!J27 -> 0.2625 | K64: =Assumption!K27 -> 0.2625 | ... M64: =Assumption!M27 -> 0.2625
A65: Lease | B65: =+D16/B8 -> 0.0064822032 | C65: =+E16/C8 -> 0.0041982386 | D65: =+F16/D8 -> 0.0028962417 | E65: =+G16/E8 -> 0.0016857871 | F65: =+H16/F8 -> 0.0011063293 | G65: =+I16/G8 -> 0.00053482769 | H65: =+J16/H8 -> 0.00043838335 | I65: =+K16/I8 -> 0.00036531946 | ... M65: =+O16/M8 -> 0
B66: -------------- | C66: -------------- | D66: -------------- | E66: -------------- | F66: -------------- | G66: -------------- | H66: -------------- | I66: -------------- | J66: -------------- | K66: -------------- | L66: -------------- | M66: --------------
A67: Total Operating Expenses | B67: =+B18/B8 -> 0.49488926 | C67: =+C18/C8 -> 0.43944968 | D67: =+D18/D8 -> 0.47622038 | E67: =+E18/E8 -> 0.47494653 | F67: =+F18/F8 -> 0.47425423 | G67: =+G18/G8 -> 0.46857048 | H67: =+H18/H8 -> 0.46823131 | I67: =+I18/I8 -> 0.46536532 | ... M67: =+M18/M8 -> 0.46518529
B68: -------------- | C68: -------------- | D68: -------------- | E68: -------------- | F68: -------------- | G68: -------------- | H68: -------------- | I68: -------------- | J68: -------------- | K68: -------------- | L68: -------------- | M68: --------------
A69: Operating Income | B69: =+B20/B8 -> 0.31240293 | C69: =+C20/C8 -> 0.38593601 | D69: =D20/D11 -> 0.42796351 | E69: =E20/E11 -> 0.43120177 | F69: =F20/F11 -> 0.43203086 | G69: =G20/G11 -> 0.44051286 | H69: =H20/H11 -> 0.44091784 | I69: =I20/I11 -> 0.44433992 | J69: =J20/J11 -> 0.44441262 | K69: =K20/K11 -> 0.44446807 | ... M69: =M20/M11 -> 0.44455488
A71: Other Income/(Expense) | B71: 0 | C71: 0 | D71: =Assumption!D38 -> 0 | E71: =Assumption!E38 -> 0 | F71: =Assumption!F38 -> 0 | G71: =Assumption!G38 -> 0 | H71: =Assumption!H38 -> 0 | I71: =Assumption!I38 -> 0 | J71: =Assumption!J38 -> 0 | K71: =Assumption!K38 -> 0 | ... M71: =Assumption!M38 -> 0
B72: -------------- | C72: -------------- | D72: -------------- | E72: -------------- | F72: -------------- | G72: -------------- | H72: -------------- | I72: -------------- | J72: -------------- | K72: -------------- | L72: -------------- | M72: --------------
A73: Pretax Income | B73: =+B24/B8 -> 0.31240293 | C73: =+C24/C8 -> 0.38593601 | D73: =D24/D8 -> 0.35627962 | E73: =E24/E8 -> 0.36005347 | F73: =F24/F8 -> 0.36074577 | G73: =G24/G8 -> 0.36892952 | H73: =H24/H8 -> 0.36926869 | I73: =I24/I8 -> 0.37213468 | J73: =J24/J8 -> 0.37219557 | K73: =K24/K8 -> 0.37224201 | ... M73: =M24/M8 -> 0.37231471
A74: Income Tax Rate | B74: 0.138 | C74: 0.165 | D74: 0.16 | E74: 0.16 | F74: 0.16 | G74: 0.16 | H74: 0.16 | I74: 0.16 | J74: 0.16 | K74: 0.16 | L74: 0.16 | M74: 0.16
B75: -------------- | C75: -------------- | D75: -------------- | E75: -------------- | F75: -------------- | G75: -------------- | H75: -------------- | I75: -------------- | J75: -------------- | K75: -------------- | L75: -------------- | M75: --------------
A76: Net Income | B76: =+B27/B8 -> 0.26929132 | C76: =+C27/C8 -> 0.32225657 | D76: =D27/D8 -> 0.29927488 | E76: =E27/E8 -> 0.30244492 | F76: =F27/F8 -> 0.30302644 | G76: =G27/G8 -> 0.3099008 | H76: =H27/H8 -> 0.3101857 | I76: =I27/I8 -> 0.31259313 | J76: =J27/J8 -> 0.31264428 | K76: =K27/K8 -> 0.31268329 | ... M76: =M27/M8 -> 0.31274436
A78: Net PP&E | B78: 12913.6 | C78: 17102.4 | D78: =C78-D114-D30 -> 22636.204 | E78: =D78-E114-E30 -> 29992.052 | F78: =E78-F114-F30 -> 39433.645 | G78: =F78-G114-G30 -> 50878.545 | H78: =G78-H114-H30 -> 64824.617 | I78: =H78-I114-I30 -> 81047.844 | J78: =I78-J114-J30 -> 100438.63 | K78: =J78-K114-K30 -> 123147.81 | ... M78: =L78-M114-M30 -> 180978.51
A79: Revenue/Net PP&E | B79: =+B8/B78 -> 2.6425009 | C79: =+C8/C78 -> 2.6337064 | D79: =D8/D78 -> 2.6266049 | E79: =E8/E78 -> 2.5771252 | F79: =F8/F78 -> 2.4893072 | G79: =G8/G78 -> 2.3923924 | H79: =H8/H78 -> 2.290799 | I79: =I8/I78 -> 2.1987038 | J79: =J8/J78 -> 2.1290636 | K79: =K8/K78 -> 2.0490131 | ... M79: =M8/M78 -> 1.9413706
A80: Capital Expenditure % of Rev | B80: =-B30/B8 -> 0.10110127 | C80: =-C30/C8 -> 0.11233785 | D80: =Assumption!D33 -> 0.12 | E80: =Assumption!E33 -> 0.12 | F80: =Assumption!F33 -> 0.12 | G80: =Assumption!G33 -> 0.1175 | H80: =Assumption!H33 -> 0.1175 | I80: =Assumption!I33 -> 0.115 | J80: =Assumption!J33 -> 0.115 | K80: =Assumption!K33 -> 0.115 | ... M80: =Assumption!M33 -> 0.115
A81: Depreciation/Revenue | B81: =+B114/B8 -> 0.029940629 | C81: =+C114/C8 -> 0.026945543 | D81: =D114/D8 -> 0.026926634 | E81: =E114/E8 -> 0.024831976 | F81: =F114/F8 -> 0.023816659 | G81: =G114/G8 -> 0.023474662 | H81: =H114/H8 -> 0.023587164 | I81: =I114/I8 -> 0.023960669 | J81: =J114/J8 -> 0.024321139 | K81: =K114/K8 -> 0.025002589 | ... M81: =M114/M8 -> 0.026155226
A82: Working Capital/Revenue | B82: 0.19
A84: Discount Rate:
A85: Risk-Free Rate | B85: 0.043
A86: Risk Premium | B86: 0.047
A87: Beta | B87: 0.8
A88: K(e) | B88: =B85+B87*B86 -> 0.0806
A89: K(d) | B89: 0.046
A90: Tax Rate | B90: 0.16
A91: Debt/Capital | B91: 0.05
A92: WACC | B92: =(B89*(1-B90)*B91+B88*(1-B91)) -> 0.078502
B93: 0 | C93: 0 | D93: 1.5 | E93: 9 | F93: =+E93+12 -> 21 | G93: =+F93+12 -> 33 | H93: =+G93+12 -> 45 | I93: =+H93+12 -> 57 | J93: =+I93+12 -> 69 | K93: =+J93+12 -> 81 | L93: =+K93+12 -> 93 | M93: =+L93+12 -> 105 | N93: =+M93+6 -> 111
A95: Eli Lilly
A96: Discounted Cash Flow Analysis
A97: For the Years Ended
A98: Depreciation Schedule
B100: =2023 -> 2023 | C100: =+B100+1 -> 2024 | D100: =+C100+1 -> 2025 | E100: =+D100+1 -> 2026 | F100: =+E100+1 -> 2027 | G100: =+F100+1 -> 2028 | H100: =+G100+1 -> 2029 | I100: =+H100+1 -> 2030 | J100: =+I100+1 -> 2031 | ... M100: =+L100+1 -> 2034
B101: -------------- | C101: -------------- | D101: -------------- | E101: -------------- | F101: -------------- | G101: -------------- | H101: -------------- | I101: -------------- | J101: -------------- | K101: -------------- | L101: -------------- | M101: --------------
A102: 2024 Net PP&E | D102: =$C$78*(2050-D100)/325 -> 1315.5692 | E102: =$C$78*(2050-E100)/325 -> 1262.9465 | F102: =$C$78*(2050-F100)/325 -> 1210.3237 | G102: =$C$78*(2050-G100)/325 -> 1157.7009 | H102: =$C$78*(2050-H100)/325 -> 1105.0782 | I102: =$C$78*(2050-I100)/325 -> 1052.4554 | J102: =$C$78*(2050-J100)/325 -> 999.83262 | K102: =$C$78*(2050-K100)/325 -> 947.20985 | ... M102: =$C$78*(2050-M100)/325 -> 841.96431
A103: 2025 Capital Expenditures | D103: =-$D$30/25 -> 285.39055 | E103: =-$D$30/25 -> 285.39055 | F103: =-$D$30/25 -> 285.39055 | G103: =-$D$30/25 -> 285.39055 | H103: =-$D$30/25 -> 285.39055 | I103: =-$D$30/25 -> 285.39055 | J103: =-$D$30/25 -> 285.39055 | K103: =-$D$30/25 -> 285.39055 | ... M103: =-$D$30/25 -> 285.39055
A104: 2026 Capital Expenditures | E104: =-$E$30/25 -> 371.00771 | F104: =-$E$30/25 -> 371.00771 | G104: =-$E$30/25 -> 371.00771 | H104: =-$E$30/25 -> 371.00771 | I104: =-$E$30/25 -> 371.00771 | J104: =-$E$30/25 -> 371.00771 | K104: =-$E$30/25 -> 371.00771 | L104: =-$E$30/25 -> 371.00771 | M104: =-$E$30/25 -> 371.00771
A105: 2027 Capital Expenditures | F105: =-$F$30/25 -> 471.17979 | G105: =-$F$30/25 -> 471.17979 | H105: =-$F$30/25 -> 471.17979 | I105: =-$F$30/25 -> 471.17979 | J105: =-$F$30/25 -> 471.17979 | K105: =-$F$30/25 -> 471.17979 | L105: =-$F$30/25 -> 471.17979 | M105: =-$F$30/25 -> 471.17979
A106: 2028 Capital Expenditures | G106: =-$G$30/25 -> 572.0908 | H106: =-$G$30/25 -> 572.0908 | I106: =-$G$30/25 -> 572.0908 | J106: =-$G$30/25 -> 572.0908 | K106: =-$G$30/25 -> 572.0908 | L106: =-$G$30/25 -> 572.0908 | M106: =-$G$30/25 -> 572.0908
A107: 2029 Capital Expenditures | H107: =-$H$30/25 -> 697.95078 | I107: =-$H$30/25 -> 697.95078 | J107: =-$H$30/25 -> 697.95078 | K107: =-$H$30/25 -> 697.95078 | L107: =-$H$30/25 -> 697.95078 | M107: =-$H$30/25 -> 697.95078
A108: 2030 Capital Expenditures | I108: =-$I$30/25 -> 819.72091 | J108: =-$I$30/25 -> 819.72091 | K108: =-$I$30/25 -> 819.72091 | L108: =-$I$30/25 -> 819.72091 | M108: =-$I$30/25 -> 819.72091
A109: 2031 Capital Expenditures | J109: =-$J$30/25 -> 983.66509 | K109: =-$J$30/25 -> 983.66509 | L109: =-$J$30/25 -> 983.66509 | M109: =-$J$30/25 -> 983.66509
A110: 2032 Capital Expenditures | K110: =-$K$30/25 -> 1160.7248 | L110: =-$K$30/25 -> 1160.7248 | M110: =-$K$30/25 -> 1160.7248
A111: 2033 Capital Expenditures | L111: =-$L$30/25 -> 1369.6553 | M111: =-$L$30/25 -> 1369.6553
A112: 2034 Capital Expenditures | M112: =-$M$30/25 -> 1616.1932
...
