Workbook
Name CashBalRepay: Summary!$R$17
Name CashSweep: Summary!$R$18
Name Cost_of_Sales: '[1]Naming & Data Tables'!$C$9
Name Current_Sales: '[1]Naming & Data Tables'!$C$4
Name EntryMultiple: RetAnalysis!$E$6
Name FinStructure: Summary!$R$15
Name Forecast_Sales: '[1]Naming & Data Tables'!$C$8
Name Gross_Margin: '[1]Naming & Data Tables'!$C$6
Name Gross_Profit: '[1]Naming & Data Tables'!$C$10
Name IQ_CH: 110000
Name IQ_CQ: 5000
Name IQ_CY: 10000
Name IQ_DAILY: 500000
Name IQ_FH: 100000
Name IQ_FQ: 500
Name IQ_FY: 1000
Name IQ_LTM: 2000
Name IQ_MONTH: 15000
Name IQ_NTM: 6000
Name IQ_WEEK: 50000
Name IQ_YTD: 3000
Name OpScenario: Summary!$R$16
Name Sales_Growth_Rate: '[1]Naming & Data Tables'!$C$5

Sheet Summary
B2: LBO Analysis
B3: ($ in millions, fiscal year ending December 31)
B5: Transaction Summary
B6: Sources of Funds | I6: Uses of Funds | M6: Purchase Price | P6: Returns Analysis
E7: % of Total | F7: Multiple of EBITDA | L7: % of Total | M7: Equity Purchase Price | O7: =Financing!N14 -> 5448.4417 | P7: Exit Year | R7: =RetAnalysis!K5 -> 2029
D8: Amount | E8: Sources | F8: =G26 -> 45565 | G8: Cumulative | H8: Pricing | K8: Amount | L8: Uses | M8: Plus: Existing Debt | O8: =-Financing!N10 -> 1500 | P8: Entry Multiple | R8: =RetAnalysis!E6 -> 10.5
B9: Revolver | D9: {=INDEX(Financing!D9:H9,,FinStructure)} -> 0 | E9: =IF(ISERROR(D9/$D$21),0,D9/$D$21) -> 0 | F9: =IF(ISERROR(D9/$G$33),0,D9/$G$33) -> 0 | G9: =F9 -> 0 | H9: =DebtSched!E18*10000 -> 350 | I9: Purchase Target Equity | K9: {=INDEX(Financing!D22:H22,,FinStructure)} -> 5448.4417 | L9: =IF(ISERROR(K9/$K$21),0,K9/$K$21) -> 0.76325365 | M9: Plus: Noncontrolling Interest | O9: =Financing!N12 -> 0 | P9: Exit Multiple | R9: =RetAnalysis!E9 -> 10.5
B10: Term Loan A | D10: {=INDEX(Financing!D10:H10,,FinStructure)} -> 500 | E10: =IF(ISERROR(D10/$D$21),0,D10/$D$21) -> 0.070043299 | F10: =IF(ISERROR(D10/$G$33),0,D10/$G$33) -> 0.78376438 | G10: =F10+G9 -> 0.78376438 | H10: =DebtSched!E34*10000 -> 350 | I10: Repay Existing Term Loan | K10: {=INDEX(Financing!D23:H23,,FinStructure)} -> 1000 | L10: =IF(ISERROR(K10/$K$21),0,K10/$K$21) -> 0.1400866 | M10: Plus: Preferred Equity | O10: =Financing!N11 -> 0 | P10: IRR | R10: =RetAnalysis!K41 -> 0.19239375
B11: Term Loan B | D11: {=INDEX(Financing!D11:H11,,FinStructure)} -> 2000 | E11: =IF(ISERROR(D11/$D$21),0,D11/$D$21) -> 0.28017319 | F11: =IF(ISERROR(D11/$G$33),0,D11/$G$33) -> 3.1350575 | G11: =F11+G10 -> 3.9188219 | H11: =DebtSched!E49*10000 -> 375 | I11: Repay Existing Senior Notes | K11: {=INDEX(Financing!D24:H24,,FinStructure)} -> 500 | L11: =IF(ISERROR(K11/$K$21),0,K11/$K$21) -> 0.070043299 | M11: Less: Cash and Equivalents | O11: =-Financing!N13 -> -250 | P11: Cash Return | R11: =RetAnalysis!K26 -> 2.4104518
B12: 2nd Lien | D12: {=INDEX(Financing!D12:H12,,FinStructure)} -> 300 | E12: =IF(ISERROR(D12/$D$21),0,D12/$D$21) -> 0.042025979 | F12: =IF(ISERROR(D12/$G$33),0,D12/$G$33) -> 0.47025863 | G12: =F12+G11 -> 4.3890806 | H12: =DebtSched!E64*10000 -> 450 | I12: Tender / Call Premiums | K12: {=INDEX(Financing!D25:H25,,FinStructure)} -> 20 | L12: =IF(ISERROR(K12/$K$21),0,K12/$K$21) -> 0.0028017319 | M12: Enterprise Value | O12: =SUM(O7:O11) -> 6698.4417
B13: Senior Notes | D13: {=INDEX(Financing!D13:H13,,FinStructure)} -> 1000 | E13: =IF(ISERROR(D13/$D$21),0,D13/$D$21) -> 0.1400866 | F13: =IF(ISERROR(D13/$G$33),0,D13/$G$33) -> 1.5675288 | G13: =F13+G12 -> 5.9566093 | H13: =DebtSched!E78 -> 0.0875 | I13: Financing Fees | K13: {=INDEX(Financing!D26:H26,,FinStructure)} -> 140 | L13: =IF(ISERROR(K13/$K$21),0,K13/$K$21) -> 0.019612124
B14: Senior Subordinated Notes | D14: {=INDEX(Financing!D14:H14,,FinStructure)} -> 1000 | E14: =IF(ISERROR(D14/$D$21),0,D14/$D$21) -> 0.1400866 | F14: =IF(ISERROR(D14/$G$33),0,D14/$G$33) -> 1.5675288 | G14: =F14+G13 -> 7.5241381 | H14: =DebtSched!E89 -> 0.09 | I14: Other Fees and Expenses | K14: {=INDEX(Financing!D27:H27,,FinStructure)} -> 30 | L14: =IF(ISERROR(K14/$K$21),0,K14/$K$21) -> 0.0042025979 | M14: Transaction Multiples | P14: Settings
B15: Equity Contribution | D15: {=INDEX(Financing!D15:H15,,FinStructure)} -> 2088.4417 | E15: =IF(ISERROR(D15/$D$21),0,D15/$D$21) -> 0.29256268 | F15: =IF(ISERROR(D15/$G$33),0,D15/$G$33) -> 3.2736924 | G15: =F15+G14 -> 10.79783 | M15: Enterprise Value / Sales | P15: Financing Structure | R15: 3
B16: Cash on Hand | D16: {=INDEX(Financing!D16:H16,,FinStructure)} -> 250 | E16: =IF(ISERROR(D16/$D$21),0,D16/$D$21) -> 0.035021649 | F16: =IF(ISERROR(D16/$G$33),0,D16/$G$33) -> 0.39188219 | G16: =F16+G15 -> 11.189713 | M16: =" LTM "&TEXT(G26,"mm/dd/yyyy") -> LTM 09/30/2024 | N16: =G27 -> 3200 | O16: =IF(ISERROR($O$12/N16),0,$O$12/N16) -> 2.093263 | P16: Operating Scenario | R16: =RetAnalysis!D65 -> 1
E17: =IF(ISERROR(D17/$D$21),0,D17/$D$21) -> 0 | F17: =IF(ISERROR(D17/$G$33),0,D17/$G$33) -> 0 | G17: =F17+G16 -> 11.189713 | M17: =" "&H26&"E" -> 2024E | N17: =H27 -> 3238.4 | O17: =IF(ISERROR($O$12/N17),0,$O$12/N17) -> 2.0684417 | P17: Cash Balance | R17: 1 | S17: *Cash balance indicates whether cash balance should be used to make optional repayments
E18: =IF(ISERROR(D18/$D$21),0,D18/$D$21) -> 0 | F18: =IF(ISERROR(D18/$G$33),0,D18/$G$33) -> 0 | G18: =F18+G17 -> 11.189713 | M18: Enterprise Value / EBITDA | P18: Cash Flow Sweep | R18: 1 | S18: *Cash sweep indicates whether to use available cash to make optional repayments
E19: =IF(ISERROR(D19/$D$21),0,D19/$D$21) -> 0 | F19: =IF(ISERROR(D19/$G$33),0,D19/$G$33) -> 0 | G19: =F19+G18 -> 11.189713 | M19: =M16 -> LTM 09/30/2024 | N19: =G33 -> 637.94682 | O19: =IF(ISERROR($O$12/N19),0,$O$12/N19) -> 10.5
E20: =IF(ISERROR(D20/$D$21),0,D20/$D$21) -> 0 | F20: =IF(ISERROR(D20/$G$33),0,D20/$G$33) -> 0 | G20: =F20+G19 -> 11.189713 | M20: =M17 -> 2024E | N20: =H33 -> 650.72629 | O20: =IF(ISERROR($O$12/N20),0,$O$12/N20) -> 10.293793
B21: Total Sources | D21: =SUM(D9:D20) -> 7138.4417 | E21: =SUM(E9:E20) -> 1 | F21: =SUM(F9:F20) -> 11.189713 | G21: =IF(ISERROR(D21/G33),0,D21/G33) -> 11.189713 | I21: Total Uses | K21: =SUM(K9:K20) -> 7138.4417 | L21: =SUM(L9:L20) -> 1
B23: Transaction Summary
D24: Historical Period | I24: Projection Period
G25: LTM | H25: Pro forma | I25: 1 | J25: =I25+1 -> 2 | K25: =J25+1 -> 3 | L25: =K25+1 -> 4 | M25: =L25+1 -> 5 | N25: =M25+1 -> 6 | O25: =N25+1 -> 7 | P25: =O25+1 -> 8 | Q25: =P25+1 -> 9 | R25: =Q25+1 -> 10
D26: =E26-1 -> 2021 | E26: =F26-1 -> 2022 | F26: =H26-1 -> 2023 | G26: 45565 | H26: =YEAR(G26) -> 2024 | I26: =$H$26+I25 -> 2025 | J26: =$H$26+J25 -> 2026 | K26: =$H$26+K25 -> 2027 | L26: =$H$26+L25 -> 2028 | M26: =$H$26+M25 -> 2029 | N26: =$H$26+N25 -> 2030 | O26: =$H$26+O25 -> 2031 | P26: =$H$26+P25 -> 2032 | ... R26: =$H$26+R25 -> 2034
B27: Sales | D27: =IncStmt!E6 -> 2520 | E27: =IncStmt!F6 -> 2780 | F27: =IncStmt!G6 -> 3070 | G27: =IncStmt!H6 -> 3200 | H27: =IncStmt!I6 -> 3238.4 | I27: =IncStmt!J6 -> 3335.552 | J27: =IncStmt!K6 -> 3418.9408 | K27: =IncStmt!L6 -> 3555.6984 | ... R27: =IncStmt!S6 -> 4567.55
B28: % growth | D28: =IncStmt!E7 -> NA | E28: =IncStmt!F7 -> 0.1031746 | F28: =IncStmt!G7 -> 0.10431655 | G28: =IncStmt!H7 -> NA | H28: =IncStmt!I7 -> 0.05485342 | I28: =IncStmt!J7 -> 0.03 | J28: =IncStmt!K7 -> 0.025 | K28: =IncStmt!L7 -> 0.04 | ... R28: =IncStmt!S7 -> 0.035
B30: Gross Profit | D30: =IncStmt!E10 -> 957.6 | E30: =IncStmt!F10 -> 1084.2 | F30: =IncStmt!G10 -> 1228 | G30: =IncStmt!H10 -> 1258.1832 | H30: =IncStmt!I10 -> 1277.165 | I30: =IncStmt!J10 -> 1334.2208 | J30: =IncStmt!K10 -> 1367.5763 | K30: =IncStmt!L10 -> 1422.2794 | ... R30: =IncStmt!S10 -> 1827.02
B31: % margin | D31: =IncStmt!E11 -> 0.38 | E31: =IncStmt!F11 -> 0.39 | F31: =IncStmt!G11 -> 0.4 | G31: =IncStmt!H11 -> 0.39318224 | H31: =IncStmt!I11 -> 0.39438148 | I31: =IncStmt!J11 -> 0.4 | J31: =IncStmt!K11 -> 0.4 | K31: =IncStmt!L11 -> 0.4 | ... R31: =IncStmt!S11 -> 0.4
B33: EBITDA | D33: =IncStmt!E17 -> 476.28 | E33: =IncStmt!F17 -> 556 | F33: =IncStmt!G17 -> 644.7 | G33: =IncStmt!H17 -> 637.94682 | H33: =IncStmt!I17 -> 650.72629 | I33: =IncStmt!J17 -> 733.82144 | J33: =IncStmt!K17 -> 752.16698 | K33: =IncStmt!L17 -> 782.25366 | ... R33: =IncStmt!S17 -> 1004.861
B34: % margin | D34: =IncStmt!E18 -> 0.189 | E34: =IncStmt!F18 -> 0.2 | F34: =IncStmt!G18 -> 0.21 | G34: =IncStmt!H18 -> 0.19935838 | H34: =IncStmt!I18 -> 0.20094068 | I34: =IncStmt!J18 -> 0.22 | J34: =IncStmt!K18 -> 0.22 | K34: =IncStmt!L18 -> 0.22 | ... R34: =IncStmt!S18 -> 0.22
B36: Capital Expenditures | D36: 136.4 | E36: 114 | F36: 144 | G36: 152.3 | H36: 155.3 | I36: =-CFStmt!F24 -> 166.7776 | J36: =-CFStmt!G24 -> 170.94704 | K36: =-CFStmt!H24 -> 177.78492 | L36: =-CFStmt!I24 -> 185.78524 | M36: =-CFStmt!J24 -> 192.28773 | N36: =-CFStmt!K24 -> 199.0178 | O36: =-CFStmt!L24 -> 205.98342 | P36: =-CFStmt!M24 -> 213.19284 | ... R36: =-CFStmt!O24 -> 228.3775
B37: % sales | D37: =IF(ISERROR(D36/D27),0,D36/D27) -> 0.054126984 | E37: =IF(ISERROR(E36/E27),0,E36/E27) -> 0.041007194 | F37: =IF(ISERROR(F36/F27),0,F36/F27) -> 0.046905537 | G37: =IF(ISERROR(G36/G27),0,G36/G27) -> 0.04759375 | H37: =IF(ISERROR(H36/H27),0,H36/H27) -> 0.047955781 | I37: =IF(ISERROR(I36/I27),0,I36/I27) -> 0.05 | J37: =IF(ISERROR(J36/J27),0,J36/J27) -> 0.05 | K37: =IF(ISERROR(K36/K27),0,K36/K27) -> 0.05 | ... R37: =IF(ISERROR(R36/R27),0,R36/R27) -> 0.05
B39: Cash Interest Expense | H39: =IncStmt!I34 -> 426.18427 | I39: =IncStmt!J34 -> 408.46027 | J39: =IncStmt!K34 -> 384.63129 | K39: =IncStmt!L34 -> 358.57525 | L39: =IncStmt!M34 -> 343.70773 | M39: =IncStmt!N34 -> 326.88661 | N39: =IncStmt!O34 -> 307.7182 | O39: =IncStmt!P34 -> 281.71713 | ... R39: =IncStmt!S34 -> 219.76056
B40: Total Interest Expense | H40: =IncStmt!I36 -> 444.44142 | I40: =IncStmt!J36 -> 426.71742 | J40: =IncStmt!K36 -> 402.88843 | K40: =IncStmt!L36 -> 376.83239 | L40: =IncStmt!M36 -> 359.96487 | M40: =IncStmt!N36 -> 343.14375 | N40: =IncStmt!O36 -> 323.97534 | O40: =IncStmt!P36 -> 296.72427 | ... R40: =IncStmt!S36 -> 225.66056
XX1000: 127155

Sheet IncStmt
B1: =Summary!$B$3 -> ($ in millions, fiscal year ending December 31)
B2: Income Statement
E3: Historical Period | J3: Projection Period
H4: LTM | I4: Pro Forma | J4: 1 | K4: =J4+1 -> 2 | L4: =K4+1 -> 3 | M4: =L4+1 -> 4 | N4: =M4+1 -> 5 | O4: =N4+1 -> 6 | P4: =O4+1 -> 7 | Q4: =P4+1 -> 8 | R4: =Q4+1 -> 9 | S4: =R4+1 -> 10
E5: =F5-1 -> 2021 | F5: =G5-1 -> 2022 | G5: =I5-1 -> 2023 | H5: =Summary!G26 -> 45565 | I5: =YEAR($H$5) -> 2024 | J5: =$I$5+J4 -> 2025 | K5: =$I$5+K4 -> 2026 | L5: =$I$5+L4 -> 2027 | M5: =$I$5+M4 -> 2028 | N5: =$I$5+N4 -> 2029 | O5: =$I$5+O4 -> 2030 | P5: =$I$5+P4 -> 2031 | Q5: =$I$5+Q4 -> 2032 | ... S5: =$I$5+S4 -> 2034
B6: Sales | E6: 2520 | F6: 2780 | G6: 3070 | H6: 3200 | I6: =H6*1.012 -> 3238.4 | J6: =I6*(1+J46) -> 3335.552 | K6: =J6*(1+K46) -> 3418.9408 | L6: =K6*(1+L46) -> 3555.6984 | M6: =L6*(1+M46) -> 3715.7049 | N6: =M6*(1+N46) -> 3845.7545 | O6: =N6*(1+O46) -> 3980.3559 | P6: =O6*(1+P46) -> 4119.6684 | Q6: =P6*(1+Q46) -> 4263.8568 | ... S6: =R6*(1+S46) -> 4567.55
B7: % growth | E7: NA | F7: =IF(ISERROR(F6/E6-1),0,F6/E6-1) -> 0.1031746 | G7: =IF(ISERROR(G6/F6-1),0,G6/F6-1) -> 0.10431655 | H7: NA | I7: =IF(ISERROR(I6/G6-1),0,I6/G6-1) -> 0.05485342 | J7: =IF(ISERROR(J6/I6-1),0,J6/I6-1) -> 0.03 | K7: =IF(ISERROR(K6/J6-1),0,K6/J6-1) -> 0.025 | L7: =IF(ISERROR(L6/K6-1),0,L6/K6-1) -> 0.04 | M7: =IF(ISERROR(M6/L6-1),0,M6/L6-1) -> 0.045 | N7: =IF(ISERROR(N6/M6-1),0,N6/M6-1) -> 0.035 | O7: =IF(ISERROR(O6/N6-1),0,O6/N6-1) -> 0.035 | P7: =IF(ISERROR(P6/O6-1),0,P6/O6-1) -> 0.035 | Q7: =IF(ISERROR(Q6/P6-1),0,Q6/P6-1) -> 0.035 | ... S7: =IF(ISERROR(S6/R6-1),0,S6/R6-1) -> 0.035
B9: Cost of Goods Sold | E9: 1562.4 | F9: 1695.8 | G9: 1842 | H9: 1941.8168 | I9: =H9*1.01 -> 1961.235 | J9: =J6*J47 -> 2001.3312 | K9: =K6*K47 -> 2051.3645 | L9: =L6*L47 -> 2133.4191 | M9: =M6*M47 -> 2229.4229 | N9: =N6*N47 -> 2307.4527 | O9: =O6*O47 -> 2388.2136 | P9: =P6*P47 -> 2471.801 | Q9: =Q6*Q47 -> 2558.3141 | ... S9: =S6*S47 -> 2740.53
B10: Gross Profit | E10: =E6-E9 -> 957.6 | F10: =F6-F9 -> 1084.2 | G10: =G6-G9 -> 1228 | H10: =H6-H9 -> 1258.1832 | I10: =I6-I9 -> 1277.165 | J10: =J6-J9 -> 1334.2208 | K10: =K6-K9 -> 1367.5763 | L10: =L6-L9 -> 1422.2794 | ... S10: =S6-S9 -> 1827.02
B11: % margin | E11: =IF(ISERROR(E10/E6),0,E10/E6) -> 0.38 | F11: =IF(ISERROR(F10/F6),0,F10/F6) -> 0.39 | G11: =IF(ISERROR(G10/G6),0,G10/G6) -> 0.4 | H11: =IF(ISERROR(H10/H6),0,H10/H6) -> 0.39318224 | I11: =IF(ISERROR(I10/I6),0,I10/I6) -> 0.39438148 | J11: =IF(ISERROR(J10/J6),0,J10/J6) -> 0.4 | K11: =IF(ISERROR(K10/K6),0,K10/K6) -> 0.4 | L11: =IF(ISERROR(L10/L6),0,L10/L6) -> 0.4 | ... S11: =IF(ISERROR(S10/S6),0,S10/S6) -> 0.4
B13: Selling, General & Administrative | E13: 481.32 | F13: 528.2 | G13: 583.3 | H13: 620.23634 | I13: =H13*1.01 -> 626.4387 | J13: =J6*J48 -> 600.39936 | K13: =K6*K48 -> 615.40934 | L13: =L6*L48 -> 640.02572 | M13: =M6*M48 -> 668.82688 | N13: =N6*N48 -> 692.23582 | O13: =O6*O48 -> 716.46407 | P13: =P6*P48 -> 741.54031 | Q13: =Q6*Q48 -> 767.49422 | ... S13: =S6*S48 -> 822.159
B14: % sales | E14: =IF(ISERROR(E13/E6),0,E13/E6) -> 0.191 | F14: =IF(ISERROR(F13/F6),0,F13/F6) -> 0.19 | G14: =IF(ISERROR(G13/G6),0,G13/G6) -> 0.19 | H14: =IF(ISERROR(H13/H6),0,H13/H6) -> 0.19382386 | I14: =IF(ISERROR(I13/I6),0,I13/I6) -> 0.1934408 | J14: =IF(ISERROR(J13/J6),0,J13/J6) -> 0.18 | K14: =IF(ISERROR(K13/K6),0,K13/K6) -> 0.18 | L14: =IF(ISERROR(L13/L6),0,L13/L6) -> 0.18 | ... S14: =IF(ISERROR(S13/S6),0,S13/S6) -> 0.18
B16: Other Expense / (Income) | E16: 0 | F16: 0 | G16: 0 | H16: 0 | I16: =H16 -> 0 | J16: =J6*J49 -> 0 | K16: =K6*K49 -> 0 | L16: =L6*L49 -> 0 | M16: =M6*M49 -> 0 | N16: =N6*N49 -> 0 | O16: =O6*O49 -> 0 | P16: =P6*P49 -> 0 | Q16: =Q6*Q49 -> 0 | ... S16: =S6*S49 -> 0
B17: EBITDA | E17: =E10-E13-E16 -> 476.28 | F17: =F10-F13-F16 -> 556 | G17: =G10-G13-G16 -> 644.7 | H17: =H10-H13-H16 -> 637.94682 | I17: =I10-I13-I16 -> 650.72629 | J17: =J10-J13-J16 -> 733.82144 | K17: =K10-K13-K16 -> 752.16698 | L17: =L10-L13-L16 -> 782.25366 | ... S17: =S10-S13-S16 -> 1004.861
B18: % margin | E18: =IF(ISERROR(E17/E6),0,E17/E6) -> 0.189 | F18: =IF(ISERROR(F17/F6),0,F17/F6) -> 0.2 | G18: =IF(ISERROR(G17/G6),0,G17/G6) -> 0.21 | H18: =IF(ISERROR(H17/H6),0,H17/H6) -> 0.19935838 | I18: =IF(ISERROR(I17/I6),0,I17/I6) -> 0.20094068 | J18: =IF(ISERROR(J17/J6),0,J17/J6) -> 0.22 | K18: =IF(ISERROR(K17/K6),0,K17/K6) -> 0.22 | L18: =IF(ISERROR(L17/L6),0,L17/L6) -> 0.22 | ... S18: =IF(ISERROR(S17/S6),0,S17/S6) -> 0.22
B20: Depreciation | E20: 114 | F20: 118 | G20: 140 | H20: 145 | I20: =H20 -> 145 | J20: =J6*J50 -> 166.7776 | K20: =K6*K50 -> 170.94704 | L20: =L6*L50 -> 177.78492 | M20: =M6*M50 -> 185.78524 | N20: =N6*N50 -> 192.28773 | O20: =O6*O50 -> 199.0178 | P20: =P6*P50 -> 205.98342 | Q20: =Q6*Q50 -> 213.19284 | ... S20: =S6*S50 -> 228.3775
B21: Amortization | E21: 39 | F21: 42 | G21: 46.5 | H21: 49 | I21: =H21 -> 49 | J21: =J6*J51 -> 66.71104 | K21: =K6*K51 -> 68.378816 | L21: =L6*L51 -> 71.113969 | M21: =M6*M51 -> 74.314097 | N21: =N6*N51 -> 76.915091 | O21: =O6*O51 -> 79.607119 | P21: =P6*P51 -> 82.393368 | Q21: =Q6*Q51 -> 85.277136 | ... S21: =S6*S51 -> 91.351
B22: EBIT | E22: =E17-SUM(E20:E21) -> 323.28 | F22: =F17-SUM(F20:F21) -> 396 | G22: =G17-SUM(G20:G21) -> 458.2 | H22: =H17-SUM(H20:H21) -> 443.94682 | I22: =I17-SUM(I20:I21) -> 456.72629 | J22: =J17-SUM(J20:J21) -> 500.3328 | K22: =K17-SUM(K20:K21) -> 512.84112 | L22: =L17-SUM(L20:L21) -> 533.35476 | ... S22: =S17-SUM(S20:S21) -> 685.1325
B23: % margin | E23: =IF(ISERROR(E22/E6),0,E22/E6) -> 0.12828571 | F23: =IF(ISERROR(F22/F6),0,F22/F6) -> 0.14244604 | G23: =IF(ISERROR(G22/G6),0,G22/G6) -> 0.14925081 | H23: =IF(ISERROR(H22/H6),0,H22/H6) -> 0.13873338 | I23: =IF(ISERROR(I22/I6),0,I22/I6) -> 0.14103455 | J23: =IF(ISERROR(J22/J6),0,J22/J6) -> 0.15 | K23: =IF(ISERROR(K22/K6),0,K22/K6) -> 0.15 | L23: =IF(ISERROR(L22/L6),0,L22/L6) -> 0.15 | ... S23: =IF(ISERROR(S22/S6),0,S22/S6) -> 0.15
B25: Interest Expense
B26: Revolver | I26: =BalSheet!H24*(IF(DebtSched!E$6>DebtSched!E19,DebtSched!E$6,DebtSched!E19)+DebtSched!E18) -> 0 | J26: =DebtSched!F28 -> 0.25474824 | K26: =DebtSched!G28 -> 0.24216808 | L26: =DebtSched!H28 -> 0 | M26: =DebtSched!I28 -> 0 | N26: =DebtSched!J28 -> 0 | O26: =DebtSched!K28 -> 0 | P26: =DebtSched!L28 -> 45.396712 | Q26: =DebtSched!M28 -> 115.2324 | ... S26: =DebtSched!O28 -> 132.06056 | T26: (1 point for entire row)
B27: Term Loan A | I27: =BalSheet!H25*(IF(DebtSched!E$6>DebtSched!E35,DebtSched!E$6,DebtSched!E35)+DebtSched!E34) -> 42.5 | J27: =DebtSched!F45 -> 37.96875 | K27: =DebtSched!G45 -> 31.277345 | L27: =DebtSched!H45 -> 23.875251 | M27: =DebtSched!I45 -> 16.647727 | N27: =DebtSched!J45 -> 6.2688249 | O27: =DebtSched!K45 -> 0 | P27: =DebtSched!L45 -> 0 | Q27: =DebtSched!M45 -> 0 | ... S27: =DebtSched!O45 -> 0 | T27: (1 point for entire row)
B28: Term Loan B | I28: =BalSheet!H26*(IF(DebtSched!E$6>DebtSched!E50,DebtSched!E$6,DebtSched!E50)+DebtSched!E49) -> 175 | J28: =DebtSched!F60 -> 166.165 | K28: =DebtSched!G60 -> 156.615 | L28: =DebtSched!H60 -> 145.275 | M28: =DebtSched!I60 -> 143.785 | N28: =DebtSched!J60 -> 140.41778 | O28: =DebtSched!K60 -> 127.5182 | P28: =DebtSched!L60 -> 58.620417 | Q28: =DebtSched!M60 -> 0 | ... S28: =DebtSched!O60 -> 0 | T28: (1 point for entire row)
B29: 2nd Lien | I29: =BalSheet!H28*(DebtSched!E6+DebtSched!E64) -> 28.5 | J29: =DebtSched!F74 -> 23.8875 | K29: =DebtSched!G74 -> 16.3125 | L29: =DebtSched!H74 -> 9.225 | M29: =DebtSched!I74 -> 3.075 | N29: =DebtSched!J74 -> 0 | O29: =DebtSched!K74 -> 0 | P29: =DebtSched!L74 -> 0 | Q29: =DebtSched!M74 -> 0 | ... S29: =DebtSched!O74 -> 0 | T29: (1 point for entire row)
B30: Senior Notes | I30: =J30 -> 87.5 | J30: =DebtSched!F85 -> 87.5 | K30: =DebtSched!G85 -> 87.5 | L30: =DebtSched!H85 -> 87.5 | M30: =DebtSched!I85 -> 87.5 | N30: =DebtSched!J85 -> 87.5 | O30: =DebtSched!K85 -> 87.5 | P30: =DebtSched!L85 -> 87.5 | Q30: =DebtSched!M85 -> 87.5 | ... S30: =DebtSched!O85 -> 87.5 | T30: (1 point for entire row)
B31: Senior Subordinated Notes | I31: =J31 -> 90 | J31: =DebtSched!F96 -> 90 | K31: =DebtSched!G96 -> 90 | L31: =DebtSched!H96 -> 90 | M31: =DebtSched!I96 -> 90 | N31: =DebtSched!J96 -> 90 | O31: =DebtSched!K96 -> 90 | P31: =DebtSched!L96 -> 90 | Q31: =DebtSched!M96 -> 90 | ... S31: =DebtSched!O96 -> 0 | T31: (1 point for entire row)
B32: Commitment Fee on Unused Revolver | I32: =J32 -> 2.4842748 | J32: =DebtSched!F29 -> 2.4842748 | K32: =DebtSched!G29 -> 2.4842748 | L32: =DebtSched!H29 -> 2.5 | M32: =DebtSched!I29 -> 2.5 | N32: =DebtSched!J29 -> 2.5 | O32: =DebtSched!K29 -> 2.5 | P32: =DebtSched!L29 -> 0 | Q32: =DebtSched!M29 -> 0 | ... S32: =DebtSched!O29 -> 0 | T32: (1 point for entire row)
B33: Administrative Agent Fee | I33: =J33 -> 0.2 | J33: =DebtSched!F30 -> 0.2 | K33: =DebtSched!G30 -> 0.2 | L33: =DebtSched!H30 -> 0.2 | M33: =DebtSched!I30 -> 0.2 | N33: =DebtSched!J30 -> 0.2 | O33: =DebtSched!K30 -> 0.2 | P33: =DebtSched!L30 -> 0.2 | Q33: =DebtSched!M30 -> 0.2 | ... S33: =DebtSched!O30 -> 0.2 | T33: (1 point for entire row)
B34: Cash Interest Expense | I34: =SUM(I26:I33) -> 426.18427 | J34: =SUM(J26:J33) -> 408.46027 | K34: =SUM(K26:K33) -> 384.63129 | L34: =SUM(L26:L33) -> 358.57525 | M34: =SUM(M26:M33) -> 343.70773 | N34: =SUM(N26:N33) -> 326.88661 | O34: =SUM(O26:O33) -> 307.7182 | P34: =SUM(P26:P33) -> 281.71713 | ... S34: =SUM(S26:S33) -> 219.76056 | T34: (1 point for entire row)
B35: Amortization of Deferred Financing Fees | I35: =J35 -> 18.257143 | J35: =Financing!E58 -> 18.257143 | K35: =Financing!F58 -> 18.257143 | L35: =Financing!G58 -> 18.257143 | M35: =Financing!H58 -> 16.257143 | N35: =Financing!I58 -> 16.257143 | O35: =Financing!J58 -> 16.257143 | P35: =Financing!K58 -> 15.007143 | Q35: =Financing!L58 -> 9.65 | ... S35: =Financing!N58 -> 5.9 | T35: (1 point for entire row)
B36: Total Interest Expense | I36: =I34+I35 -> 444.44142 | J36: =SUM(J34:J35) -> 426.71742 | K36: =SUM(K34:K35) -> 402.88843 | L36: =SUM(L34:L35) -> 376.83239 | M36: =SUM(M34:M35) -> 359.96487 | N36: =SUM(N34:N35) -> 343.14375 | O36: =SUM(O34:O35) -> 323.97534 | P36: =SUM(P34:P35) -> 296.72427 | Q36: =SUM(Q34:Q35) -> 302.5824 | ... S36: =SUM(S34:S35) -> 225.66056 | T36: (1 point for entire row)
B37: (Interest Income) | J37: =((CFStmt!F41+CFStmt!F42)/2)*IncStmt!J52 -> 0 | K37: =((CFStmt!G41+CFStmt!G42)/2)*IncStmt!K52 -> 0 | L37: =((CFStmt!H41+CFStmt!H42)/2)*IncStmt!L52 -> 0 | M37: =((CFStmt!I41+CFStmt!I42)/2)*IncStmt!M52 -> 0 | N37: =((CFStmt!J41+CFStmt!J42)/2)*IncStmt!N52 -> 0 | O37: =((CFStmt!K41+CFStmt!K42)/2)*IncStmt!O52 -> 0 | P37: =((CFStmt!L41+CFStmt!L42)/2)*IncStmt!P52 -> 0 | Q37: =((CFStmt!M41+CFStmt!M42)/2)*IncStmt!Q52 -> 0 | ... S37: =((CFStmt!O41+CFStmt!O42)/2)*IncStmt!S52 -> 0 | T37: (1 point for entire row)
B38: Net Interest Expense | J38: =J36-J37 -> 426.71742 | K38: =K36-K37 -> 402.88843 | L38: =L36-L37 -> 376.83239 | M38: =M36-M37 -> 359.96487 | N38: =N36-N37 -> 343.14375 | O38: =O36-O37 -> 323.97534 | P38: =P36-P37 -> 296.72427 | Q38: =Q36-Q37 -> 302.5824 | ... S38: =S36-S37 -> 225.66056 | T38: (1 point for entire row)
B40: Earnings Before Taxes | J40: =J22-J38 -> 73.615384 | K40: =K22-K38 -> 109.95269 | L40: =L22-L38 -> 156.52237 | M40: =M22-M38 -> 197.39086 | N40: =N22-N38 -> 233.71943 | O40: =O22-O38 -> 273.07805 | P40: =P22-P38 -> 321.22599 | Q40: =Q22-Q38 -> 336.99612 | ... S40: =S22-S38 -> 459.47194
B41: Income Taxes | J41: =J40*J53 -> 18.403846 | K41: =K40*K53 -> 27.488172 | L41: =L40*L53 -> 39.130593 | M41: =M40*M53 -> 49.347715 | N41: =N40*N53 -> 58.429857 | O41: =O40*O53 -> 68.269512 | P41: =P40*P53 -> 80.306497 | Q41: =Q40*Q53 -> 84.24903 | ... S41: =S40*S53 -> 114.86799
B42: Net Income | J42: =J40-J41 -> 55.211538 | K42: =K40-K41 -> 82.464517 | L42: =L40-L41 -> 117.39178 | M42: =M40-M41 -> 148.04314 | N42: =N40-N41 -> 175.28957 | O42: =O40-O41 -> 204.80854 | P42: =P40-P41 -> 240.91949 | Q42: =Q40-Q41 -> 252.74709 | ... S42: =S40-S41 -> 344.60396
B43: % margin | J43: =J42/J6 -> 0.016552444 | K43: =K42/K6 -> 0.024119902 | L43: =L42/L6 -> 0.033015111 | M43: =M42/M6 -> 0.039842547 | N43: =N42/N6 -> 0.045580021 | O43: =O42/O6 -> 0.051454829 | P43: =P42/P6 -> 0.058480311 | Q43: =Q42/Q6 -> 0.059276637 | ... S43: =S42/S6 -> 0.075446127
B45: Income Statement Assumptions
B46: Sales (% growth) | E46: NA | F46: =F7 -> 0.1031746 | G46: =G7 -> 0.10431655 | H46: =H7 -> NA | I46: =I7 -> 0.05485342 | J46: =Assumptions1!F8 -> 0.03 | K46: =Assumptions1!G8 -> 0.025 | L46: =Assumptions1!H8 -> 0.04 | M46: =Assumptions1!I8 -> 0.045 | N46: =Assumptions1!J8 -> 0.035 | O46: =Assumptions1!K8 -> 0.035 | P46: =Assumptions1!L8 -> 0.035 | Q46: =Assumptions1!M8 -> 0.035 | ... S46: =Assumptions1!O8 -> 0.035
B47: Cost of Goods Sold (% margin) | E47: =IF(ISERROR(E9/E6),0,E9/E6) -> 0.62 | F47: =IF(ISERROR(F9/F6),0,F9/F6) -> 0.61 | G47: =IF(ISERROR(G9/G6),0,G9/G6) -> 0.6 | H47: =IF(ISERROR(H9/H6),0,H9/H6) -> 0.60681776 | I47: =IF(ISERROR(I9/I6),0,I9/I6) -> 0.60561852 | J47: =Assumptions1!F14 -> 0.6 | K47: =Assumptions1!G14 -> 0.6 | L47: =Assumptions1!H14 -> 0.6 | M47: =Assumptions1!I14 -> 0.6 | N47: =Assumptions1!J14 -> 0.6 | O47: =Assumptions1!K14 -> 0.6 | P47: =Assumptions1!L14 -> 0.6 | Q47: =Assumptions1!M14 -> 0.6 | ... S47: =Assumptions1!O14 -> 0.6
B48: SG&A (% sales) | E48: =IF(ISERROR(E13/E6),0,E13/E6) -> 0.191 | F48: =IF(ISERROR(F13/F6),0,F13/F6) -> 0.19 | G48: =IF(ISERROR(G13/G6),0,G13/G6) -> 0.19 | H48: =IF(ISERROR(H13/H6),0,H13/H6) -> 0.19382386 | I48: =IF(ISERROR(I13/I6),0,I13/I6) -> 0.1934408 | J48: =Assumptions1!F20 -> 0.18 | K48: =Assumptions1!G20 -> 0.18 | L48: =Assumptions1!H20 -> 0.18 | M48: =Assumptions1!I20 -> 0.18 | N48: =Assumptions1!J20 -> 0.18 | O48: =Assumptions1!K20 -> 0.18 | P48: =Assumptions1!L20 -> 0.18 | Q48: =Assumptions1!M20 -> 0.18 | ... S48: =Assumptions1!O20 -> 0.18
B49: Other (Income)/Expense (% sales) | E49: =IF(ISERROR(E16/E6),0,E16/E6) -> 0 | F49: =IF(ISERROR(F16/F6),0,F16/F6) -> 0 | G49: =IF(ISERROR(G16/G6),0,G16/G6) -> 0 | H49: =IF(ISERROR(H16/H6),0,H16/H6) -> 0 | I49: =IF(ISERROR(I16/I6),0,I16/I6) -> 0 | J49: =Assumptions1!F26 -> 0 | K49: =Assumptions1!G26 -> 0 | L49: =Assumptions1!H26 -> 0 | M49: =Assumptions1!I26 -> 0 | N49: =Assumptions1!J26 -> 0 | O49: =Assumptions1!K26 -> 0 | P49: =Assumptions1!L26 -> 0 | Q49: =Assumptions1!M26 -> 0 | ... S49: =Assumptions1!O26 -> 0
B50: Depreciation (% sales) | E50: =IF(ISERROR(E20/$E$6),0,E20/$E$6) -> 0.045238095 | F50: =IF(ISERROR(F20/$E$6),0,F20/$E$6) -> 0.046825397 | G50: =IF(ISERROR(G20/$E$6),0,G20/$E$6) -> 0.055555556 | H50: =IF(ISERROR(H20/$E$6),0,H20/$E$6) -> 0.057539683 | I50: =IF(ISERROR(I20/$E$6),0,I20/$E$6) -> 0.057539683 | J50: =Assumptions1!F32 -> 0.05 | K50: =Assumptions1!G32 -> 0.05 | L50: =Assumptions1!H32 -> 0.05 | M50: =Assumptions1!I32 -> 0.05 | N50: =Assumptions1!J32 -> 0.05 | O50: =Assumptions1!K32 -> 0.05 | P50: =Assumptions1!L32 -> 0.05 | Q50: =Assumptions1!M32 -> 0.05 | ... S50: =Assumptions1!O32 -> 0.05
B51: Amortization (% sales) | E51: =IF(ISERROR(E21/E6),0,E21/E6) -> 0.01547619 | F51: =IF(ISERROR(F21/F6),0,F21/F6) -> 0.015107914 | G51: =IF(ISERROR(G21/G6),0,G21/G6) -> 0.01514658 | H51: =IF(ISERROR(H21/H6),0,H21/H6) -> 0.0153125 | I51: =IF(ISERROR(I21/I6),0,I21/I6) -> 0.015130929 | J51: =Assumptions1!F38 -> 0.02 | K51: =Assumptions1!G38 -> 0.02 | L51: =Assumptions1!H38 -> 0.02 | M51: =Assumptions1!I38 -> 0.02 | N51: =Assumptions1!J38 -> 0.02 | O51: =Assumptions1!K38 -> 0.02 | P51: =Assumptions1!L38 -> 0.02 | Q51: =Assumptions1!M38 -> 0.02 | ... S51: =Assumptions1!O38 -> 0.02
B52: Interest Income | I52: 0.02 | J52: =I52 -> 0.02 | K52: =J52 -> 0.02 | L52: =K52 -> 0.02 | M52: =L52 -> 0.02 | N52: =M52 -> 0.02 | O52: =N52 -> 0.02 | P52: =O52 -> 0.02 | Q52: =P52 -> 0.02 | ... S52: =R52 -> 0.02
B53: Tax Rate | J53: =Assumptions1!S7 -> 0.25 | K53: =J53 -> 0.25 | L53: =K53 -> 0.25 | M53: =L53 -> 0.25 | N53: =M53 -> 0.25 | O53: =N53 -> 0.25 | P53: =O53 -> 0.25 | Q53: =P53 -> 0.25 | R53: =Q53 -> 0.25 | S53: =R53 -> 0.25
XX1000: 127155

Sheet BalSheet
B1: =Summary!$B$3 -> ($ in millions, fiscal year ending December 31)
B2: Balance Sheet
I3: Projection Period
E4: Opening | F4: Adjustments | H4: Pro Forma | I4: 1 | J4: =I4+1 -> 2 | K4: =J4+1 -> 3 | L4: =K4+1 -> 4 | M4: =L4+1 -> 5 | N4: =M4+1 -> 6 | O4: =N4+1 -> 7 | P4: =O4+1 -> 8 | Q4: =P4+1 -> 9 | R4: =Q4+1 -> 10
E5: =H5 -> 2024 | F5: + | G5: - | H5: =IncStmt!I5 -> 2024 | I5: =$H$5+I4 -> 2025 | J5: =$H$5+J4 -> 2026 | K5: =$H$5+K4 -> 2027 | L5: =$H$5+L4 -> 2028 | M5: =$H$5+M4 -> 2029 | N5: =$H$5+N4 -> 2030 | O5: =$H$5+O4 -> 2031 | P5: =$H$5+P4 -> 2032 | ... R5: =$H$5+R4 -> 2034
B6: Cash and Cash Equivalents | E6: 250 | G6: =IF(OR(FinStructure=1,FinStructure=2,FinStructure=3,FinStructure=4),-E6,0) -> -250 | H6: =SUM(E6:G6) -> 0 | I6: =CFStmt!F42 -> 0 | J6: =CFStmt!G42 -> 0 | K6: =CFStmt!H42 -> 0 | L6: =CFStmt!I42 -> 0 | M6: =CFStmt!J42 -> 0 | N6: =CFStmt!K42 -> 0 | O6: =CFStmt!L42 -> 0 | P6: =CFStmt!M42 -> 0 | ... R6: =CFStmt!O42 -> 0
B7: Accounts Receivable | E7: 450 | H7: =SUM(E7:G7) -> 450 | I7: =IncStmt!J6*BalSheet!I50/365 -> 434.99253 | J7: =IncStmt!K6*BalSheet!J50/365 -> 445.86735 | K7: =IncStmt!L6*BalSheet!K50/365 -> 463.70204 | L7: =IncStmt!M6*BalSheet!L50/365 -> 484.56863 | M7: =IncStmt!N6*BalSheet!M50/365 -> 501.52854 | N7: =IncStmt!O6*BalSheet!N50/365 -> 519.08203 | O7: =IncStmt!P6*BalSheet!O50/365 -> 537.24991 | P7: =IncStmt!Q6*BalSheet!P50/365 -> 556.05365 | ... R7: =IncStmt!S6*BalSheet!R50/365 -> 595.65857
B8: Inventories | E8: 600 | H8: =SUM(E8:G8) -> 600 | I8: =IncStmt!J9*BalSheet!I51/365 -> 580.11189 | J8: =IncStmt!K9*BalSheet!J51/365 -> 594.61469 | K8: =IncStmt!L9*BalSheet!K51/365 -> 618.39928 | L8: =IncStmt!M9*BalSheet!L51/365 -> 646.22725 | M8: =IncStmt!N9*BalSheet!M51/365 -> 668.8452 | N8: =IncStmt!O9*BalSheet!N51/365 -> 692.25478 | O8: =IncStmt!P9*BalSheet!O51/365 -> 716.4837 | P8: =IncStmt!Q9*BalSheet!P51/365 -> 741.56063 | ... R8: =IncStmt!S9*BalSheet!R51/365 -> 794.37828
B9: Prepaids and Other Current Assets | E9: 175 | H9: =SUM(E9:G9) -> 175 | I9: =IncStmt!J6*BalSheet!H52 -> 180.25 | J9: =IncStmt!K6*BalSheet!I52 -> 174.36598 | K9: =IncStmt!L6*BalSheet!J52 -> 181.34062 | L9: =IncStmt!M6*BalSheet!K52 -> 189.50095 | M9: =IncStmt!N6*BalSheet!L52 -> 196.13348 | N9: =IncStmt!O6*BalSheet!M52 -> 202.99815 | O9: =IncStmt!P6*BalSheet!N52 -> 210.10309 | P9: =IncStmt!Q6*BalSheet!O52 -> 217.4567 | ... R9: =IncStmt!S6*BalSheet!Q52 -> 232.94505
B10: Total Current Assets | E10: =SUM(E6:E9) -> 1475 | H10: =SUM(H6:H9) -> 1225 | I10: =SUM(I6:I9) -> 1195.3544 | J10: =SUM(J6:J9) -> 1214.848 | K10: =SUM(K6:K9) -> 1263.4419 | L10: =SUM(L6:L9) -> 1320.2968 | M10: =SUM(M6:M9) -> 1366.5072 | N10: =SUM(N6:N9) -> 1414.335 | O10: =SUM(O6:O9) -> 1463.8367 | ... R10: =SUM(R6:R9) -> 1622.9819
B12: Property, Plant, and Equipment, net | E12: 2500 | H12: =SUM(E12:G12) -> 2500 | I12: =H12-CFStmt!F8-CFStmt!F24 -> 2500 | J12: =I12-CFStmt!G8-CFStmt!G24 -> 2500 | K12: =J12-CFStmt!H8-CFStmt!H24 -> 2500 | L12: =K12-CFStmt!I8-CFStmt!I24 -> 2500 | M12: =L12-CFStmt!J8-CFStmt!J24 -> 2500 | N12: =M12-CFStmt!K8-CFStmt!K24 -> 2500 | O12: =N12-CFStmt!L8-CFStmt!L24 -> 2500 | P12: =O12-CFStmt!M8-CFStmt!M24 -> 2500 | ... R12: =Q12-CFStmt!O8-CFStmt!O24 -> 2500
B13: Goodwill | E13: 1000 | F13: =IF(OR(FinStructure=1,FinStructure=2,FinStructure=3,FinStructure=4),Summary!K9 - (BalSheet!E38-BalSheet!E13),0) -> 2948.4417 | G13: =IF(OR(FinStructure=1,FinStructure=2,FinStructure=3,FinStructure=4),-BalSheet!E13,0) -> -1000 | H13: =SUM(E13:G13) -> 2948.4417 | I13: =H13 -> 2948.4417 | J13: =I13 -> 2948.4417 | K13: =J13 -> 2948.4417 | L13: =K13 -> 2948.4417 | M13: =L13 -> 2948.4417 | N13: =M13 -> 2948.4417 | O13: =N13 -> 2948.4417 | P13: =O13 -> 2948.4417 | ... R13: =Q13 -> 2948.4417
B14: Intangible Assets | E14: 875 | H14: =SUM(E14:G14) -> 875 | I14: =H14-IncStmt!J21 -> 808.28896 | J14: =I14-IncStmt!K21 -> 739.91014 | K14: =J14-IncStmt!L21 -> 668.79618 | L14: =K14-IncStmt!M21 -> 594.48208 | M14: =L14-IncStmt!N21 -> 517.56699 | N14: =M14-IncStmt!O21 -> 437.95987 | O14: =N14-IncStmt!P21 -> 355.5665 | P14: =O14-IncStmt!Q21 -> 270.28936 | ... R14: =Q14-IncStmt!S21 -> 90.676529
B15: Other Assets | E15: 150 | H15: =SUM(E15:G15) -> 150 | I15: =H15 -> 150 | J15: =I15 -> 150 | K15: =J15 -> 150 | L15: =K15 -> 150 | M15: =L15 -> 150 | N15: =M15 -> 150 | O15: =N15 -> 150 | P15: =O15 -> 150 | ... R15: =Q15 -> 150
B16: Deferred Financing Fees | E16: 0 | F16: =IF(OR(FinStructure=1,FinStructure=2,FinStructure=3,FinStructure=4),Summary!K13,0) -> 140 | H16: =SUM(E16:G16) -> 140 | I16: =H16-IncStmt!J35 -> 121.74286 | J16: =I16-IncStmt!K35 -> 103.48571 | K16: =J16-IncStmt!L35 -> 85.228571 | L16: =K16-IncStmt!M35 -> 68.971429 | M16: =L16-IncStmt!N35 -> 52.714286 | N16: =M16-IncStmt!O35 -> 36.457143 | O16: =N16-IncStmt!P35 -> 21.45 | P16: =O16-IncStmt!Q35 -> 11.8 | ... R16: =Q16-IncStmt!S35 -> 2.3092639e-14
B17: Total Assets | E17: =E10+SUM(E12:E16) -> 6000 | H17: =H10+SUM(H12:H16) -> 7838.4417 | I17: =I10+SUM(I12:I16) -> 7723.8279 | J17: =J10+SUM(J12:J16) -> 7656.6855 | K17: =K10+SUM(K12:K16) -> 7615.9083 | L17: =L10+SUM(L12:L16) -> 7582.192 | M17: =M10+SUM(M12:M16) -> 7535.2301 | N17: =N10+SUM(N12:N16) -> 7487.1936 | O17: =O10+SUM(O12:O16) -> 7439.2948 | ... R17: =R10+SUM(R12:R16) -> 7312.1001
B19: Accounts Payable | E19: 215 | H19: =SUM(E19:G19) -> 215 | I19: =IncStmt!J9*BalSheet!I55/365 -> 207.80946 | J19: =IncStmt!K9*BalSheet!J55/365 -> 213.0047 | K19: =IncStmt!L9*BalSheet!K55/365 -> 221.52488 | L19: =IncStmt!M9*BalSheet!L55/365 -> 231.4935 | M19: =IncStmt!N9*BalSheet!M55/365 -> 239.59578 | N19: =IncStmt!O9*BalSheet!N55/365 -> 247.98163 | O19: =IncStmt!P9*BalSheet!O55/365 -> 256.66098 | P19: =IncStmt!Q9*BalSheet!P55/365 -> 265.64412 | ... R19: =IncStmt!S9*BalSheet!R55/365 -> 284.56462
B20: Accrued Liabilities | E20: 275 | H20: =SUM(E20:G20) -> 275 | I20: =IncStmt!J6*BalSheet!I56 -> 266.84416 | J20: =IncStmt!K6*BalSheet!J56 -> 273.51526 | K20: =IncStmt!L6*BalSheet!K56 -> 284.45587 | L20: =IncStmt!M6*BalSheet!L56 -> 297.25639 | M20: =IncStmt!N6*BalSheet!M56 -> 307.66036 | N20: =IncStmt!O6*BalSheet!N56 -> 318.42848 | O20: =IncStmt!P6*BalSheet!O56 -> 329.57347 | P20: =IncStmt!Q6*BalSheet!P56 -> 341.10854 | ... R20: =IncStmt!S6*BalSheet!R56 -> 365.404
B21: Other Current Liabilities | E21: 100 | H21: =SUM(E21:G21) -> 100 | I21: =IncStmt!J6*BalSheet!I57 -> 96.731008 | J21: =IncStmt!K6*BalSheet!J57 -> 99.149283 | K21: =IncStmt!L6*BalSheet!K57 -> 103.11525 | L21: =IncStmt!M6*BalSheet!L57 -> 107.75544 | M21: =IncStmt!N6*BalSheet!M57 -> 111.52688 | N21: =IncStmt!O6*BalSheet!N57 -> 115.43032 | O21: =IncStmt!P6*BalSheet!O57 -> 119.47038 | P21: =IncStmt!Q6*BalSheet!P57 -> 123.65185 | ... R21: =IncStmt!S6*BalSheet!R57 -> 132.45895
B22: Total Current Liabilities | E22: =SUM(E19:E21) -> 590 | H22: =SUM(H19:H21) -> 590 | I22: =SUM(I19:I21) -> 571.38463 | J22: =SUM(J19:J21) -> 585.66924 | K22: =SUM(K19:K21) -> 609.09601 | L22: =SUM(L19:L21) -> 636.50533 | M22: =SUM(M19:M21) -> 658.78302 | N22: =SUM(N19:N21) -> 681.84043 | O22: =SUM(O19:O21) -> 705.70484 | ... R22: =SUM(R19:R21) -> 782.42757
B24: =IncStmt!B26 -> Revolver | E24: 0 | F24: =Summary!D9 -> 0 | H24: =SUM(E24:G24) -> 0 | I24: =DebtSched!F25 -> 6.2900801 | J24: =DebtSched!G25 -> 0 | K24: =DebtSched!H25 -> 0 | L24: =DebtSched!I25 -> 0 | M24: =DebtSched!J25 -> 0 | N24: =DebtSched!K25 -> 0 | O24: =DebtSched!L25 -> 1261.0198 | P24: =DebtSched!M25 -> 1939.8802 | ... R24: =DebtSched!O25 -> 2127.4592
B25: =IncStmt!B27 -> Term Loan A | E25: 0 | F25: =Summary!D10 -> 500 | H25: =SUM(E25:G25) -> 500 | I25: =DebtSched!F42 -> 437.5 | J25: =DebtSched!G42 -> 374.89858 | K25: =DebtSched!H42 -> 288.30284 | L25: =DebtSched!I42 -> 174.13402 | M25: =DebtSched!J42 -> 0 | N25: =DebtSched!K42 -> 0 | O25: =DebtSched!L42 -> 0 | P25: =DebtSched!M42 -> 0 | ... R25: =DebtSched!O42 -> 0
B26: =IncStmt!B28 -> Term Loan B | E26: 0 | F26: =Summary!D11 -> 2000 | H26: =SUM(E26:G26) -> 2000 | I26: =DebtSched!F57 -> 1980 | J26: =DebtSched!G57 -> 1960 | K26: =DebtSched!H57 -> 1940 | L26: =DebtSched!I57 -> 1920 | M26: =DebtSched!J57 -> 1849.6049 | N26: =DebtSched!K57 -> 1573.7025 | O26: =DebtSched!L57 -> 0 | P26: =DebtSched!M57 -> 0 | ... R26: =DebtSched!O57 -> 0
B27: Existing Term Loan | E27: 1000 | G27: =IF(OR(FinStructure=1,FinStructure=2,FinStructure=3,FinStructure=4),-BalSheet!E27,0) -> -1000 | H27: =SUM(E27:G27) -> 0 | I27: =$H$27 -> 0 | J27: =$H$27 -> 0 | K27: =$H$27 -> 0 | L27: =$H$27 -> 0 | M27: =$H$27 -> 0 | N27: =$H$27 -> 0 | O27: =$H$27 -> 0 | P27: =$H$27 -> 0 | ... R27: =$H$27 -> 0
B28: =Summary!B12 -> 2nd Lien | E28: 0 | F28: =Summary!D12 -> 300 | H28: =SUM(E28:G28) -> 300 | I28: =DebtSched!F71 -> 225 | J28: =DebtSched!G71 -> 150 | K28: =DebtSched!H71 -> 75 | L28: =DebtSched!I71 -> 0 | M28: =DebtSched!J71 -> 0 | N28: =DebtSched!K71 -> 0 | O28: =DebtSched!L71 -> 0 | P28: =DebtSched!M71 -> 0 | ... R28: =DebtSched!O71 -> 0
B29: =Summary!B13 -> Senior Notes | E29: 0 | F29: =Summary!D13 -> 1000 | H29: =SUM(E29:G29) -> 1000 | I29: =DebtSched!F83 -> 1000 | J29: =DebtSched!G83 -> 1000 | K29: =DebtSched!H83 -> 1000 | L29: =DebtSched!I83 -> 1000 | M29: =DebtSched!J83 -> 1000 | N29: =DebtSched!K83 -> 1000 | O29: =DebtSched!L83 -> 1000 | P29: =DebtSched!M83 -> 1000 | ... R29: =DebtSched!O83 -> 0
B30: Existing Senior Notes | E30: 500 | G30: =IF(OR(FinStructure=1,FinStructure=2,FinStructure=3,FinStructure=4),-E30,0) -> -500 | H30: =SUM(E30:G30) -> 0 | I30: =$H$30 -> 0 | J30: =$H$30 -> 0 | K30: =$H$30 -> 0 | L30: =$H$30 -> 0 | M30: =$H$30 -> 0 | N30: =$H$30 -> 0 | O30: =$H$30 -> 0 | P30: =$H$30 -> 0 | ... R30: =$H$30 -> 0
B31: =Summary!B14 -> Senior Subordinated Notes | E31: 0 | F31: =Summary!D14 -> 1000 | H31: =SUM(E31:G31) -> 1000 | I31: =DebtSched!F94 -> 1000 | J31: =DebtSched!G94 -> 1000 | K31: =DebtSched!H94 -> 1000 | L31: =DebtSched!I94 -> 1000 | M31: =DebtSched!J94 -> 1000 | N31: =DebtSched!K94 -> 1000 | O31: =DebtSched!L94 -> 1000 | P31: =DebtSched!M94 -> 0 | ... R31: =DebtSched!O94 -> 0
B32: Other Debt | E32: 0 | H32: =SUM(E32:G32) -> 0 | I32: =H32 -> 0 | J32: =I32 -> 0 | K32: =J32 -> 0 | L32: =K32 -> 0 | M32: =L32 -> 0 | N32: =M32 -> 0 | O32: =N32 -> 0 | P32: =O32 -> 0 | ... R32: =Q32 -> 0
B33: Deferred Income Taxes | E33: 300 | H33: =SUM(E33:G33) -> 300 | I33: =H33 -> 300 | J33: =I33 -> 300 | K33: =J33 -> 300 | L33: =K33 -> 300 | M33: =L33 -> 300 | N33: =M33 -> 300 | O33: =N33 -> 300 | P33: =O33 -> 300 | ... R33: =Q33 -> 300
B34: Other Long-term Liabilities | E34: 110 | H34: =SUM(E34:G34) -> 110 | I34: =H34 -> 110 | J34: =I34 -> 110 | K34: =J34 -> 110 | L34: =K34 -> 110 | M34: =L34 -> 110 | N34: =M34 -> 110 | O34: =N34 -> 110 | P34: =O34 -> 110 | ... R34: =Q34 -> 110
B35: Total Liabilities | E35: =E22+SUM(E24:E34) -> 2500 | H35: =H22+SUM(H24:H34) -> 5800 | I35: =I22+SUM(I24:I34) -> 5630.1747 | J35: =J22+SUM(J24:J34) -> 5480.5678 | K35: =K22+SUM(K24:K34) -> 5322.3989 | L35: =L22+SUM(L24:L34) -> 5140.6394 | M35: =M22+SUM(M24:M34) -> 4918.3879 | N35: =N22+SUM(N24:N34) -> 4665.5429 | O35: =O22+SUM(O24:O34) -> 4376.7246 | ... R35: =R22+SUM(R24:R34) -> 3319.8868
B37: Noncontrolling Interest | E37: 0 | H37: =SUM(E37:G37) -> 0 | I37: =H37 -> 0 | J37: =I37 -> 0 | K37: =J37 -> 0 | L37: =K37 -> 0 | M37: =L37 -> 0 | N37: =M37 -> 0 | O37: =N37 -> 0 | P37: =O37 -> 0 | ... R37: =Q37 -> 0
B38: Shareholders' Equity | E38: 3500 | F38: =Summary!D15-Summary!K12-Summary!K14 -> 2038.4417 | G38: =IF(OR(FinStructure=1,FinStructure=2,FinStructure=3,FinStructure=4),-E38,0) -> -3500 | H38: =SUM(E38:G38) -> 2038.4417 | I38: =H38+IncStmt!J42 -> 2093.6532 | J38: =I38+IncStmt!K42 -> 2176.1177 | K38: =J38+IncStmt!L42 -> 2293.5095 | L38: =K38+IncStmt!M42 -> 2441.5526 | M38: =L38+IncStmt!N42 -> 2616.8422 | N38: =M38+IncStmt!O42 -> 2821.6507 | O38: =N38+IncStmt!P42 -> 3062.5702 | P38: =O38+IncStmt!Q42 -> 3315.3173 | ... R38: =Q38+IncStmt!S42 -> 3992.2133
B39: Total Shareholders' Equity | E39: =SUM(E37:E38) -> 3500 | H39: =SUM(H37:H38) -> 2038.4417 | I39: =SUM(I37:I38) -> 2093.6532 | J39: =SUM(J37:J38) -> 2176.1177 | K39: =SUM(K37:K38) -> 2293.5095 | L39: =SUM(L37:L38) -> 2441.5526 | M39: =SUM(M37:M38) -> 2616.8422 | N39: =SUM(N37:N38) -> 2821.6507 | O39: =SUM(O37:O38) -> 3062.5702 | ... R39: =SUM(R37:R38) -> 3992.2133
B41: Total Liabilities and Equity | E41: =E35+E39 -> 6000 | H41: =H35+H39 -> 7838.4417 | I41: =I35+I39 -> 7723.8279 | J41: =J35+J39 -> 7656.6855 | K41: =K35+K39 -> 7615.9083 | L41: =L35+L39 -> 7582.192 | M41: =M35+M39 -> 7535.2301 | N41: =N35+N39 -> 7487.1936 | O41: =O35+O39 -> 7439.2948 | ... R41: =R35+R39 -> 7312.1001
B43: Balance Check | E43: =E17-E41 -> 0 | H43: =H17-H41 -> 0 | I43: =I17-I41 -> 0 | J43: =J17-J41 -> 0 | K43: =K17-K41 -> 0 | L43: =L17-L41 -> 0 | M43: =M17-M41 -> 0 | N43: =N17-N41 -> 0 | O43: =O17-O41 -> 0 | ... R43: =R17-R41 -> 0
B45: Net Working Capital | E45: =SUM(E7:E9)-SUM(E19:E21) -> 635 | H45: =SUM(H7:H9)-SUM(H19:H21) -> 635 | I45: =SUM(I7:I9)-SUM(I19:I21) -> 623.9698 | J45: =SUM(J7:J9)-SUM(J19:J21) -> 629.17878 | K45: =SUM(K7:K9)-SUM(K19:K21) -> 654.34593 | L45: =SUM(L7:L9)-SUM(L19:L21) -> 683.79149 | M45: =SUM(M7:M9)-SUM(M19:M21) -> 707.7242 | N45: =SUM(N7:N9)-SUM(N19:N21) -> 732.49454 | O45: =SUM(O7:O9)-SUM(O19:O21) -> 758.13185 | ... R45: =SUM(R7:R9)-SUM(R19:R21) -> 840.55434
B46: (Increase) / Decrease in Net Working Capital | I46: =H45-I45 -> 11.030199 | J46: =I45-J45 -> -5.2089758 | K46: =J45-K45 -> -25.167151 | L46: =K45-L45 -> -29.445567 | M46: =L45-M45 -> -23.932702 | N46: =M45-N45 -> -24.770347 | O46: =N45-O45 -> -25.637309 | P46: =O45-P45 -> -26.534615 | ... R46: =Q45-R45 -> -28.424543
B48: Balance Sheet Assumptions
B49: Current Assets
B50: Days Sales Outstanding (DSO) | E50: =IF(ISERROR(E7/IncStmt!$I6*365),0,E7/IncStmt!$I6*365) -> 50.719491 | H50: =IF(ISERROR(H7/IncStmt!$I6*365),0,H7/IncStmt!$I6*365) -> 50.719491 | I50: =Assumptions2!F8 -> 47.6 | J50: =Assumptions2!G8 -> 47.6 | K50: =Assumptions2!H8 -> 47.6 | L50: =Assumptions2!I8 -> 47.6 | M50: =Assumptions2!J8 -> 47.6 | N50: =Assumptions2!K8 -> 47.6 | O50: =Assumptions2!L8 -> 47.6 | P50: =Assumptions2!M8 -> 47.6 | ... R50: =Assumptions2!O8 -> 47.6
B51: Days Inventory Held (DIH) | E51: =IF(ISERROR(E8/IncStmt!$I9*365),0,E8/IncStmt!$I9*365) -> 111.66433 | H51: =IF(ISERROR(H8/IncStmt!$I9*365),0,H8/IncStmt!$I9*365) -> 111.66433 | I51: =Assumptions2!F14 -> 105.8 | J51: =Assumptions2!G14 -> 105.8 | K51: =Assumptions2!H14 -> 105.8 | L51: =Assumptions2!I14 -> 105.8 | M51: =Assumptions2!J14 -> 105.8 | N51: =Assumptions2!K14 -> 105.8 | O51: =Assumptions2!L14 -> 105.8 | P51: =Assumptions2!M14 -> 105.8 | ... R51: =Assumptions2!O14 -> 105.8
B52: Prepaid and Other Current Assets (% of sales) | E52: =IF(ISERROR(E9/IncStmt!$I6),0,E9/IncStmt!$I6) -> 0.054039032 | H52: =IF(ISERROR(H9/IncStmt!$I6),0,H9/IncStmt!$I6) -> 0.054039032 | I52: =Assumptions2!F20 -> 0.051 | J52: =Assumptions2!G20 -> 0.051 | K52: =Assumptions2!H20 -> 0.051 | L52: =Assumptions2!I20 -> 0.051 | M52: =Assumptions2!J20 -> 0.051 | N52: =Assumptions2!K20 -> 0.051 | O52: =Assumptions2!L20 -> 0.051 | P52: =Assumptions2!M20 -> 0.051 | ... R52: =Assumptions2!O20 -> 0.051
B54: Current Liabilities
B55: Days Payable Outstanding (DPO) | E55: =IF(ISERROR(E19/IncStmt!$I9*365),0,E19/IncStmt!$I9*365) -> 40.013053 | H55: =IF(ISERROR(H19/IncStmt!$I9*365),0,H19/IncStmt!$I9*365) -> 40.013053 | I55: =Assumptions2!F27 -> 37.9 | J55: =Assumptions2!G27 -> 37.9 | K55: =Assumptions2!H27 -> 37.9 | L55: =Assumptions2!I27 -> 37.9 | M55: =Assumptions2!J27 -> 37.9 | N55: =Assumptions2!K27 -> 37.9 | O55: =Assumptions2!L27 -> 37.9 | P55: =Assumptions2!M27 -> 37.9 | ... R55: =Assumptions2!O27 -> 37.9
B56: Accrued Liabilities (% of sales) | E56: =IF(ISERROR(E20/IncStmt!$I6),0,E20/IncStmt!$I6) -> 0.084918478 | H56: =IF(ISERROR(H20/IncStmt!$I6),0,H20/IncStmt!$I6) -> 0.084918478 | I56: =Assumptions2!F33 -> 0.08 | J56: =Assumptions2!G33 -> 0.08 | K56: =Assumptions2!H33 -> 0.08 | L56: =Assumptions2!I33 -> 0.08 | M56: =Assumptions2!J33 -> 0.08 | N56: =Assumptions2!K33 -> 0.08 | O56: =Assumptions2!L33 -> 0.08 | P56: =Assumptions2!M33 -> 0.08 | ... R56: =Assumptions2!O33 -> 0.08
B57: Other Current Liabilities (% of sales) | E57: =IF(ISERROR(E21/IncStmt!$I6),0,E21/IncStmt!$I6) -> 0.030879447 | H57: =IF(ISERROR(H21/IncStmt!$I6),0,H21/IncStmt!$I6) -> 0.030879447 | I57: =Assumptions2!F39 -> 0.029 | J57: =Assumptions2!G39 -> 0.029 | K57: =Assumptions2!H39 -> 0.029 | L57: =Assumptions2!I39 -> 0.029 | M57: =Assumptions2!J39 -> 0.029 | N57: =Assumptions2!K39 -> 0.029 | O57: =Assumptions2!L39 -> 0.029 | P57: =Assumptions2!M39 -> 0.029 | ... R57: =Assumptions2!O39 -> 0.029
XX1000: 127155

Sheet CFStmt
B1: =Summary!$B$3 -> ($ in millions, fiscal year ending December 31)
B2: Cash Flow Statement
F3: Projection Period
F4: 1 | G4: =F4+1 -> 2 | H4: =G4+1 -> 3 | I4: =H4+1 -> 4 | J4: =I4+1 -> 5 | K4: =J4+1 -> 6 | L4: =K4+1 -> 7 | M4: =L4+1 -> 8 | N4: =M4+1 -> 9 | O4: =N4+1 -> 10
F5: =IncStmt!$I$5+F4 -> 2025 | G5: =IncStmt!$I$5+G4 -> 2026 | H5: =IncStmt!$I$5+H4 -> 2027 | I5: =IncStmt!$I$5+I4 -> 2028 | J5: =IncStmt!$I$5+J4 -> 2029 | K5: =IncStmt!$I$5+K4 -> 2030 | L5: =IncStmt!$I$5+L4 -> 2031 | M5: =IncStmt!$I$5+M4 -> 2032 | ... O5: =IncStmt!$I$5+O4 -> 2034
B6: Operating Activities
B7: Net Income | F7: =IncStmt!J42 -> 55.211538 | G7: =IncStmt!K42 -> 82.464517 | H7: =IncStmt!L42 -> 117.39178 | I7: =IncStmt!M42 -> 148.04314 | J7: =IncStmt!N42 -> 175.28957 | K7: =IncStmt!O42 -> 204.80854 | L7: =IncStmt!P42 -> 240.91949 | M7: =IncStmt!Q42 -> 252.74709 | ... O7: =IncStmt!S42 -> 344.60396
B8: Plus: Depreciation | F8: =IncStmt!J20 -> 166.7776 | G8: =IncStmt!K20 -> 170.94704 | H8: =IncStmt!L20 -> 177.78492 | I8: =IncStmt!M20 -> 185.78524 | J8: =IncStmt!N20 -> 192.28773 | K8: =IncStmt!O20 -> 199.0178 | L8: =IncStmt!P20 -> 205.98342 | M8: =IncStmt!Q20 -> 213.19284 | ... O8: =IncStmt!S20 -> 228.3775
B9: Plus: Amortization | F9: =IncStmt!J21 -> 66.71104 | G9: =IncStmt!K21 -> 68.378816 | H9: =IncStmt!L21 -> 71.113969 | I9: =IncStmt!M21 -> 74.314097 | J9: =IncStmt!N21 -> 76.915091 | K9: =IncStmt!O21 -> 79.607119 | L9: =IncStmt!P21 -> 82.393368 | M9: =IncStmt!Q21 -> 85.277136 | ... O9: =IncStmt!S21 -> 91.351
B10: Plus: Amortization of Financing Fees | F10: =IncStmt!J35 -> 18.257143 | G10: =IncStmt!K35 -> 18.257143 | H10: =IncStmt!L35 -> 18.257143 | I10: =IncStmt!M35 -> 16.257143 | J10: =IncStmt!N35 -> 16.257143 | K10: =IncStmt!O35 -> 16.257143 | L10: =IncStmt!P35 -> 15.007143 | M10: =IncStmt!Q35 -> 9.65 | ... O10: =IncStmt!S35 -> 5.9
B12: Changes in Working Capital Accounts
B13: (Inc.) / Dec. in Accounts Receivable | F13: =BalSheet!H7-BalSheet!I7 -> 15.007465 | G13: =BalSheet!I7-BalSheet!J7 -> -10.874813 | H13: =BalSheet!J7-BalSheet!K7 -> -17.834694 | I13: =BalSheet!K7-BalSheet!L7 -> -20.866592 | J13: =BalSheet!L7-BalSheet!M7 -> -16.959902 | K13: =BalSheet!M7-BalSheet!N7 -> -17.553499 | L13: =BalSheet!N7-BalSheet!O7 -> -18.167871 | M13: =BalSheet!O7-BalSheet!P7 -> -18.803747 | ... O13: =BalSheet!Q7-BalSheet!R7 -> -20.143044
B14: (Inc.) / Dec. in Inventories | F14: =BalSheet!H8-BalSheet!I8 -> 19.888107 | G14: =BalSheet!I8-BalSheet!J8 -> -14.502797 | H14: =BalSheet!J8-BalSheet!K8 -> -23.784588 | I14: =BalSheet!K8-BalSheet!L8 -> -27.827968 | J14: =BalSheet!L8-BalSheet!M8 -> -22.617954 | K14: =BalSheet!M8-BalSheet!N8 -> -23.409582 | L14: =BalSheet!N8-BalSheet!O8 -> -24.228917 | M14: =BalSheet!O8-BalSheet!P8 -> -25.076929 | ... O14: =BalSheet!Q8-BalSheet!R8 -> -26.863034
B15: (Inc.) / Dec. in Prepaid and Other Current Assets | F15: =BalSheet!H9-BalSheet!I9 -> -5.25 | G15: =BalSheet!I9-BalSheet!J9 -> 5.8840192 | H15: =BalSheet!J9-BalSheet!K9 -> -6.9746392 | I15: =BalSheet!K9-BalSheet!L9 -> -8.1603279 | J15: =BalSheet!L9-BalSheet!M9 -> -6.6325332 | K15: =BalSheet!M9-BalSheet!N9 -> -6.8646718 | L15: =BalSheet!N9-BalSheet!O9 -> -7.1049354 | M15: =BalSheet!O9-BalSheet!P9 -> -7.3536081 | ... O15: =BalSheet!Q9-BalSheet!R9 -> -7.8773688
B17: Inc. / (Dec.) in Accounts Receivable | F17: =BalSheet!I19-BalSheet!H19 -> -7.1905412 | G17: =BalSheet!J19-BalSheet!I19 -> 5.1952365 | H17: =BalSheet!K19-BalSheet!J19 -> 8.5201878 | I17: =BalSheet!L19-BalSheet!K19 -> 9.9686197 | J17: =BalSheet!M19-BalSheet!L19 -> 8.1022726 | K17: =BalSheet!N19-BalSheet!M19 -> 8.3858521 | L17: =BalSheet!O19-BalSheet!N19 -> 8.679357 | M17: =BalSheet!P19-BalSheet!O19 -> 8.9831345 | ... O17: =BalSheet!R19-BalSheet!Q19 -> 9.6229582
B18: Inc. / (Dec.) in Accrued Liabilities | F18: =BalSheet!I20-BalSheet!H20 -> -8.15584 | G18: =BalSheet!J20-BalSheet!I20 -> 6.671104 | H18: =BalSheet!K20-BalSheet!J20 -> 10.940611 | I18: =BalSheet!L20-BalSheet!K20 -> 12.800514 | J18: =BalSheet!M20-BalSheet!L20 -> 10.403974 | K18: =BalSheet!N20-BalSheet!M20 -> 10.768113 | L18: =BalSheet!O20-BalSheet!N20 -> 11.144997 | M18: =BalSheet!P20-BalSheet!O20 -> 11.535072 | ... O18: =BalSheet!R20-BalSheet!Q20 -> 12.356657
B19: Inc. / (Dec.) in Other Current Liabilities | F19: =BalSheet!I21-BalSheet!H21 -> -3.268992 | G19: =BalSheet!J21-BalSheet!I21 -> 2.4182752 | H19: =BalSheet!K21-BalSheet!J21 -> 3.9659713 | I19: =BalSheet!L21-BalSheet!K21 -> 4.6401865 | J19: =BalSheet!M21-BalSheet!L21 -> 3.7714404 | K19: =BalSheet!N21-BalSheet!M21 -> 3.9034408 | L19: =BalSheet!O21-BalSheet!N21 -> 4.0400613 | M19: =BalSheet!P21-BalSheet!O21 -> 4.1814634 | ... O19: =BalSheet!R21-BalSheet!Q21 -> 4.4792882
B20: (Inc.) / Dec. in Net Working Capital | F20: =SUM(F13:F19) -> 11.030199 | G20: =SUM(G13:G19) -> -5.2089758 | H20: =SUM(H13:H19) -> -25.167151 | I20: =SUM(I13:I19) -> -29.445567 | J20: =SUM(J13:J19) -> -23.932702 | K20: =SUM(K13:K19) -> -24.770347 | L20: =SUM(L13:L19) -> -25.637309 | M20: =SUM(M13:M19) -> -26.534615 | ... O20: =SUM(O13:O19) -> -28.424543
B21: Cash Flow from Operating Activities | F21: =SUM(F7:F10)+F20 -> 317.98752 | G21: =SUM(G7:G10)+G20 -> 334.83854 | H21: =SUM(H7:H10)+H20 -> 359.38066 | I21: =SUM(I7:I10)+I20 -> 394.95406 | J21: =SUM(J7:J10)+J20 -> 436.81683 | K21: =SUM(K7:K10)+K20 -> 474.92025 | L21: =SUM(L7:L10)+L20 -> 518.66611 | M21: =SUM(M7:M10)+M20 -> 534.33245 | ... O21: =SUM(O7:O10)+O20 -> 641.80791
B23: Investing Activities
B24: Capital Expenditures | F24: =-F48*IncStmt!J6 -> -166.7776 | G24: =-G48*IncStmt!K6 -> -170.94704 | H24: =-H48*IncStmt!L6 -> -177.78492 | I24: =-I48*IncStmt!M6 -> -185.78524 | J24: =-J48*IncStmt!N6 -> -192.28773 | K24: =-K48*IncStmt!O6 -> -199.0178 | L24: =-L48*IncStmt!P6 -> -205.98342 | M24: =-M48*IncStmt!Q6 -> -213.19284 | ... O24: =-O48*IncStmt!S6 -> -228.3775
B25: Other Investing Activities | F25: 0 | G25: 0 | H25: 0 | I25: 0 | J25: 0 | K25: 0 | L25: 0 | M25: 0 | N25: 0 | O25: 0
B26: Cash Flow from Investing Activities | F26: =SUM(F24:F25) -> -166.7776 | G26: =SUM(G24:G25) -> -170.94704 | H26: =SUM(H24:H25) -> -177.78492 | I26: =SUM(I24:I25) -> -185.78524 | J26: =SUM(J24:J25) -> -192.28773 | K26: =SUM(K24:K25) -> -199.0178 | L26: =SUM(L24:L25) -> -205.98342 | M26: =SUM(M24:M25) -> -213.19284 | ... O26: =SUM(O24:O25) -> -228.3775
B28: Financing Activities
B29: Revolving Credit Facility | F29: =DebtSched!F24 -> 6.2900801 | G29: =DebtSched!G24 -> -6.2900801 | H29: =DebtSched!H24 -> 0 | I29: =DebtSched!I24 -> 0 | J29: =DebtSched!J24 -> 0 | K29: =DebtSched!K24 -> 0 | L29: =DebtSched!L24 -> 1261.0198 | M29: =DebtSched!M24 -> 678.86039 | ... O29: =DebtSched!O24 -> 586.56959 | P29: (1 point for the row)
B30: Term Loan A | F30: =DebtSched!F40+DebtSched!F41 -> -62.5 | G30: =DebtSched!G40+DebtSched!G41 -> -62.60142 | H30: =DebtSched!H40+DebtSched!H41 -> -86.595738 | I30: =DebtSched!I40+DebtSched!I41 -> -114.16882 | J30: =DebtSched!J40+DebtSched!J41 -> -174.13402 | K30: =DebtSched!K40+DebtSched!K41 -> 0 | L30: =DebtSched!L40+DebtSched!L41 -> 0 | M30: =DebtSched!M40+DebtSched!M41 -> 0 | ... O30: =DebtSched!O40+DebtSched!O41 -> 0 | P30: (1 point for the row)
B31: Term Loan B | F31: =DebtSched!F55+DebtSched!F56 -> -20 | G31: =DebtSched!G55+DebtSched!G56 -> -20 | H31: =DebtSched!H55+DebtSched!H56 -> -20 | I31: =DebtSched!I55+DebtSched!I56 -> -20 | J31: =DebtSched!J55+DebtSched!J56 -> -70.395079 | K31: =DebtSched!K55+DebtSched!K56 -> -275.90245 | L31: =DebtSched!L55+DebtSched!L56 -> -1573.7025 | M31: =DebtSched!M55+DebtSched!M56 -> 0 | ... O31: =DebtSched!O55+DebtSched!O56 -> 0 | P31: (1 point for the row)
B32: 2nd Lien | F32: =DebtSched!F70 -> -75 | G32: =DebtSched!G70 -> -75 | H32: =DebtSched!H70 -> -75 | I32: =DebtSched!I70 -> -75 | J32: =DebtSched!J70 -> 0 | K32: =DebtSched!K70 -> 0 | L32: =DebtSched!L70 -> 0 | M32: =DebtSched!M70 -> 0 | ... O32: =DebtSched!O70 -> 0 | P32: (1 point for the row)
B33: Senior Notes | F33: =DebtSched!F82 -> 0 | G33: =DebtSched!G82 -> 0 | H33: =DebtSched!H82 -> 0 | I33: =DebtSched!I82 -> 0 | J33: =DebtSched!J82 -> 0 | K33: =DebtSched!K82 -> 0 | L33: =DebtSched!L82 -> 0 | M33: =DebtSched!M82 -> 0 | ... O33: =DebtSched!O82 -> -1000 | P33: (1 point for the row)
B34: Senior Subordinated Notes | F34: =DebtSched!F93 -> 0 | G34: =DebtSched!G93 -> 0 | H34: =DebtSched!H93 -> 0 | I34: =DebtSched!I93 -> 0 | J34: =DebtSched!J93 -> 0 | K34: =DebtSched!K93 -> 0 | L34: =DebtSched!L93 -> 0 | M34: =DebtSched!M93 -> -1000 | ... O34: =DebtSched!O93 -> 0 | P34: (1 point for the row)
B35: Other Debt
B36: Dividends
B37: Equity Issuance (Repurchase)
B38: Cash Flow from Financing Activities | F38: =SUM(F29:F37) -> -151.20992 | G38: =SUM(G29:G37) -> -163.8915 | H38: =SUM(H29:H37) -> -181.59574 | I38: =SUM(I29:I37) -> -209.16882 | J38: =SUM(J29:J37) -> -244.5291 | K38: =SUM(K29:K37) -> -275.90245 | L38: =SUM(L29:L37) -> -312.68269 | M38: =SUM(M29:M37) -> -321.13961 | ... O38: =SUM(O29:O37) -> -413.43041
B40: Excess Cash for the Period | F40: =F21+F26+F38 -> 0 | G40: =G21+G26+G38 -> 0 | H40: =H21+H26+H38 -> 0 | I40: =I21+I26+I38 -> 0 | J40: =J21+J26+J38 -> 0 | K40: =K21+K26+K38 -> 0 | L40: =L21+L26+L38 -> 0 | M40: =M21+M26+M38 -> 0 | ... O40: =O21+O26+O38 -> 0
B41: Beginning Cash Balance | F41: =BalSheet!H6 -> 0 | G41: =BalSheet!I6 -> 0 | H41: =BalSheet!J6 -> 0 | I41: =BalSheet!K6 -> 0 | J41: =BalSheet!L6 -> 0 | K41: =BalSheet!M6 -> 0 | L41: =BalSheet!N6 -> 0 | M41: =BalSheet!O6 -> 0 | ... O41: =BalSheet!Q6 -> 0
B42: Ending Cash Balance | F42: =F40+F41 -> 0 | G42: =G40+G41 -> 0 | H42: =H40+H41 -> 0 | I42: =I40+I41 -> 0 | J42: =J40+J41 -> 0 | K42: =K40+K41 -> 0 | L42: =L40+L41 -> 0 | M42: =M40+M41 -> 0 | ... O42: =O40+O41 -> 0
B47: Cash Flow Statement Assumptions
B48: Capital Expenditures (% of sales) | F48: =Assumptions1!F45 -> 0.05 | G48: =Assumptions1!G45 -> 0.05 | H48: =Assumptions1!H45 -> 0.05 | I48: =Assumptions1!I45 -> 0.05 | J48: =Assumptions1!J45 -> 0.05 | K48: =Assumptions1!K45 -> 0.05 | L48: =Assumptions1!L45 -> 0.05 | M48: =Assumptions1!M45 -> 0.05 | ... O48: =Assumptions1!O45 -> 0.05
XX1000: 127155

Sheet RetAnalysis
B1: =Summary!$B$3 -> ($ in millions, fiscal year ending December 31)
B2: Returns Analysis
G3: Projection Period
F4: =IncStmt!$I$4 -> Pro Forma | G4: 1 | H4: =G4+1 -> 2 | I4: =H4+1 -> 3 | J4: =I4+1 -> 4 | K4: =J4+1 -> 5 | L4: =K4+1 -> 6 | M4: =L4+1 -> 7 | N4: =M4+1 -> 8 | O4: =N4+1 -> 9 | P4: =O4+1 -> 10
F5: =IncStmt!$I$5 -> 2024 | G5: =IncStmt!$I$5+G4 -> 2025 | H5: =IncStmt!$I$5+H4 -> 2026 | I5: =IncStmt!$I$5+I4 -> 2027 | J5: =IncStmt!$I$5+J4 -> 2028 | K5: =IncStmt!$I$5+K4 -> 2029 | L5: =IncStmt!$I$5+L4 -> 2030 | M5: =IncStmt!$I$5+M4 -> 2031 | N5: =IncStmt!$I$5+N4 -> 2032 | ... P5: =IncStmt!$I$5+P4 -> 2034
B6: Entry EBITDA Multiple | E6: 10.5
B7: Initial Equity Investment | F7: =Summary!D15 -> 2088.4417
B8: EBITDA | G8: =IncStmt!J17 -> 733.82144 | H8: =IncStmt!K17 -> 752.16698 | I8: =IncStmt!L17 -> 782.25366 | J8: =IncStmt!M17 -> 817.45507 | K8: =IncStmt!N17 -> 846.066 | L8: =IncStmt!O17 -> 875.67831 | M8: =IncStmt!P17 -> 906.32705 | N8: =IncStmt!Q17 -> 938.04849 | ... P8: =IncStmt!S17 -> 1004.861 | Q8: (1 point for the row)
B9: Exit EBITDA Multiple | E9: 10.5
B10: Enterprise Value at Exit | G10: =G8*$E$9 -> 7705.1251 | H10: =H8*$E$9 -> 7897.7532 | I10: =I8*$E$9 -> 8213.6634 | J10: =J8*$E$9 -> 8583.2782 | K10: =K8*$E$9 -> 8883.693 | L10: =L8*$E$9 -> 9194.6222 | M10: =M8*$E$9 -> 9516.434 | N10: =N8*$E$9 -> 9849.5092 | ... P10: =P8*$E$9 -> 10551.04 | Q10: (1 point for the row)
B12: Less: Net Debt
B13: Revolving Credit Facility | G13: =BalSheet!I24 -> 6.2900801 | H13: =BalSheet!J24 -> 0 | I13: =BalSheet!K24 -> 0 | J13: =BalSheet!L24 -> 0 | K13: =BalSheet!M24 -> 0 | L13: =BalSheet!N24 -> 0 | M13: =BalSheet!O24 -> 1261.0198 | N13: =BalSheet!P24 -> 1939.8802 | ... P13: =BalSheet!R24 -> 2127.4592 | Q13: (1 point for the row)
B14: Term Loan A | G14: =BalSheet!I25 -> 437.5 | H14: =BalSheet!J25 -> 374.89858 | I14: =BalSheet!K25 -> 288.30284 | J14: =BalSheet!L25 -> 174.13402 | K14: =BalSheet!M25 -> 0 | L14: =BalSheet!N25 -> 0 | M14: =BalSheet!O25 -> 0 | N14: =BalSheet!P25 -> 0 | ... P14: =BalSheet!R25 -> 0 | Q14: (1 point for the row)
B15: Term Loan B | G15: =BalSheet!I26 -> 1980 | H15: =BalSheet!J26 -> 1960 | I15: =BalSheet!K26 -> 1940 | J15: =BalSheet!L26 -> 1920 | K15: =BalSheet!M26 -> 1849.6049 | L15: =BalSheet!N26 -> 1573.7025 | M15: =BalSheet!O26 -> 0 | N15: =BalSheet!P26 -> 0 | ... P15: =BalSheet!R26 -> 0 | Q15: (1 point for the row)
B16: 2nd Lien | G16: =BalSheet!I28 -> 225 | H16: =BalSheet!J28 -> 150 | I16: =BalSheet!K28 -> 75 | J16: =BalSheet!L28 -> 0 | K16: =BalSheet!M28 -> 0 | L16: =BalSheet!N28 -> 0 | M16: =BalSheet!O28 -> 0 | N16: =BalSheet!P28 -> 0 | ... P16: =BalSheet!R28 -> 0 | Q16: (1 point for the row)
B17: Senior Notes | G17: =BalSheet!I29 -> 1000 | H17: =BalSheet!J29 -> 1000 | I17: =BalSheet!K29 -> 1000 | J17: =BalSheet!L29 -> 1000 | K17: =BalSheet!M29 -> 1000 | L17: =BalSheet!N29 -> 1000 | M17: =BalSheet!O29 -> 1000 | N17: =BalSheet!P29 -> 1000 | ... P17: =BalSheet!R29 -> 0 | Q17: (1 point for the row)
B18: Senior Subordinated Notes | G18: =BalSheet!I31 -> 1000 | H18: =BalSheet!J31 -> 1000 | I18: =BalSheet!K31 -> 1000 | J18: =BalSheet!L31 -> 1000 | K18: =BalSheet!M31 -> 1000 | L18: =BalSheet!N31 -> 1000 | M18: =BalSheet!O31 -> 1000 | N18: =BalSheet!P31 -> 0 | ... P18: =BalSheet!R31 -> 0 | Q18: (1 point for the row)
B19: Other Debt | G19: =BalSheet!I32 -> 0 | H19: =BalSheet!J32 -> 0 | I19: =BalSheet!K32 -> 0 | J19: =BalSheet!L32 -> 0 | K19: =BalSheet!M32 -> 0 | L19: =BalSheet!N32 -> 0 | M19: =BalSheet!O32 -> 0 | N19: =BalSheet!P32 -> 0 | ... P19: =BalSheet!R32 -> 0 | Q19: (1 point for the row)
B20: Total Debt | G20: =SUM(G13:G19) -> 4648.7901 | H20: =SUM(H13:H19) -> 4484.8986 | I20: =SUM(I13:I19) -> 4303.3028 | J20: =SUM(J13:J19) -> 4094.134 | K20: =SUM(K13:K19) -> 3849.6049 | L20: =SUM(L13:L19) -> 3573.7025 | M20: =SUM(M13:M19) -> 3261.0198 | N20: =SUM(N13:N19) -> 2939.8802 | ... P20: =SUM(P13:P19) -> 2127.4592 | Q20: (1 point for the row)
B21: Less: Cash and Cash Equivalents | G21: =BalSheet!I6 -> 0 | H21: =BalSheet!J6 -> 0 | I21: =BalSheet!K6 -> 0 | J21: =BalSheet!L6 -> 0 | K21: =BalSheet!M6 -> 0 | L21: =BalSheet!N6 -> 0 | M21: =BalSheet!O6 -> 0 | N21: =BalSheet!P6 -> 0 | ... P21: =BalSheet!R6 -> 0 | Q21: (1 point for the row)
B22: Net Debt | G22: =G20-G21 -> 4648.7901 | H22: =H20-H21 -> 4484.8986 | I22: =I20-I21 -> 4303.3028 | J22: =J20-J21 -> 4094.134 | K22: =K20-K21 -> 3849.6049 | L22: =L20-L21 -> 3573.7025 | M22: =M20-M21 -> 3261.0198 | N22: =N20-N21 -> 2939.8802 | ... P22: =P20-P21 -> 2127.4592 | Q22: (1 point for the row)
B24: Equity Value at Exit | G24: =G10-G22 -> 3056.335 | H24: =H10-H22 -> 3412.8547 | I24: =I10-I22 -> 3910.3605 | J24: =J10-J22 -> 4489.1442 | K24: =K10-K22 -> 5034.088 | L24: =L10-L22 -> 5620.9198 | M24: =M10-M22 -> 6255.4142 | N24: =N10-N22 -> 6909.629 | ... P24: =P10-P22 -> 8423.5813 | Q24: (1 point for the row)
B26: Cash Return | G26: =IF(ISERROR(G24/$F$7),0,G24/$F$7) -> 1.4634524 | H26: =IF(ISERROR(H24/$F$7),0,H24/$F$7) -> 1.6341633 | I26: =IF(ISERROR(I24/$F$7),0,I24/$F$7) -> 1.872382 | J26: =IF(ISERROR(J24/$F$7),0,J24/$F$7) -> 2.1495186 | K26: =IF(ISERROR(K24/$F$7),0,K24/$F$7) -> 2.4104518 | L26: =IF(ISERROR(L24/$F$7),0,L24/$F$7) -> 2.6914421 | M26: =IF(ISERROR(M24/$F$7),0,M24/$F$7) -> 2.9952545 | N26: =IF(ISERROR(N24/$F$7),0,N24/$F$7) -> 3.3085095 | ... P26: =IF(ISERROR(P24/$F$7),0,P24/$F$7) -> 4.0334291
G28: =G4 -> 1 | H28: =H4 -> 2 | I28: =I4 -> 3 | J28: =J4 -> 4 | K28: =K4 -> 5 | L28: =L4 -> 6 | M28: =M4 -> 7 | N28: =N4 -> 8 | ... P28: =P4 -> 10
E29: Exit Year | G29: =G5 -> 2025 | H29: =H5 -> 2026 | I29: =I5 -> 2027 | J29: =J5 -> 2028 | K29: =K5 -> 2029 | L29: =L5 -> 2030 | M29: =M5 -> 2031 | N29: =N5 -> 2032 | ... P29: =P5 -> 2034
B30: Initial Equity Investment | G30: =-$F$7 -> -2088.4417 | H30: =-$F$7 -> -2088.4417 | I30: =-$F$7 -> -2088.4417 | J30: =-$F$7 -> -2088.4417 | K30: =-$F$7 -> -2088.4417 | L30: =-$F$7 -> -2088.4417 | M30: =-$F$7 -> -2088.4417 | N30: =-$F$7 -> -2088.4417 | ... P30: =-$F$7 -> -2088.4417 | Q30: (10 points for G30:P40)
B31: Equity Proceeds | E31: 1 | G31: =IF($E31<G$28,0,IF($E31=G$28,G$24,"")) -> 3056.335 | H31: =IF($E31<H$28,0,IF($E31=H$28,H$24,"")) -> 0 | I31: =IF($E31<I$28,0,IF($E31=I$28,I$24,"")) -> 0 | J31: =IF($E31<J$28,0,IF($E31=J$28,J$24,"")) -> 0 | K31: =IF($E31<K$28,0,IF($E31=K$28,K$24,"")) -> 0 | L31: =IF($E31<L$28,0,IF($E31=L$28,L$24,"")) -> 0 | M31: =IF($E31<M$28,0,IF($E31=M$28,M$24,"")) -> 0 | N31: =IF($E31<N$28,0,IF($E31=N$28,N$24,"")) -> 0 | ... P31: =IF($E31<P$28,0,IF($E31=P$28,P$24,"")) -> 0
E32: =E31+1 -> 2 | G32: =IF($E32<G$28,0,IF($E32=G$28,G$24,"")) | H32: =IF($E32<H$28,0,IF($E32=H$28,H$24,"")) -> 3412.8547 | I32: =IF($E32<I$28,0,IF($E32=I$28,I$24,"")) -> 0 | J32: =IF($E32<J$28,0,IF($E32=J$28,J$24,"")) -> 0 | K32: =IF($E32<K$28,0,IF($E32=K$28,K$24,"")) -> 0 | L32: =IF($E32<L$28,0,IF($E32=L$28,L$24,"")) -> 0 | M32: =IF($E32<M$28,0,IF($E32=M$28,M$24,"")) -> 0 | N32: =IF($E32<N$28,0,IF($E32=N$28,N$24,"")) -> 0 | ... P32: =IF($E32<P$28,0,IF($E32=P$28,P$24,"")) -> 0
E33: =E32+1 -> 3 | G33: =IF($E33<G$28,0,IF($E33=G$28,G$24,"")) | H33: =IF($E33<H$28,0,IF($E33=H$28,H$24,"")) | I33: =IF($E33<I$28,0,IF($E33=I$28,I$24,"")) -> 3910.3605 | J33: =IF($E33<J$28,0,IF($E33=J$28,J$24,"")) -> 0 | K33: =IF($E33<K$28,0,IF($E33=K$28,K$24,"")) -> 0 | L33: =IF($E33<L$28,0,IF($E33=L$28,L$24,"")) -> 0 | M33: =IF($E33<M$28,0,IF($E33=M$28,M$24,"")) -> 0 | N33: =IF($E33<N$28,0,IF($E33=N$28,N$24,"")) -> 0 | ... P33: =IF($E33<P$28,0,IF($E33=P$28,P$24,"")) -> 0
E34: =E33+1 -> 4 | G34: =IF($E34<G$28,0,IF($E34=G$28,G$24,"")) | H34: =IF($E34<H$28,0,IF($E34=H$28,H$24,"")) | I34: =IF($E34<I$28,0,IF($E34=I$28,I$24,"")) | J34: =IF($E34<J$28,0,IF($E34=J$28,J$24,"")) -> 4489.1442 | K34: =IF($E34<K$28,0,IF($E34=K$28,K$24,"")) -> 0 | L34: =IF($E34<L$28,0,IF($E34=L$28,L$24,"")) -> 0 | M34: =IF($E34<M$28,0,IF($E34=M$28,M$24,"")) -> 0 | N34: =IF($E34<N$28,0,IF($E34=N$28,N$24,"")) -> 0 | ... P34: =IF($E34<P$28,0,IF($E34=P$28,P$24,"")) -> 0
E35: =E34+1 -> 5 | G35: =IF($E35<G$28,0,IF($E35=G$28,G$24,"")) | H35: =IF($E35<H$28,0,IF($E35=H$28,H$24,"")) | I35: =IF($E35<I$28,0,IF($E35=I$28,I$24,"")) | J35: =IF($E35<J$28,0,IF($E35=J$28,J$24,"")) | K35: =IF($E35<K$28,0,IF($E35=K$28,K$24,"")) -> 5034.088 | L35: =IF($E35<L$28,0,IF($E35=L$28,L$24,"")) -> 0 | M35: =IF($E35<M$28,0,IF($E35=M$28,M$24,"")) -> 0 | N35: =IF($E35<N$28,0,IF($E35=N$28,N$24,"")) -> 0 | ... P35: =IF($E35<P$28,0,IF($E35=P$28,P$24,"")) -> 0
E36: =E35+1 -> 6 | G36: =IF($E36<G$28,0,IF($E36=G$28,G$24,"")) | H36: =IF($E36<H$28,0,IF($E36=H$28,H$24,"")) | I36: =IF($E36<I$28,0,IF($E36=I$28,I$24,"")) | J36: =IF($E36<J$28,0,IF($E36=J$28,J$24,"")) | K36: =IF($E36<K$28,0,IF($E36=K$28,K$24,"")) | L36: =IF($E36<L$28,0,IF($E36=L$28,L$24,"")) -> 5620.9198 | M36: =IF($E36<M$28,0,IF($E36=M$28,M$24,"")) -> 0 | N36: =IF($E36<N$28,0,IF($E36=N$28,N$24,"")) -> 0 | ... P36: =IF($E36<P$28,0,IF($E36=P$28,P$24,"")) -> 0
E37: =E36+1 -> 7 | G37: =IF($E37<G$28,0,IF($E37=G$28,G$24,"")) | H37: =IF($E37<H$28,0,IF($E37=H$28,H$24,"")) | I37: =IF($E37<I$28,0,IF($E37=I$28,I$24,"")) | J37: =IF($E37<J$28,0,IF($E37=J$28,J$24,"")) | K37: =IF($E37<K$28,0,IF($E37=K$28,K$24,"")) | L37: =IF($E37<L$28,0,IF($E37=L$28,L$24,"")) | M37: =IF($E37<M$28,0,IF($E37=M$28,M$24,"")) -> 6255.4142 | N37: =IF($E37<N$28,0,IF($E37=N$28,N$24,"")) -> 0 | ... P37: =IF($E37<P$28,0,IF($E37=P$28,P$24,"")) -> 0
E38: =E37+1 -> 8 | G38: =IF($E38<G$28,0,IF($E38=G$28,G$24,"")) | H38: =IF($E38<H$28,0,IF($E38=H$28,H$24,"")) | I38: =IF($E38<I$28,0,IF($E38=I$28,I$24,"")) | J38: =IF($E38<J$28,0,IF($E38=J$28,J$24,"")) | K38: =IF($E38<K$28,0,IF($E38=K$28,K$24,"")) | L38: =IF($E38<L$28,0,IF($E38=L$28,L$24,"")) | M38: =IF($E38<M$28,0,IF($E38=M$28,M$24,"")) | N38: =IF($E38<N$28,0,IF($E38=N$28,N$24,"")) -> 6909.629 | ... P38: =IF($E38<P$28,0,IF($E38=P$28,P$24,"")) -> 0
E39: =E38+1 -> 9 | G39: =IF($E39<G$28,0,IF($E39=G$28,G$24,"")) | H39: =IF($E39<H$28,0,IF($E39=H$28,H$24,"")) | I39: =IF($E39<I$28,0,IF($E39=I$28,I$24,"")) | J39: =IF($E39<J$28,0,IF($E39=J$28,J$24,"")) | K39: =IF($E39<K$28,0,IF($E39=K$28,K$24,"")) | L39: =IF($E39<L$28,0,IF($E39=L$28,L$24,"")) | M39: =IF($E39<M$28,0,IF($E39=M$28,M$24,"")) | N39: =IF($E39<N$28,0,IF($E39=N$28,N$24,"")) | ... P39: =IF($E39<P$28,0,IF($E39=P$28,P$24,"")) -> 0
E40: =E39+1 -> 10 | G40: =IF($E40<G$28,0,IF($E40=G$28,G$24,"")) | H40: =IF($E40<H$28,0,IF($E40=H$28,H$24,"")) | I40: =IF($E40<I$28,0,IF($E40=I$28,I$24,"")) | J40: =IF($E40<J$28,0,IF($E40=J$28,J$24,"")) | K40: =IF($E40<K$28,0,IF($E40=K$28,K$24,"")) | L40: =IF($E40<L$28,0,IF($E40=L$28,L$24,"")) | M40: =IF($E40<M$28,0,IF($E40=M$28,M$24,"")) | N40: =IF($E40<N$28,0,IF($E40=N$28,N$24,"")) | ... P40: =IF($E40<P$28,0,IF($E40=P$28,P$24,"")) -> 8423.5813
B41: IRR | G41: =IF(ISERROR(IRR(G30:G40,0.1)),"NA",IRR(G30:G40,0.1)) -> 0.46345244 | H41: =IF(ISERROR(IRR(H30:H40,0.1)),"NA",IRR(H30:H40,0.1)) -> 0.27834396 | I41: =IF(ISERROR(IRR(I30:I40,0.1)),"NA",IRR(I30:I40,0.1)) -> 0.23253185 | J41: =IF(ISERROR(IRR(J30:J40,0.1)),"NA",IRR(J30:J40,0.1)) -> 0.21083594 | K41: =IF(ISERROR(IRR(K30:K40,0.1)),"NA",IRR(K30:K40,0.1)) -> 0.19239375 | L41: =IF(ISERROR(IRR(L30:L40,0.1)),"NA",IRR(L30:L40,0.1)) -> 0.17940828 | M41: =IF(ISERROR(IRR(M30:M40,0.1)),"NA",IRR(M30:M40,0.1)) -> 0.16966626 | N41: =IF(ISERROR(IRR(N30:N40,0.1)),"NA",IRR(N30:N40,0.1)) -> 0.16132573 | ... P41: =IF(ISERROR(IRR(P30:P40,0.1)),"NA",IRR(P30:P40,0.1)) -> 0.14965476
C43: (7 points for data table) | K43: (10 points for data table)
C44: IRR Assuming Exit after Year 5 | K44: ="IRR Assuming "&TEXT(EntryMultiple,"0.0x")&" Entry Multiple" -> IRR Assuming 10.5x Entry Multiple
D45: Exit Multiple | L45: Exit Year
C46: =K41 -> 0.19239375 | D46: =E46-0.5 -> 10 | E46: =F46-0.5 -> 10.5 | F46: 11 | G46: =F46+0.5 -> 11.5 | H46: =G46+0.5 -> 12 | L46: =I29 -> 2027 | M46: =J29 -> 2028 | N46: =K29 -> 2029 | O46: =L29 -> 2030 | P46: =M29 -> 2031
C47: =C48-0.5 -> 9 | D47: 0.32442541 | E47: 0.34788117 | F47: 0.36980946 | G47: 0.39041737 | H47: 0.40987134 | L47: =I41 -> 0.23253185 | M47: =J41 -> 0.21083594 | N47: =K41 -> 0.19239375 | O47: =L41 -> 0.17940828 | P47: =M41 -> 0.16966626
C48: =C49-0.5 -> 9.5 | D48: 0.26025034 | E48: 0.28256955 | F48: 0.30343531 | G48: 0.32304466 | H48: 0.34155599 | K48: =K49-0.5 -> 10 | L48: 0.18998619 | M48: 0.18228054 | N48: 0.17164378 | O48: 0.1635747 | P48: 0.15716771
B49: Entry | C49: =C50-0.5 -> 10 | D49: 0.21113208 | E49: 0.23258139 | F49: 0.25263391 | G49: 0.27147898 | H49: 0.28926883 | J49: Exit | K49: =K50-0.5 -> 10.5 | L49: 0.23253185 | M49: 0.21083594 | N49: 0.19239375 | O49: 0.17940828 | P49: 0.16966626
B50: Multiple | C50: 10.5 | D50: 0.17164378 | E50: 0.19239375 | F50: 0.21179247 | G50: 0.23002311 | H50: 0.24723293 | J50: Multiple | K50: 11 | L50: 0.27232707 | M50: 0.23750301 | N50: 0.21179247 | O50: 0.19424534 | P50: 0.1814114
C51: =C50+0.5 -> 11 | D51: 0.13880631 | E51: 0.15897473 | F51: 0.17782976 | G51: 0.19554946 | H51: 0.21227694 | K51: =K50+0.5 -> 11.5 | L51: 0.30977743 | M51: 0.26254971 | N51: 0.23002311 | O51: 0.20821422 | P51: 0.19249512
C52: =C51+0.5 -> 11.5 | D52: 0.11081699 | E52: 0.13048971 | F52: 0.14888132 | G52: 0.16616551 | H52: 0.18248187 | K52: =K51+0.5 -> 12 | L52: 0.34520051 | M52: 0.28618867 | N52: 0.24723293 | O52: 0.2214194 | P52: 0.20299317
C55: (7 points for data table)
C56: ="IRR Assuming "&TEXT(EntryMultiple,"0.0x")&" Entry Multiple & Operating Scenarios" -> IRR Assuming 10.5x Entry Multiple & Operating Scenarios
D57: Exit Year
D58: =I29 -> 2027 | E58: =J29 -> 2028 | F58: =K29 -> 2029 | G58: =L29 -> 2030 | H58: =M29 -> 2031
D59: =I41 -> 0.23253185 | E59: =J41 -> 0.21083594 | F59: =K41 -> 0.19239375 | G59: =L41 -> 0.17940828 | H59: =M41 -> 0.16966626
C60: 1 | D60: 0.23253185 | E60: 0.21083594 | F60: 0.19239375 | G60: 0.17940828 | H60: 0.16966626
B61: Operating | C61: 2 | D61: 0.31214086 | E61: 0.2721731 | F61: 0.24129933 | G61: 0.22022959 | H61: 0.20477767
B62: Scenario | C62: 3 | D62: 0.39376509 | E62: 0.33389333 | F62: 0.29179365 | G62: 0.26338075 | H62: 0.24269028
C63: 4 | D63: 0.043940906 | E63: 0.059230406 | F63: 0.062756378 | G63: 0.064944694 | H63: 0.06644203
C65: Operating Scenario | D65: 1
XX1000: 127155

Sheet DebtSched
B1: =Summary!$B$3 -> ($ in millions, fiscal year ending December 31)
B2: Debt Schedule
F3: Projection Period
E4: =IncStmt!$I$4 -> Pro Forma | F4: 1 | G4: =F4+1 -> 2 | H4: =G4+1 -> 3 | I4: =H4+1 -> 4 | J4: =I4+1 -> 5 | K4: =J4+1 -> 6 | L4: =K4+1 -> 7 | M4: =L4+1 -> 8 | N4: =M4+1 -> 9 | O4: =N4+1 -> 10
E5: =IncStmt!$I$5 -> 2024 | F5: =IncStmt!$I$5+F4 -> 2025 | G5: =IncStmt!$I$5+G4 -> 2026 | H5: =IncStmt!$I$5+H4 -> 2027 | I5: =IncStmt!$I$5+I4 -> 2028 | J5: =IncStmt!$I$5+J4 -> 2029 | K5: =IncStmt!$I$5+K4 -> 2030 | L5: =IncStmt!$I$5+L4 -> 2031 | M5: =IncStmt!$I$5+M4 -> 2032 | ... O5: =IncStmt!$I$5+O4 -> 2034
B6: Forward SOFR Curve | E6: 0.05 | F6: 0.046 | G6: 0.042 | H6: 0.037 | I6: 0.037 | J6: 0.037 | K6: 0.037 | L6: 0.037 | M6: 0.037 | N6: 0.037 | O6: 0.037
B7: Minimum Cash Balance | D7: 0
B9: Cash Flow from Operating Activities | F9: =CFStmt!F21 -> 317.98752 | G9: =CFStmt!G21 -> 334.83854 | H9: =CFStmt!H21 -> 359.38066 | I9: =CFStmt!I21 -> 394.95406 | J9: =CFStmt!J21 -> 436.81683 | K9: =CFStmt!K21 -> 474.92025 | L9: =CFStmt!L21 -> 518.66611 | M9: =CFStmt!M21 -> 534.33245 | ... O9: =CFStmt!O21 -> 641.80791
B10: Cash Flow from Investing Activities | F10: =CFStmt!F26 -> -166.7776 | G10: =CFStmt!G26 -> -170.94704 | H10: =CFStmt!H26 -> -177.78492 | I10: =CFStmt!I26 -> -185.78524 | J10: =CFStmt!J26 -> -192.28773 | K10: =CFStmt!K26 -> -199.0178 | L10: =CFStmt!L26 -> -205.98342 | M10: =CFStmt!M26 -> -213.19284 | ... O10: =CFStmt!O26 -> -228.3775
B11: Cash Flow Available for Debt Repayments | F11: =SUM(F9:F10) -> 151.20992 | G11: =SUM(G9:G10) -> 163.8915 | H11: =SUM(H9:H10) -> 181.59574 | I11: =SUM(I9:I10) -> 209.16882 | J11: =SUM(J9:J10) -> 244.5291 | K11: =SUM(K9:K10) -> 275.90245 | L11: =SUM(L9:L10) -> 312.68269 | M11: =SUM(M9:M10) -> 321.13961 | ... O11: =SUM(O9:O10) -> 413.43041
B12: Total Mandatory Repayments | F12: =F40+F55+F70+F82+F93 -> -157.5 | G12: =G40+G55+G70+G82+G93 -> -157.5 | H12: =H40+H55+H70+H82+H93 -> -157.5 | I12: =I40+I55+I70+I82+I93 -> -157.5 | J12: =J40+J55+J70+J82+J93 -> -82.5 | K12: =K40+K55+K70+K82+K93 -> -20 | L12: =L40+L55+L70+L82+L93 -> -1573.7025 | M12: =M40+M55+M70+M82+M93 -> -1000 | ... O12: =O40+O55+O70+O82+O93 -> -1000 | P12: (5 points for the row)
B13: Cash from Balance Sheet | F13: =IF(CashBalRepay=1,BalSheet!H6-DebtSched!$D$7,0) -> 0 | G13: =IF(CashBalRepay=1,BalSheet!I6-DebtSched!$D$7,0) -> 0 | H13: =IF(CashBalRepay=1,BalSheet!J6-DebtSched!$D$7,0) -> 0 | I13: =IF(CashBalRepay=1,BalSheet!K6-DebtSched!$D$7,0) -> 0 | J13: =IF(CashBalRepay=1,BalSheet!L6-DebtSched!$D$7,0) -> 0 | K13: =IF(CashBalRepay=1,BalSheet!M6-DebtSched!$D$7,0) -> 0 | L13: =IF(CashBalRepay=1,BalSheet!N6-DebtSched!$D$7,0) -> 0 | M13: =IF(CashBalRepay=1,BalSheet!O6-DebtSched!$D$7,0) -> 0 | ... O13: =IF(CashBalRepay=1,BalSheet!Q6-DebtSched!$D$7,0) -> 0
B14: Cash Available for Optional Debt Repayments | F14: =SUM(F11:F13) -> -6.2900801 | G14: =SUM(G11:G13) -> 6.3914997 | H14: =SUM(H11:H13) -> 24.095738 | I14: =SUM(I11:I13) -> 51.668818 | J14: =SUM(J11:J13) -> 162.0291 | K14: =SUM(K11:K13) -> 255.90245 | L14: =SUM(L11:L13) -> -1261.0198 | M14: =SUM(M11:M13) -> -678.86039 | ... O14: =SUM(O11:O13) -> -586.56959
B16: Revolving Credit Facility
B17: Revolving Credit Facility Size | E17: {=INDEX(Financing!D8:H8,FinStructure)} -> 500
B18: Spread | E18: 0.035
B19: SOFR Floor | E19: 0
B20: Term | E20: 7
B21: Commitment Fee on Unused Portion | E21: 0.005
B23: Beginning Balance | F23: =BalSheet!H24 -> 0 | G23: =F25 -> 6.2900801 | H23: =G25 -> 0 | I23: =H25 -> 0 | J23: =I25 -> 0 | K23: =J25 -> 0 | L23: =K25 -> 0 | M23: =L25 -> 1261.0198 | N23: =M25 -> 1939.8802 | O23: =N25 -> 1540.8896 | P23: (1 point for the row)
B24: Drawdown / (Repayment) | F24: =IF(F23>0,-MIN(F14,F23),-MIN(F14,0)) -> 6.2900801 | G24: =IF(G23>0,-MIN(G14,G23),-MIN(G14,0)) -> -6.2900801 | H24: =IF(H23>0,-MIN(H14,H23),-MIN(H14,0)) -> 0 | I24: =IF(I23>0,-MIN(I14,I23),-MIN(I14,0)) -> 0 | J24: =IF(J23>0,-MIN(J14,J23),-MIN(J14,0)) -> 0 | K24: =IF(K23>0,-MIN(K14,K23),-MIN(K14,0)) -> 0 | L24: =IF(L23>0,-MIN(L14,L23),-MIN(L14,0)) -> 1261.0198 | M24: =IF(M23>0,-MIN(M14,M23),-MIN(M14,0)) -> 678.86039 | ... O24: =IF(O23>0,-MIN(O14,O23),-MIN(O14,0)) -> 586.56959 | P24: (5 points for the row)
B25: Ending Balance | F25: =SUM(F23:F24) -> 6.2900801 | G25: =SUM(G23:G24) -> 0 | H25: =SUM(H23:H24) -> 0 | I25: =SUM(I23:I24) -> 0 | J25: =SUM(J23:J24) -> 0 | K25: =SUM(K23:K24) -> 0 | L25: =SUM(L23:L24) -> 1261.0198 | M25: =SUM(M23:M24) -> 1939.8802 | ... O25: =SUM(O23:O24) -> 2127.4592 | P25: (1 point for the row)
B27: Interest Rate | F27: =MAX($E19,F$6)+$E18 -> 0.081 | G27: =MAX($E19,G$6)+$E18 -> 0.077 | H27: =MAX($E19,H$6)+$E18 -> 0.072 | I27: =MAX($E19,I$6)+$E18 -> 0.072 | J27: =MAX($E19,J$6)+$E18 -> 0.072 | K27: =MAX($E19,K$6)+$E18 -> 0.072 | L27: =MAX($E19,L$6)+$E18 -> 0.072 | M27: =MAX($E19,M$6)+$E18 -> 0.072 | ... O27: =MAX($E19,O$6)+$E18 -> 0.072
B28: Interest Expense | F28: =AVERAGE(F23,F25)*F27 -> 0.25474824 | G28: =AVERAGE(G23,G25)*G27 -> 0.24216808 | H28: =AVERAGE(H23,H25)*H27 -> 0 | I28: =AVERAGE(I23,I25)*I27 -> 0 | J28: =AVERAGE(J23,J25)*J27 -> 0 | K28: =AVERAGE(K23,K25)*K27 -> 0 | L28: =AVERAGE(L23,L25)*L27 -> 45.396712 | M28: =AVERAGE(M23,M25)*M27 -> 115.2324 | ... O28: =AVERAGE(O23,O25)*O27 -> 132.06056
B29: Commitment Fee | F29: =MAX($E$21*($E17-AVERAGE(F23,F25)),0) -> 2.4842748 | G29: =MAX($E$21*($E17-AVERAGE(G23,G25)),0) -> 2.4842748 | H29: =MAX($E$21*($E17-AVERAGE(H23,H25)),0) -> 2.5 | I29: =MAX($E$21*($E17-AVERAGE(I23,I25)),0) -> 2.5 | J29: =MAX($E$21*($E17-AVERAGE(J23,J25)),0) -> 2.5 | K29: =MAX($E$21*($E17-AVERAGE(K23,K25)),0) -> 2.5 | L29: =MAX($E$21*($E17-AVERAGE(L23,L25)),0) -> 0 | M29: =MAX($E$21*($E17-AVERAGE(M23,M25)),0) -> 0 | ... O29: =MAX($E$21*($E17-AVERAGE(O23,O25)),0) -> 0
B30: Administrative Agent Fee | F30: =IF($E$17>0,0.2,0) -> 0.2 | G30: =IF($E$17>0,0.2,0) -> 0.2 | H30: =IF($E$17>0,0.2,0) -> 0.2 | I30: =IF($E$17>0,0.2,0) -> 0.2 | J30: =IF($E$17>0,0.2,0) -> 0.2 | K30: =IF($E$17>0,0.2,0) -> 0.2 | L30: =IF($E$17>0,0.2,0) -> 0.2 | M30: =IF($E$17>0,0.2,0) -> 0.2 | ... O30: =IF($E$17>0,0.2,0) -> 0.2
B32: Term Loan A
B33: =B32&" Size" -> Term Loan A Size | E33: =Summary!D10 -> 500
B34: Spread | E34: 0.035
B35: SOFR Floor | E35: 0.01
B36: Term | E36: 6
B37: Repayment Schedule | F37: 0.125 | G37: 0.125 | H37: 0.125 | I37: 0.125 | J37: 0.125 | K37: =1-SUM(F37:J37) -> 0.375
B39: Beginning Balance | F39: =E33 -> 500 | G39: =F42 -> 437.5 | H39: =G42 -> 374.89858 | I39: =H42 -> 288.30284 | J39: =I42 -> 174.13402 | K39: =J42 -> 0 | L39: =K42 -> 0 | M39: =L42 -> 0 | N39: =M42 -> 0 | O39: =N42 -> 0 | P39: (1 point for the row)
B40: Mandatory Repayments | F40: =IF(F39>($E$33*F37),-($E$33*F37),IF((F39>0),-F39,0)) -> -62.5 | G40: =IF(G39>($E$33*G37),-($E$33*G37),IF((G39>0),-G39,0)) -> -62.5 | H40: =IF(H39>($E$33*H37),-($E$33*H37),IF((H39>0),-H39,0)) -> -62.5 | I40: =IF(I39>($E$33*I37),-($E$33*I37),IF((I39>0),-I39,0)) -> -62.5 | J40: =IF(J39>($E$33*J37),-($E$33*J37),IF((J39>0),-J39,0)) -> -62.5 | K40: =IF(K39>($E$33*K37),-($E$33*K37),IF((K39>0),-K39,0)) -> 0 | L40: =IF(L39>($E$33*L37),-($E$33*L37),IF((L39>0),-L39,0)) -> 0 | M40: =IF(M39>($E$33*M37),-($E$33*M37),IF((M39>0),-M39,0)) -> 0 | ... O40: =IF(O39>($E$33*O37),-($E$33*O37),IF((O39>0),-O39,0)) -> 0 | P40: (5 point for the row)
B41: Optional Repayments | F41: =IF(AND(CashSweep=1,(DebtSched!F39+DebtSched!F40)>0),-MIN((DebtSched!F39+DebtSched!F40),(DebtSched!F14+DebtSched!F24)),0) -> 0 | G41: =IF(AND(CashSweep=1,(DebtSched!G39+DebtSched!G40)>0),-MIN((DebtSched!G39+DebtSched!G40),(DebtSched!G14+DebtSched!G24)),0) -> -0.10141967 | H41: =IF(AND(CashSweep=1,(DebtSched!H39+DebtSched!H40)>0),-MIN((DebtSched!H39+DebtSched!H40),(DebtSched!H14+DebtSched!H24)),0) -> -24.095738 | I41: =IF(AND(CashSweep=1,(DebtSched!I39+DebtSched!I40)>0),-MIN((DebtSched!I39+DebtSched!I40),(DebtSched!I14+DebtSched!I24)),0) -> -51.668818 | J41: =IF(AND(CashSweep=1,(DebtSched!J39+DebtSched!J40)>0),-MIN((DebtSched!J39+DebtSched!J40),(DebtSched!J14+DebtSched!J24)),0) -> -111.63402 | K41: =IF(AND(CashSweep=1,(DebtSched!K39+DebtSched!K40)>0),-MIN((DebtSched!K39+DebtSched!K40),(DebtSched!K14+DebtSched!K24)),0) -> 0 | L41: =IF(AND(CashSweep=1,(DebtSched!L39+DebtSched!L40)>0),-MIN((DebtSched!L39+DebtSched!L40),(DebtSched!L14+DebtSched!L24)),0) -> 0 | M41: =IF(AND(CashSweep=1,(DebtSched!M39+DebtSched!M40)>0),-MIN((DebtSched!M39+DebtSched!M40),(DebtSched!M14+DebtSched!M24)),0) -> 0 | ... O41: =IF(AND(CashSweep=1,(DebtSched!O39+DebtSched!O40)>0),-MIN((DebtSched!O39+DebtSched!O40),(DebtSched!O14+DebtSched!O24)),0) -> 0 | P41: (5 point for the row)
B42: Ending Balance | F42: =SUM(F39:F41) -> 437.5 | G42: =SUM(G39:G41) -> 374.89858 | H42: =SUM(H39:H41) -> 288.30284 | I42: =SUM(I39:I41) -> 174.13402 | J42: =SUM(J39:J41) -> 0 | K42: =SUM(K39:K41) -> 0 | L42: =SUM(L39:L41) -> 0 | M42: =SUM(M39:M41) -> 0 | ... O42: =SUM(O39:O41) -> 0 | P42: (1 point for the row)
B44: Interest Rate | F44: =MAX($E$35,F6)+$E$34 -> 0.081 | G44: =MAX($E$35,G6)+$E$34 -> 0.077 | H44: =MAX($E$35,H6)+$E$34 -> 0.072 | I44: =MAX($E$35,I6)+$E$34 -> 0.072 | J44: =MAX($E$35,J6)+$E$34 -> 0.072 | K44: =MAX($E$35,K6)+$E$34 -> 0.072 | L44: =MAX($E$35,L6)+$E$34 -> 0.072 | M44: =MAX($E$35,M6)+$E$34 -> 0.072 | ... O44: =MAX($E$35,O6)+$E$34 -> 0.072 | P44: (3 point for the row)
B45: Interest Expense | F45: =((F42+F39)/2)*F44 -> 37.96875 | G45: =((G42+G39)/2)*G44 -> 31.277345 | H45: =((H42+H39)/2)*H44 -> 23.875251 | I45: =((I42+I39)/2)*I44 -> 16.647727 | J45: =((J42+J39)/2)*J44 -> 6.2688249 | K45: =((K42+K39)/2)*K44 -> 0 | L45: =((L42+L39)/2)*L44 -> 0 | M45: =((M42+M39)/2)*M44 -> 0 | ... O45: =((O42+O39)/2)*O44 -> 0 | P45: (3 point for the row)
B47: Term Loan B
B48: =B47&" Size" -> Term Loan B Size | E48: =Summary!D11 -> 2000
B49: Spread | E49: 0.0375
B50: SOFR Floor | E50: 0.01
B51: Term | E51: 7
B52: Repayment (annual amortization, bullet at maturity) | E52: 0.01 | F52: =E52 -> 0.01 | G52: =F52 -> 0.01 | H52: =G52 -> 0.01 | I52: =H52 -> 0.01 | J52: =I52 -> 0.01 | K52: =J52 -> 0.01 | L52: =1-SUM(F52:K52) -> 0.94
B54: Beginning Balance | F54: =E48 -> 2000 | G54: =F57 -> 1980 | H54: =G57 -> 1960 | I54: =H57 -> 1940 | J54: =I57 -> 1920 | K54: =J57 -> 1849.6049 | L54: =K57 -> 1573.7025 | M54: =L57 -> 0 | N54: =M57 -> 0 | O54: =N57 -> 0 | P54: (5 point for the row)
B55: Mandatory Repayments | F55: =IF(F54>($E$48*F52),-($E$48*F52),IF((F54>0),-F54,0)) -> -20 | G55: =IF(G54>($E$48*G52),-($E$48*G52),IF((G54>0),-G54,0)) -> -20 | H55: =IF(H54>($E$48*H52),-($E$48*H52),IF((H54>0),-H54,0)) -> -20 | I55: =IF(I54>($E$48*I52),-($E$48*I52),IF((I54>0),-I54,0)) -> -20 | J55: =IF(J54>($E$48*J52),-($E$48*J52),IF((J54>0),-J54,0)) -> -20 | K55: =IF(K54>($E$48*K52),-($E$48*K52),IF((K54>0),-K54,0)) -> -20 | L55: =IF(L54>($E$48*L52),-($E$48*L52),IF((L54>0),-L54,0)) -> -1573.7025 | M55: =IF(M54>($E$48*M52),-($E$48*M52),IF((M54>0),-M54,0)) -> 0 | ... O55: =IF(O54>($E$48*O52),-($E$48*O52),IF((O54>0),-O54,0)) -> 0 | P55: (5 point for the row)
B56: Optional Repayments | F56: =IF(AND(CashSweep =1,(DebtSched!F54+DebtSched!F55)>0), -MIN((DebtSched!F54+DebtSched!F55),(DebtSched!F14+DebtSched!F24+DebtSched!F41)),0) -> 0 | G56: =IF(AND(CashSweep =1,(DebtSched!G54+DebtSched!G55)>0), -MIN((DebtSched!G54+DebtSched!G55),(DebtSched!G14+DebtSched!G24+DebtSched!G41)),0) -> 0 | H56: =IF(AND(CashSweep =1,(DebtSched!H54+DebtSched!H55)>0), -MIN((DebtSched!H54+DebtSched!H55),(DebtSched!H14+DebtSched!H24+DebtSched!H41)),0) -> 0 | I56: =IF(AND(CashSweep =1,(DebtSched!I54+DebtSched!I55)>0), -MIN((DebtSched!I54+DebtSched!I55),(DebtSched!I14+DebtSched!I24+DebtSched!I41)),0) -> 0 | J56: =IF(AND(CashSweep =1,(DebtSched!J54+DebtSched!J55)>0), -MIN((DebtSched!J54+DebtSched!J55),(DebtSched!J14+DebtSched!J24+DebtSched!J41)),0) -> -50.395079 | K56: =IF(AND(CashSweep =1,(DebtSched!K54+DebtSched!K55)>0), -MIN((DebtSched!K54+DebtSched!K55),(DebtSched!K14+DebtSched!K24+DebtSched!K41)),0) -> -255.90245 | L56: =IF(AND(CashSweep =1,(DebtSched!L54+DebtSched!L55)>0), -MIN((DebtSched!L54+DebtSched!L55),(DebtSched!L14+DebtSched!L24+DebtSched!L41)),0) -> 0 | M56: =IF(AND(CashSweep =1,(DebtSched!M54+DebtSched!M55)>0), -MIN((DebtSched!M54+DebtSched!M55),(DebtSched!M14+DebtSched!M24+DebtSched!M41)),0) -> 0 | ... O56: =IF(AND(CashSweep =1,(DebtSched!O54+DebtSched!O55)>0), -MIN((DebtSched!O54+DebtSched!O55),(DebtSched!O14+DebtSched!O24+DebtSched!O41)),0) -> 0 | P56: (3 point for the row)
B57: Ending Balance | F57: =SUM(F54:F56) -> 1980 | G57: =SUM(G54:G56) -> 1960 | H57: =SUM(H54:H56) -> 1940 | I57: =SUM(I54:I56) -> 1920 | J57: =SUM(J54:J56) -> 1849.6049 | K57: =SUM(K54:K56) -> 1573.7025 | L57: =SUM(L54:L56) -> 0 | M57: =SUM(M54:M56) -> 0 | ... O57: =SUM(O54:O56) -> 0 | P57: (3 point for the row)
B59: Interest Rate | F59: =MAX($E$50,F6)+$E$49 -> 0.0835 | G59: =MAX($E$50,G6)+$E$49 -> 0.0795 | H59: =MAX($E$50,H6)+$E$49 -> 0.0745 | I59: =MAX($E$50,I6)+$E$49 -> 0.0745 | J59: =MAX($E$50,J6)+$E$49 -> 0.0745 | K59: =MAX($E$50,K6)+$E$49 -> 0.0745 | L59: =MAX($E$50,L6)+$E$49 -> 0.0745 | M59: =MAX($E$50,M6)+$E$49 -> 0.0745 | ... O59: =MAX($E$50,O6)+$E$49 -> 0.0745 | P59: (3 point for the row)
B60: Interest Expense | F60: =((F54+F57)/2)*F59 -> 166.165 | G60: =((G54+G57)/2)*G59 -> 156.615 | H60: =((H54+H57)/2)*H59 -> 145.275 | I60: =((I54+I57)/2)*I59 -> 143.785 | J60: =((J54+J57)/2)*J59 -> 140.41778 | K60: =((K54+K57)/2)*K59 -> 127.5182 | L60: =((L54+L57)/2)*L59 -> 58.620417 | M60: =((M54+M57)/2)*M59 -> 0 | ... O60: =((O54+O57)/2)*O59 -> 0 | P60: (3 point for the row)
B62: Second Lien
B63: =B62&" Size" -> Second Lien Size | E63: =Summary!D12 -> 300
B64: Spread | E64: 0.045
B65: SOFR Floor | E65: 0
B66: Term | E66: 3
F67: 0.25 | G67: 0.25 | H67: 0.25 | I67: 0.25
B69: Beginning Balance | F69: =BalSheet!H28 -> 300 | G69: =BalSheet!I28 -> 225 | H69: =BalSheet!J28 -> 150 | I69: =BalSheet!K28 -> 75 | J69: =BalSheet!L28 -> 0 | K69: =BalSheet!M28 -> 0 | L69: =BalSheet!N28 -> 0 | M69: =BalSheet!O28 -> 0 | ... O69: =BalSheet!Q28 -> 0
B70: Mandatory Repayments | F70: =-$E$63*F67 -> -75 | G70: =-$E$63*G67 -> -75 | H70: =-$E$63*H67 -> -75 | I70: =-$E$63*I67 -> -75 | P70: (1 point for the row)
B71: Ending Balance | F71: =F69+F70 -> 225 | G71: =G69+G70 -> 150 | H71: =H69+H70 -> 75 | I71: =I69+I70 -> 0 | J71: =J69+J70 -> 0 | K71: =K69+K70 -> 0 | L71: =L69+L70 -> 0 | M71: =M69+M70 -> 0 | ... O71: =O69+O70 -> 0
B73: Interest Rate | F73: =IF(F$6>$E65,F$6,$E65)+$E$64 -> 0.091 | G73: =IF(G$6>$E65,G$6,$E65)+$E$64 -> 0.087 | H73: =IF(H$6>$E65,H$6,$E65)+$E$64 -> 0.082 | I73: =IF(I$6>$E65,I$6,$E65)+$E$64 -> 0.082 | J73: =IF(J$6>$E65,J$6,$E65)+$E$64 -> 0.082 | K73: =IF(K$6>$E65,K$6,$E65)+$E$64 -> 0.082 | L73: =IF(L$6>$E65,L$6,$E65)+$E$64 -> 0.082 | M73: =IF(M$6>$E65,M$6,$E65)+$E$64 -> 0.082 | ... O73: =IF(O$6>$E65,O$6,$E65)+$E$64 -> 0.082
B74: Interest Expense | F74: =AVERAGE(F69,F71)*F73 -> 23.8875 | G74: =AVERAGE(G69,G71)*G73 -> 16.3125 | H74: =AVERAGE(H69,H71)*H73 -> 9.225 | I74: =AVERAGE(I69,I71)*I73 -> 3.075 | J74: =AVERAGE(J69,J71)*J73 -> 0 | K74: =AVERAGE(K69,K71)*K73 -> 0 | L74: =AVERAGE(L69,L71)*L73 -> 0 | M74: =AVERAGE(M69,M71)*M73 -> 0 | ... O74: =AVERAGE(O69,O71)*O73 -> 0
B76: Senior Notes
B77: =B76&" Size" -> Senior Notes Size | E77: =Summary!D13 -> 1000
B78: Coupon | E78: 0.0875
B79: Term | E79: 10
B81: Beginning Balance | F81: =BalSheet!H29 -> 1000 | G81: =BalSheet!I29 -> 1000 | H81: =BalSheet!J29 -> 1000 | I81: =BalSheet!K29 -> 1000 | J81: =BalSheet!L29 -> 1000 | K81: =BalSheet!M29 -> 1000 | L81: =BalSheet!N29 -> 1000 | M81: =BalSheet!O29 -> 1000 | ... O81: =BalSheet!Q29 -> 1000
B82: Maturity Repayment | F82: =IF($E$79=F4,-$E$77,0) -> 0 | G82: =IF($E$79=G4,-$E$77,0) -> 0 | H82: =IF($E$79=H4,-$E$77,0) -> 0 | I82: =IF($E$79=I4,-$E$77,0) -> 0 | J82: =IF($E$79=J4,-$E$77,0) -> 0 | K82: =IF($E$79=K4,-$E$77,0) -> 0 | L82: =IF($E$79=L4,-$E$77,0) -> 0 | M82: =IF($E$79=M4,-$E$77,0) -> 0 | ... O82: =IF($E$79=O4,-$E$77,0) -> -1000 | P82: (3 point for the row)
B83: Ending Balance | F83: =F81+F82 -> 1000 | G83: =G81+G82 -> 1000 | H83: =H81+H82 -> 1000 | I83: =I81+I82 -> 1000 | J83: =J81+J82 -> 1000 | K83: =K81+K82 -> 1000 | L83: =L81+L82 -> 1000 | M83: =M81+M82 -> 1000 | ... O83: =O81+O82 -> 0
B85: Interest Expense | F85: =F81*$E$78 -> 87.5 | G85: =G81*$E$78 -> 87.5 | H85: =H81*$E$78 -> 87.5 | I85: =I81*$E$78 -> 87.5 | J85: =J81*$E$78 -> 87.5 | K85: =K81*$E$78 -> 87.5 | L85: =L81*$E$78 -> 87.5 | M85: =M81*$E$78 -> 87.5 | ... O85: =O81*$E$78 -> 87.5 | P85: (1 point for the row)
B87: Senior Subordinated Notes
B88: =B87&" Size" -> Senior Subordinated Notes Size | E88: =Summary!D14 -> 1000
B89: Coupon | E89: 0.09
B90: Term | E90: 8
B92: Beginning Balance | F92: =BalSheet!H31 -> 1000 | G92: =BalSheet!I31 -> 1000 | H92: =BalSheet!J31 -> 1000 | I92: =BalSheet!K31 -> 1000 | J92: =BalSheet!L31 -> 1000 | K92: =BalSheet!M31 -> 1000 | L92: =BalSheet!N31 -> 1000 | M92: =BalSheet!O31 -> 1000 | ... O92: =BalSheet!Q31 -> 0
B93: Maturity Repayment | F93: =IF($E$90=F4,-$E$88,0) -> 0 | G93: =IF($E$90=G4,-$E$88,0) -> 0 | H93: =IF($E$90=H4,-$E$88,0) -> 0 | I93: =IF($E$90=I4,-$E$88,0) -> 0 | J93: =IF($E$90=J4,-$E$88,0) -> 0 | K93: =IF($E$90=K4,-$E$88,0) -> 0 | L93: =IF($E$90=L4,-$E$88,0) -> 0 | M93: =IF($E$90=M4,-$E$88,0) -> -1000 | ... O93: =IF($E$90=O4,-$E$88,0) -> 0 | P93: (3 point for the row)
B94: Ending Balance | F94: =F92+F93 -> 1000 | G94: =G92+G93 -> 1000 | H94: =H92+H93 -> 1000 | I94: =I92+I93 -> 1000 | J94: =J92+J93 -> 1000 | K94: =K92+K93 -> 1000 | L94: =L92+L93 -> 1000 | M94: =M92+M93 -> 0 | ... O94: =O92+O93 -> 0
B96: Interest Expense | F96: =F92*$E$89 -> 90 | G96: =G92*$E$89 -> 90 | H96: =H92*$E$89 -> 90 | I96: =I92*$E$89 -> 90 | J96: =J92*$E$89 -> 90 | K96: =K92*$E$89 -> 90 | L96: =L92*$E$89 -> 90 | M96: =M92*$E$89 -> 90 | ... O96: =O92*$E$89 -> 0 | P96: (1 point for the row)
XX1000: 127155

Sheet Financing
B1: =Summary!$B$3 -> ($ in millions, fiscal year ending December 31)
B2: Assumptions: Financing Structure & Fees
B4: Financing Structures | J4: Purchase Price
D5: Structure
D6: 1 | E6: =D6+1 -> 2 | F6: =E6+1 -> 3 | G6: =F6+1 -> 4 | H6: =G6+1 -> 5 | J6: Entry EBITDA Multiple | N6: =RetAnalysis!E6 -> 10.5
B7: Sources of Funds | D7: ="Structure "&D6 -> Structure 1 | E7: ="Structure "&E6 -> Structure 2 | F7: ="Structure "&F6 -> Structure 3 | G7: ="Structure "&G6 -> Structure 4 | H7: Status Quo | J7: ="LTM "&TEXT(Summary!G26,"mm/dd/yyyy")&" EBITDA" -> LTM 09/30/2024 EBITDA | N7: =IncStmt!H17 -> 637.94682
B8: Revolving Credit Facility Size | D8: 500 | E8: 500 | F8: 500 | G8: 500 | H8: 0 | J8: Enterprise Value | N8: =N6*N7 -> 6698.4417
B9: Revolving Credit Facility Draw | H9: 0
B10: Term Loan A | D10: 1000 | E10: 750 | F10: 500 | G10: 500 | H10: 0 | J10: Less: Total Debt | N10: =-SUM(N19:N20) -> -1500
B11: Term Loan B | D11: 1750 | E11: 2000 | F11: 2000 | G11: 1500 | H11: 0 | J11: Less: Preferred Stock | N11: 0 | O11: (1 point)
B12: 2nd Lien | F12: 300 | G12: 600 | H12: 0 | J12: Less: Noncontrolling Interest | N12: =-BalSheet!E37 -> 0 | O12: (1 point)
B13: Senior Notes | D13: 1000 | E13: 1000 | F13: 1000 | G13: 1500 | H13: 0 | J13: Plus: Cash and Cash Equivalents | N13: =BalSheet!E6 -> 250 | O13: (1 point)
B14: Senior Subordinated Notes | D14: 250 | E14: 650 | F14: 1000 | G14: 1200 | H14: 0 | J14: Equity Purchase Price | N14: =N8+SUM(N10:N13) -> 5448.4417
B15: Equity Contribution | D15: =SUM(D22:D28)-SUM(D9:D14,D16) -> 2868.4417 | E15: =SUM(E22:E28)-SUM(E9:E14,E16) -> 2478.4417 | F15: =SUM(F22:F28)-SUM(F9:F14,F16) -> 2088.4417 | G15: =SUM(G22:G28)-SUM(G9:G14,G16) -> 1598.4417 | H15: =SUM(H22:H28)-SUM(H9:H14,H16) -> 0
B16: Cash on Hand | D16: =BalSheet!$E$6 -> 250 | E16: =BalSheet!$E$6 -> 250 | F16: =BalSheet!$E$6 -> 250 | G16: =BalSheet!$E$6 -> 250 | H16: 0
B17: Total Sources of Funds | D17: =SUM(D9:D16) -> 7118.4417 | E17: =SUM(E9:E16) -> 7128.4417 | F17: =SUM(F9:F16) -> 7138.4417 | G17: =SUM(G9:G16) -> 7148.4417 | H17: =SUM(H9:H16) -> 0
J18: Existing Debt
B19: Equity (%) of Sources | D19: =D15/D17 -> 0.40295921 | E19: =E15/E17 -> 0.34768352 | F19: =F15/F17 -> 0.29256268 | G19: =G15/G17 -> 0.22360701 | J19: Existing Term Loan | N19: =BalSheet!E27 -> 1000
J20: Existing Senior Notes | N20: =BalSheet!E30 -> 500
B21: Uses of Funds
B22: Equity Purchase Price | D22: =N14 -> 5448.4417 | E22: =D22 -> 5448.4417 | F22: =E22 -> 5448.4417 | G22: =F22 -> 5448.4417 | H22: 0
B23: Repay Existing Bank Debt | D23: =N19 -> 1000 | E23: =D23 -> 1000 | F23: =E23 -> 1000 | G23: =F23 -> 1000 | H23: 0
B24: Repay Existing Senior Notes | D24: =N20 -> 500 | E24: =D24 -> 500 | F24: =E24 -> 500 | G24: =F24 -> 500 | H24: 0
B25: Tender / Call Premium | D25: 20 | E25: =D25 -> 20 | F25: =E25 -> 20 | G25: =F25 -> 20 | H25: 0
B26: Financing Fees | D26: 120 | E26: 130 | F26: 140 | G26: 150 | H26: 0
B27: Other Fees & Expenses | D27: 30 | E27: =D27 -> 30 | F27: =E27 -> 30 | G27: =F27 -> 30 | H27: 0
B29: Total Uses of Funds | D29: =SUM(D22:D28) -> 7118.4417 | E29: =SUM(E22:E28) -> 7128.4417 | F29: =SUM(F22:F28) -> 7138.4417 | G29: =SUM(G22:G28) -> 7148.4417 | H29: =SUM(H22:H28) -> 0
B32: Financing Fees
G33: Fees
D34: =INDEX(D7:H7,FinStructure) -> Structure 3 | F34: Size | G34: (%) | H34: ($)
B35: Revolving Credit Facility | F35: {=INDEX(D8:H8,FinStructure)} -> 500 | G35: 0.015 | H35: =F35*G35 -> 7.5
B36: =B10 -> Term Loan A | F36: {=INDEX(D10:H10,FinStructure)} -> 500 | G36: 0.015 | H36: =F36*G36 -> 7.5
B37: =B11 -> Term Loan B | F37: {=INDEX(D11:H11,FinStructure)} -> 2000 | G37: 0.015 | H37: =F37*G37 -> 30
B38: =B12 -> 2nd Lien | F38: {=INDEX(D12:H12,FinStructure)} -> 300 | G38: 0.02 | H38: =F38*G38 -> 6
B39: =B13 -> Senior Notes | F39: {=INDEX(D13:H13,FinStructure)} -> 1000 | G39: 0.015 | H39: =F39*G39 -> 15
B40: =B14 -> Senior Subordinated Notes | F40: {=INDEX(D14:H14,FinStructure)} -> 1000 | G40: 0.015 | H40: =F40*G40 -> 15
B41: Senior Bridge Facility | F41: =F39 -> 1000 | G41: 0.015 | H41: =F41*G41 -> 15
B42: Senior Subordinated Bridge Facility | F42: =F40 -> 1000 | G42: 0.015 | H42: =F42*G42 -> 15
B43: Other Financing Fees | H43: =IF(FinStructure=1,D26,IF(FinStructure = 2,E26,IF(FinStructure = 3,F26,IF(FinStructure = 4,G26,H26))))-SUM(H35:H42) -> 29
B44: Total Financing Fees | H44: =SUM(H35:H43) -> 140
J45: (10 points for amortization table)
B46: Amortization of Financing Fees
E47: 1 | F47: =E47+1 -> 2 | G47: =F47+1 -> 3 | H47: =G47+1 -> 4 | I47: =H47+1 -> 5 | J47: =I47+1 -> 6 | K47: =J47+1 -> 7 | L47: =K47+1 -> 8 | M47: =L47+1 -> 9 | N47: =M47+1 -> 10
D48: Term | E48: =IncStmt!$I$5+E47 -> 2025 | F48: =E48+1 -> 2026 | G48: =F48+1 -> 2027 | H48: =G48+1 -> 2028 | I48: =H48+1 -> 2029 | J48: =I48+1 -> 2030 | K48: =J48+1 -> 2031 | L48: =K48+1 -> 2032 | M48: =L48+1 -> 2033 | N48: =M48+1 -> 2034
B49: =B35 -> Revolving Credit Facility | D49: =DebtSched!E20 -> 7 | E49: =IF(E$47<=$D49,$H35/$D49,0) -> 1.0714286 | F49: =IF(F$47<=$D49,$H35/$D49,0) -> 1.0714286 | G49: =IF(G$47<=$D49,$H35/$D49,0) -> 1.0714286 | H49: =IF(H$47<=$D49,$H35/$D49,0) -> 1.0714286 | I49: =IF(I$47<=$D49,$H35/$D49,0) -> 1.0714286 | J49: =IF(J$47<=$D49,$H35/$D49,0) -> 1.0714286 | K49: =IF(K$47<=$D49,$H35/$D49,0) -> 1.0714286 | L49: =IF(L$47<=$D49,$H35/$D49,0) -> 0 | ... N49: =IF(N$47<=$D49,$H35/$D49,0) -> 0
B50: =B36 -> Term Loan A | D50: =DebtSched!E36 -> 6 | E50: =IF(E$47<=$D50,$H36/$D50,0) -> 1.25 | F50: =IF(F$47<=$D50,$H36/$D50,0) -> 1.25 | G50: =IF(G$47<=$D50,$H36/$D50,0) -> 1.25 | H50: =IF(H$47<=$D50,$H36/$D50,0) -> 1.25 | I50: =IF(I$47<=$D50,$H36/$D50,0) -> 1.25 | J50: =IF(J$47<=$D50,$H36/$D50,0) -> 1.25 | K50: =IF(K$47<=$D50,$H36/$D50,0) -> 0 | L50: =IF(L$47<=$D50,$H36/$D50,0) -> 0 | ... N50: =IF(N$47<=$D50,$H36/$D50,0) -> 0
B51: =B37 -> Term Loan B | D51: =DebtSched!E51 -> 7 | E51: =IF(E$47<=$D51,$H37/$D51,0) -> 4.2857143 | F51: =IF(F$47<=$D51,$H37/$D51,0) -> 4.2857143 | G51: =IF(G$47<=$D51,$H37/$D51,0) -> 4.2857143 | H51: =IF(H$47<=$D51,$H37/$D51,0) -> 4.2857143 | I51: =IF(I$47<=$D51,$H37/$D51,0) -> 4.2857143 | J51: =IF(J$47<=$D51,$H37/$D51,0) -> 4.2857143 | K51: =IF(K$47<=$D51,$H37/$D51,0) -> 4.2857143 | L51: =IF(L$47<=$D51,$H37/$D51,0) -> 0 | ... N51: =IF(N$47<=$D51,$H37/$D51,0) -> 0
B52: =B38 -> 2nd Lien | D52: =DebtSched!E66 -> 3 | E52: =IF(E$47<=$D52,$H38/$D52,0) -> 2 | F52: =IF(F$47<=$D52,$H38/$D52,0) -> 2 | G52: =IF(G$47<=$D52,$H38/$D52,0) -> 2 | H52: =IF(H$47<=$D52,$H38/$D52,0) -> 0 | I52: =IF(I$47<=$D52,$H38/$D52,0) -> 0 | J52: =IF(J$47<=$D52,$H38/$D52,0) -> 0 | K52: =IF(K$47<=$D52,$H38/$D52,0) -> 0 | L52: =IF(L$47<=$D52,$H38/$D52,0) -> 0 | ... N52: =IF(N$47<=$D52,$H38/$D52,0) -> 0
B53: =B39 -> Senior Notes | D53: =DebtSched!E79 -> 10 | E53: =IF(E$47<=$D53,$H39/$D53,0) -> 1.5 | F53: =IF(F$47<=$D53,$H39/$D53,0) -> 1.5 | G53: =IF(G$47<=$D53,$H39/$D53,0) -> 1.5 | H53: =IF(H$47<=$D53,$H39/$D53,0) -> 1.5 | I53: =IF(I$47<=$D53,$H39/$D53,0) -> 1.5 | J53: =IF(J$47<=$D53,$H39/$D53,0) -> 1.5 | K53: =IF(K$47<=$D53,$H39/$D53,0) -> 1.5 | L53: =IF(L$47<=$D53,$H39/$D53,0) -> 1.5 | ... N53: =IF(N$47<=$D53,$H39/$D53,0) -> 1.5
B54: =B40 -> Senior Subordinated Notes | D54: =DebtSched!E90 -> 8 | E54: =IF(E$47<=$D54,$H40/$D54,0) -> 1.875 | F54: =IF(F$47<=$D54,$H40/$D54,0) -> 1.875 | G54: =IF(G$47<=$D54,$H40/$D54,0) -> 1.875 | H54: =IF(H$47<=$D54,$H40/$D54,0) -> 1.875 | I54: =IF(I$47<=$D54,$H40/$D54,0) -> 1.875 | J54: =IF(J$47<=$D54,$H40/$D54,0) -> 1.875 | K54: =IF(K$47<=$D54,$H40/$D54,0) -> 1.875 | L54: =IF(L$47<=$D54,$H40/$D54,0) -> 1.875 | ... N54: =IF(N$47<=$D54,$H40/$D54,0) -> 0
B55: =B41 -> Senior Bridge Facility | D55: =D53 -> 10 | E55: =IF(E$47<=$D55,$H41/$D55,0) -> 1.5 | F55: =IF(F$47<=$D55,$H41/$D55,0) -> 1.5 | G55: =IF(G$47<=$D55,$H41/$D55,0) -> 1.5 | H55: =IF(H$47<=$D55,$H41/$D55,0) -> 1.5 | I55: =IF(I$47<=$D55,$H41/$D55,0) -> 1.5 | J55: =IF(J$47<=$D55,$H41/$D55,0) -> 1.5 | K55: =IF(K$47<=$D55,$H41/$D55,0) -> 1.5 | L55: =IF(L$47<=$D55,$H41/$D55,0) -> 1.5 | ... N55: =IF(N$47<=$D55,$H41/$D55,0) -> 1.5
B56: =B42 -> Senior Subordinated Bridge Facility | D56: =D54 -> 8 | E56: =IF(E$47<=$D56,$H42/$D56,0) -> 1.875 | F56: =IF(F$47<=$D56,$H42/$D56,0) -> 1.875 | G56: =IF(G$47<=$D56,$H42/$D56,0) -> 1.875 | H56: =IF(H$47<=$D56,$H42/$D56,0) -> 1.875 | I56: =IF(I$47<=$D56,$H42/$D56,0) -> 1.875 | J56: =IF(J$47<=$D56,$H42/$D56,0) -> 1.875 | K56: =IF(K$47<=$D56,$H42/$D56,0) -> 1.875 | L56: =IF(L$47<=$D56,$H42/$D56,0) -> 1.875 | ... N56: =IF(N$47<=$D56,$H42/$D56,0) -> 0
B57: =B43 -> Other Financing Fees | D57: 10 | E57: =IF(E$47<=$D57,$H43/$D57,0) -> 2.9 | F57: =IF(F$47<=$D57,$H43/$D57,0) -> 2.9 | G57: =IF(G$47<=$D57,$H43/$D57,0) -> 2.9 | H57: =IF(H$47<=$D57,$H43/$D57,0) -> 2.9 | I57: =IF(I$47<=$D57,$H43/$D57,0) -> 2.9 | J57: =IF(J$47<=$D57,$H43/$D57,0) -> 2.9 | K57: =IF(K$47<=$D57,$H43/$D57,0) -> 2.9 | L57: =IF(L$47<=$D57,$H43/$D57,0) -> 2.9 | ... N57: =IF(N$47<=$D57,$H43/$D57,0) -> 2.9
B58: Annual Amortization | E58: =SUM(E49:E57) -> 18.257143 | F58: =SUM(F49:F57) -> 18.257143 | G58: =SUM(G49:G57) -> 18.257143 | H58: =SUM(H49:H57) -> 16.257143 | I58: =SUM(I49:I57) -> 16.257143 | J58: =SUM(J49:J57) -> 16.257143 | K58: =SUM(K49:K57) -> 15.007143 | L58: =SUM(L49:L57) -> 9.65 | ... N58: =SUM(N49:N57) -> 5.9
XX1000: 127155

Sheet Assumptions1
B2: Assumptions: Income Statement & Cash Flow
F3: Projection Period
F4: 1 | G4: =F4+1 -> 2 | H4: =G4+1 -> 3 | I4: =H4+1 -> 4 | J4: =I4+1 -> 5 | K4: =J4+1 -> 6 | L4: =K4+1 -> 7 | M4: =L4+1 -> 8 | N4: =M4+1 -> 9 | O4: =N4+1 -> 10
F5: =Summary!$H$26+F4 -> 2025 | G5: =Summary!$H$26+G4 -> 2026 | H5: =Summary!$H$26+H4 -> 2027 | I5: =Summary!$H$26+I4 -> 2028 | J5: =Summary!$H$26+J4 -> 2029 | K5: =Summary!$H$26+K4 -> 2030 | L5: =Summary!$H$26+L4 -> 2031 | M5: =Summary!$H$26+M4 -> 2032 | ... O5: =Summary!$H$26+O4 -> 2034 | Q5: Other Assumptions:
B7: Income Statement Assumptions | Q7: Income Tax Rate | S7: 0.25
B8: Sales (% growth) | F8: =INDEX(F9:F12,OpScenario) -> 0.03 | G8: {=INDEX(G9:G12,OpScenario)} -> 0.025 | H8: {=INDEX(H9:H12,OpScenario)} -> 0.04 | I8: {=INDEX(I9:I12,OpScenario)} -> 0.045 | J8: {=INDEX(J9:J12,OpScenario)} -> 0.035 | K8: {=INDEX(K9:K12,OpScenario)} -> 0.035 | L8: {=INDEX(L9:L12,OpScenario)} -> 0.035 | M8: {=INDEX(M9:M12,OpScenario)} -> 0.035 | N8: {=INDEX(N9:N12,OpScenario)} -> 0.035 | O8: {=INDEX(O9:O12,OpScenario)} -> 0.035
B9: Base | E9: 1 | F9: 0.03 | G9: 0.025 | H9: 0.04 | I9: 0.045 | J9: 0.035 | K9: =J9 -> 0.035 | L9: =K9 -> 0.035 | M9: =L9 -> 0.035 | N9: =M9 -> 0.035 | O9: =N9 -> 0.035
B10: Sponsor | E10: =E9+1 -> 2 | F10: 0.04 | G10: 0.045 | H10: 0.05 | I10: 0.055 | J10: 0.04 | K10: =J10 -> 0.04 | L10: =K10 -> 0.04 | M10: =L10 -> 0.04 | N10: =M10 -> 0.04 | O10: =N10 -> 0.04
B11: Management | E11: =E10+1 -> 3 | F11: 0.035 | G11: 0.08 | H11: 0.07 | I11: 0.065 | J11: 0.05 | K11: =J11 -> 0.05 | L11: =K11 -> 0.05 | M11: =L11 -> 0.05 | N11: =M11 -> 0.05 | O11: =N11 -> 0.05
B12: Downside | E12: =E11+1 -> 4 | F12: =F9-0.02 -> 0.01 | G12: =G9-0.02 -> 0.005 | H12: =H9-0.02 -> 0.02 | I12: =I9-0.02 -> 0.025 | J12: =J9-0.02 -> 0.015 | K12: =J12 -> 0.015 | L12: =K12 -> 0.015 | M12: =L12 -> 0.015 | N12: =M12 -> 0.015 | O12: =N12 -> 0.015
B14: Cost of Goods Sold (% sales) | F14: {=INDEX(F15:F18,OpScenario)} -> 0.6 | G14: {=INDEX(G15:G18,OpScenario)} -> 0.6 | H14: {=INDEX(H15:H18,OpScenario)} -> 0.6 | I14: {=INDEX(I15:I18,OpScenario)} -> 0.6 | J14: {=INDEX(J15:J18,OpScenario)} -> 0.6 | K14: {=INDEX(K15:K18,OpScenario)} -> 0.6 | L14: {=INDEX(L15:L18,OpScenario)} -> 0.6 | M14: {=INDEX(M15:M18,OpScenario)} -> 0.6 | ... O14: {=INDEX(O15:O18,OpScenario)} -> 0.6
B15: Base | E15: 1 | F15: 0.6 | G15: 0.6 | H15: 0.6 | I15: 0.6 | J15: 0.6 | K15: =J15 -> 0.6 | L15: =K15 -> 0.6 | M15: =L15 -> 0.6 | N15: =M15 -> 0.6 | O15: =N15 -> 0.6
B16: Sponsor | E16: =E15+1 -> 2 | F16: 0.6 | G16: 0.6 | H16: 0.6 | I16: 0.6 | J16: 0.6 | K16: =J16 -> 0.6 | L16: =K16 -> 0.6 | M16: =L16 -> 0.6 | N16: =M16 -> 0.6 | O16: =N16 -> 0.6
B17: Management | E17: =E16+1 -> 3 | F17: 0.59 | G17: 0.59 | H17: 0.59 | I17: 0.59 | J17: 0.59 | K17: =J17 -> 0.59 | L17: =K17 -> 0.59 | M17: =L17 -> 0.59 | N17: =M17 -> 0.59 | O17: =N17 -> 0.59
B18: Downside | E18: =E17+1 -> 4 | F18: 0.61 | G18: 0.61 | H18: 0.61 | I18: 0.61 | J18: 0.61 | K18: =J18 -> 0.61 | L18: =K18 -> 0.61 | M18: =L18 -> 0.61 | N18: =M18 -> 0.61 | O18: =N18 -> 0.61
B20: SG&A (% sales) | F20: {=INDEX(F21:F24,OpScenario)} -> 0.18 | G20: {=INDEX(G21:G24,OpScenario)} -> 0.18 | H20: {=INDEX(H21:H24,OpScenario)} -> 0.18 | I20: {=INDEX(I21:I24,OpScenario)} -> 0.18 | J20: {=INDEX(J21:J24,OpScenario)} -> 0.18 | K20: {=INDEX(K21:K24,OpScenario)} -> 0.18 | L20: {=INDEX(L21:L24,OpScenario)} -> 0.18 | M20: {=INDEX(M21:M24,OpScenario)} -> 0.18 | ... O20: {=INDEX(O21:O24,OpScenario)} -> 0.18
B21: Base | E21: 1 | F21: 0.18 | G21: 0.18 | H21: 0.18 | I21: 0.18 | J21: 0.18 | K21: =J21 -> 0.18 | L21: =K21 -> 0.18 | M21: =L21 -> 0.18 | N21: =M21 -> 0.18 | O21: =N21 -> 0.18
B22: Sponsor | E22: =E21+1 -> 2 | F22: 0.17 | G22: 0.17 | H22: 0.17 | I22: 0.17 | J22: 0.17 | K22: =J22 -> 0.17 | L22: =K22 -> 0.17 | M22: =L22 -> 0.17 | N22: =M22 -> 0.17 | O22: =N22 -> 0.17
B23: Management | E23: =E22+1 -> 3 | F23: 0.17 | G23: 0.17 | H23: 0.17 | I23: 0.17 | J23: 0.17 | K23: =J23 -> 0.17 | L23: =K23 -> 0.17 | M23: =L23 -> 0.17 | N23: =M23 -> 0.17 | O23: =N23 -> 0.17
B24: Downside | E24: =E23+1 -> 4 | F24: 0.19 | G24: 0.19 | H24: 0.19 | I24: 0.19 | J24: 0.19 | K24: =J24 -> 0.19 | L24: =K24 -> 0.19 | M24: =L24 -> 0.19 | N24: =M24 -> 0.19 | O24: =N24 -> 0.19
B26: Other (Income) / Expense (% of sales) | F26: {=INDEX(F27:F30,OpScenario)} -> 0 | G26: {=INDEX(G27:G30,OpScenario)} -> 0 | H26: {=INDEX(H27:H30,OpScenario)} -> 0 | I26: {=INDEX(I27:I30,OpScenario)} -> 0 | J26: {=INDEX(J27:J30,OpScenario)} -> 0 | K26: {=INDEX(K27:K30,OpScenario)} -> 0 | L26: {=INDEX(L27:L30,OpScenario)} -> 0 | M26: {=INDEX(M27:M30,OpScenario)} -> 0 | ... O26: {=INDEX(O27:O30,OpScenario)} -> 0
B27: Base | E27: 1 | F27: 0 | G27: 0 | H27: 0 | I27: 0 | J27: 0 | K27: =J27 -> 0 | L27: =K27 -> 0 | M27: =L27 -> 0 | N27: =M27 -> 0 | O27: =N27 -> 0
B28: Sponsor | E28: =E27+1 -> 2 | F28: 0 | G28: 0 | H28: 0 | I28: 0 | J28: 0 | K28: =J28 -> 0 | L28: =K28 -> 0 | M28: =L28 -> 0 | N28: =M28 -> 0 | O28: =N28 -> 0
B29: Management | E29: =E28+1 -> 3 | F29: 0 | G29: 0 | H29: 0 | I29: 0 | J29: 0 | K29: =J29 -> 0 | L29: =K29 -> 0 | M29: =L29 -> 0 | N29: =M29 -> 0 | O29: =N29 -> 0
B30: Downside | E30: =E29+1 -> 4 | F30: 0 | G30: 0 | H30: 0 | I30: 0 | J30: 0 | K30: =J30 -> 0 | L30: =K30 -> 0 | M30: =L30 -> 0 | N30: =M30 -> 0 | O30: =N30 -> 0
B32: Depreciation (% sales) | F32: {=INDEX(F33:F36,OpScenario)} -> 0.05 | G32: {=INDEX(G33:G36,OpScenario)} -> 0.05 | H32: {=INDEX(H33:H36,OpScenario)} -> 0.05 | I32: {=INDEX(I33:I36,OpScenario)} -> 0.05 | J32: {=INDEX(J33:J36,OpScenario)} -> 0.05 | K32: {=INDEX(K33:K36,OpScenario)} -> 0.05 | L32: {=INDEX(L33:L36,OpScenario)} -> 0.05 | M32: {=INDEX(M33:M36,OpScenario)} -> 0.05 | ... O32: {=INDEX(O33:O36,OpScenario)} -> 0.05
B33: Base | E33: 1 | F33: 0.05 | G33: 0.05 | H33: 0.05 | I33: 0.05 | J33: 0.05 | K33: =J33 -> 0.05 | L33: =K33 -> 0.05 | M33: =L33 -> 0.05 | N33: =M33 -> 0.05 | O33: =N33 -> 0.05
B34: Sponsor | E34: =E33+1 -> 2 | F34: 0.05 | G34: 0.05 | H34: 0.05 | I34: 0.05 | J34: 0.05 | K34: =J34 -> 0.05 | L34: =K34 -> 0.05 | M34: =L34 -> 0.05 | N34: =M34 -> 0.05 | O34: =N34 -> 0.05
B35: Management | E35: =E34+1 -> 3 | F35: 0.05 | G35: 0.05 | H35: 0.05 | I35: 0.05 | J35: 0.05 | K35: =J35 -> 0.05 | L35: =K35 -> 0.05 | M35: =L35 -> 0.05 | N35: =M35 -> 0.05 | O35: =N35 -> 0.05
B36: Downside | E36: =E35+1 -> 4 | F36: 0.05 | G36: 0.05 | H36: 0.05 | I36: 0.05 | J36: 0.05 | K36: =J36 -> 0.05 | L36: =K36 -> 0.05 | M36: =L36 -> 0.05 | N36: =M36 -> 0.05 | O36: =N36 -> 0.05
B38: Amortization (% sales) | F38: {=INDEX(F39:F42,OpScenario)} -> 0.02 | G38: {=INDEX(G39:G42,OpScenario)} -> 0.02 | H38: {=INDEX(H39:H42,OpScenario)} -> 0.02 | I38: {=INDEX(I39:I42,OpScenario)} -> 0.02 | J38: {=INDEX(J39:J42,OpScenario)} -> 0.02 | K38: {=INDEX(K39:K42,OpScenario)} -> 0.02 | L38: {=INDEX(L39:L42,OpScenario)} -> 0.02 | M38: {=INDEX(M39:M42,OpScenario)} -> 0.02 | ... O38: {=INDEX(O39:O42,OpScenario)} -> 0.02
B39: Base | E39: 1 | F39: 0.02 | G39: 0.02 | H39: 0.02 | I39: 0.02 | J39: 0.02 | K39: =J39 -> 0.02 | L39: =K39 -> 0.02 | M39: =L39 -> 0.02 | N39: =M39 -> 0.02 | O39: =N39 -> 0.02
B40: Sponsor | E40: =E39+1 -> 2 | F40: 0.02 | G40: 0.02 | H40: 0.02 | I40: 0.02 | J40: 0.02 | K40: =J40 -> 0.02 | L40: =K40 -> 0.02 | M40: =L40 -> 0.02 | N40: =M40 -> 0.02 | O40: =N40 -> 0.02
B41: Management | E41: =E40+1 -> 3 | F41: 0.02 | G41: 0.02 | H41: 0.02 | I41: 0.02 | J41: 0.02 | K41: =J41 -> 0.02 | L41: =K41 -> 0.02 | M41: =L41 -> 0.02 | N41: =M41 -> 0.02 | O41: =N41 -> 0.02
B42: Downside | E42: =E41+1 -> 4 | F42: 0.02 | G42: 0.02 | H42: 0.02 | I42: 0.02 | J42: 0.02 | K42: =J42 -> 0.02 | L42: =K42 -> 0.02 | M42: =L42 -> 0.02 | N42: =M42 -> 0.02 | O42: =N42 -> 0.02
B44: Cash Flow Statement Assumptions
B45: Capital Expenditures (% sales) | F45: {=INDEX(F46:F49,OpScenario)} -> 0.05 | G45: {=INDEX(G46:G49,OpScenario)} -> 0.05 | H45: {=INDEX(H46:H49,OpScenario)} -> 0.05 | I45: {=INDEX(I46:I49,OpScenario)} -> 0.05 | J45: {=INDEX(J46:J49,OpScenario)} -> 0.05 | K45: {=INDEX(K46:K49,OpScenario)} -> 0.05 | L45: {=INDEX(L46:L49,OpScenario)} -> 0.05 | M45: {=INDEX(M46:M49,OpScenario)} -> 0.05 | ... O45: {=INDEX(O46:O49,OpScenario)} -> 0.05
B46: Base | E46: 1 | F46: 0.05 | G46: 0.05 | H46: 0.05 | I46: 0.05 | J46: 0.05 | K46: =J46 -> 0.05 | L46: =K46 -> 0.05 | M46: =L46 -> 0.05 | N46: =M46 -> 0.05 | O46: =N46 -> 0.05
B47: Sponsor | E47: =E46+1 -> 2 | F47: 0.05 | G47: 0.05 | H47: 0.05 | I47: 0.05 | J47: 0.05 | K47: =J47 -> 0.05 | L47: =K47 -> 0.05 | M47: =L47 -> 0.05 | N47: =M47 -> 0.05 | O47: =N47 -> 0.05
B48: Management | E48: =E47+1 -> 3 | F48: 0.05 | G48: 0.05 | H48: 0.05 | I48: 0.05 | J48: 0.05 | K48: =J48 -> 0.05 | L48: =K48 -> 0.05 | M48: =L48 -> 0.05 | N48: =M48 -> 0.05 | O48: =N48 -> 0.05
B49: Downside | E49: =E48+1 -> 4 | F49: 0.06 | G49: 0.06 | H49: 0.06 | I49: 0.06 | J49: 0.06 | K49: =J49 -> 0.06 | L49: =K49 -> 0.06 | M49: =L49 -> 0.06 | N49: =M49 -> 0.06 | O49: =N49 -> 0.06
XX1000: 127155

Sheet Assumptions2
B2: Assumptions: Balance Sheet
F3: Projection Period
F4: 1 | G4: =F4+1 -> 2 | H4: =G4+1 -> 3 | I4: =H4+1 -> 4 | J4: =I4+1 -> 5 | K4: =J4+1 -> 6 | L4: =K4+1 -> 7 | M4: =L4+1 -> 8 | N4: =M4+1 -> 9 | O4: =N4+1 -> 10
F5: =Summary!$H$26+F4 -> 2025 | G5: =Summary!$H$26+G4 -> 2026 | H5: =Summary!$H$26+H4 -> 2027 | I5: =Summary!$H$26+I4 -> 2028 | J5: =Summary!$H$26+J4 -> 2029 | K5: =Summary!$H$26+K4 -> 2030 | L5: =Summary!$H$26+L4 -> 2031 | M5: =Summary!$H$26+M4 -> 2032 | ... O5: =Summary!$H$26+O4 -> 2034
B7: Current Assets
B8: Days Sales Outstanding (DSO) | F8: {=INDEX(F9:F12,OpScenario)} -> 47.6 | G8: {=INDEX(G9:G12,OpScenario)} -> 47.6 | H8: {=INDEX(H9:H12,OpScenario)} -> 47.6 | I8: {=INDEX(I9:I12,OpScenario)} -> 47.6 | J8: {=INDEX(J9:J12,OpScenario)} -> 47.6 | K8: {=INDEX(K9:K12,OpScenario)} -> 47.6 | L8: {=INDEX(L9:L12,OpScenario)} -> 47.6 | M8: {=INDEX(M9:M12,OpScenario)} -> 47.6 | ... O8: {=INDEX(O9:O12,OpScenario)} -> 47.6
B9: Base | E9: 1 | F9: 47.6 | G9: 47.6 | H9: 47.6 | I9: 47.6 | J9: 47.6 | K9: =J9 -> 47.6 | L9: =K9 -> 47.6 | M9: =L9 -> 47.6 | N9: =M9 -> 47.6 | O9: =N9 -> 47.6
B10: Sponsor | E10: =E9+1 -> 2 | F10: 47.6 | G10: 47.6 | H10: 47.6 | I10: 47.6 | J10: 47.6 | K10: =J10 -> 47.6 | L10: =K10 -> 47.6 | M10: =L10 -> 47.6 | N10: =M10 -> 47.6 | O10: =N10 -> 47.6
B11: Management | E11: =E10+1 -> 3 | F11: 47.6 | G11: 47.6 | H11: 47.6 | I11: 47.6 | J11: 47.6 | K11: =J11 -> 47.6 | L11: =K11 -> 47.6 | M11: =L11 -> 47.6 | N11: =M11 -> 47.6 | O11: =N11 -> 47.6
B12: Downside | E12: =E11+1 -> 4 | F12: 50 | G12: 50 | H12: 50 | I12: 50 | J12: 50 | K12: =J12 -> 50 | L12: =K12 -> 50 | M12: =L12 -> 50 | N12: =M12 -> 50 | O12: =N12 -> 50
B14: Days Inventory Held (DIH) | F14: {=INDEX(F15:F18,OpScenario)} -> 105.8 | G14: {=INDEX(G15:G18,OpScenario)} -> 105.8 | H14: {=INDEX(H15:H18,OpScenario)} -> 105.8 | I14: {=INDEX(I15:I18,OpScenario)} -> 105.8 | J14: {=INDEX(J15:J18,OpScenario)} -> 105.8 | K14: {=INDEX(K15:K18,OpScenario)} -> 105.8 | L14: {=INDEX(L15:L18,OpScenario)} -> 105.8 | M14: {=INDEX(M15:M18,OpScenario)} -> 105.8 | ... O14: {=INDEX(O15:O18,OpScenario)} -> 105.8
B15: Base | E15: 1 | F15: 105.8 | G15: 105.8 | H15: 105.8 | I15: 105.8 | J15: 105.8 | K15: =J15 -> 105.8 | L15: =K15 -> 105.8 | M15: =L15 -> 105.8 | N15: =M15 -> 105.8 | O15: =N15 -> 105.8
B16: Sponsor | E16: =E15+1 -> 2 | F16: 105.8 | G16: 105.8 | H16: 105.8 | I16: 105.8 | J16: 105.8 | K16: =J16 -> 105.8 | L16: =K16 -> 105.8 | M16: =L16 -> 105.8 | N16: =M16 -> 105.8 | O16: =N16 -> 105.8
B17: Management | E17: =E16+1 -> 3 | F17: 105.8 | G17: 105.8 | H17: 105.8 | I17: 105.8 | J17: 105.8 | K17: =J17 -> 105.8 | L17: =K17 -> 105.8 | M17: =L17 -> 105.8 | N17: =M17 -> 105.8 | O17: =N17 -> 105.8
B18: Downside | E18: =E17+1 -> 4 | F18: 110 | G18: 110 | H18: 110 | I18: 110 | J18: 110 | K18: =J18 -> 110 | L18: =K18 -> 110 | M18: =L18 -> 110 | N18: =M18 -> 110 | O18: =N18 -> 110
B20: Prepaids and Other Current Assets (% sales) | F20: {=INDEX(F21:F24,OpScenario)} -> 0.051 | G20: {=INDEX(G21:G24,OpScenario)} -> 0.051 | H20: {=INDEX(H21:H24,OpScenario)} -> 0.051 | I20: {=INDEX(I21:I24,OpScenario)} -> 0.051 | J20: {=INDEX(J21:J24,OpScenario)} -> 0.051 | K20: {=INDEX(K21:K24,OpScenario)} -> 0.051 | L20: {=INDEX(L21:L24,OpScenario)} -> 0.051 | M20: {=INDEX(M21:M24,OpScenario)} -> 0.051 | ... O20: {=INDEX(O21:O24,OpScenario)} -> 0.051
B21: Base | E21: 1 | F21: 0.051 | G21: 0.051 | H21: 0.051 | I21: 0.051 | J21: 0.051 | K21: =J21 -> 0.051 | L21: =K21 -> 0.051 | M21: =L21 -> 0.051 | N21: =M21 -> 0.051 | O21: =N21 -> 0.051
B22: Sponsor | E22: =E21+1 -> 2 | F22: 0.051 | G22: 0.051 | H22: 0.051 | I22: 0.051 | J22: 0.051 | K22: =J22 -> 0.051 | L22: =K22 -> 0.051 | M22: =L22 -> 0.051 | N22: =M22 -> 0.051 | O22: =N22 -> 0.051
B23: Management | E23: =E22+1 -> 3 | F23: 0.051 | G23: 0.051 | H23: 0.051 | I23: 0.051 | J23: 0.051 | K23: =J23 -> 0.051 | L23: =K23 -> 0.051 | M23: =L23 -> 0.051 | N23: =M23 -> 0.051 | O23: =N23 -> 0.051
B24: Downside | E24: =E23+1 -> 4 | F24: 0.051 | G24: 0.051 | H24: 0.051 | I24: 0.051 | J24: 0.051 | K24: =J24 -> 0.051 | L24: =K24 -> 0.051 | M24: =L24 -> 0.051 | N24: =M24 -> 0.051 | O24: =N24 -> 0.051
B26: Current Liabilities
B27: Days Payable Outstanding (DPO) | F27: {=INDEX(F28:F31,OpScenario)} -> 37.9 | G27: {=INDEX(G28:G31,OpScenario)} -> 37.9 | H27: {=INDEX(H28:H31,OpScenario)} -> 37.9 | I27: {=INDEX(I28:I31,OpScenario)} -> 37.9 | J27: {=INDEX(J28:J31,OpScenario)} -> 37.9 | K27: {=INDEX(K28:K31,OpScenario)} -> 37.9 | L27: {=INDEX(L28:L31,OpScenario)} -> 37.9 | M27: {=INDEX(M28:M31,OpScenario)} -> 37.9 | ... O27: {=INDEX(O28:O31,OpScenario)} -> 37.9
B28: Base | E28: 1 | F28: 37.9 | G28: 37.9 | H28: 37.9 | I28: 37.9 | J28: 37.9 | K28: =J28 -> 37.9 | L28: =K28 -> 37.9 | M28: =L28 -> 37.9 | N28: =M28 -> 37.9 | O28: =N28 -> 37.9
B29: Sponsor | E29: =E28+1 -> 2 | F29: 37.9 | G29: 37.9 | H29: 37.9 | I29: 37.9 | J29: 37.9 | K29: =J29 -> 37.9 | L29: =K29 -> 37.9 | M29: =L29 -> 37.9 | N29: =M29 -> 37.9 | O29: =N29 -> 37.9
B30: Management | E30: =E29+1 -> 3 | F30: 37.9 | G30: 37.9 | H30: 37.9 | I30: 37.9 | J30: 37.9 | K30: =J30 -> 37.9 | L30: =K30 -> 37.9 | M30: =L30 -> 37.9 | N30: =M30 -> 37.9 | O30: =N30 -> 37.9
B31: Downside | E31: =E30+1 -> 4 | F31: 35 | G31: 35 | H31: 35 | I31: 35 | J31: 35 | K31: =J31 -> 35 | L31: =K31 -> 35 | M31: =L31 -> 35 | N31: =M31 -> 35 | O31: =N31 -> 35
B33: Accrued Liabiilities (% sales) | F33: {=INDEX(F34:F37,OpScenario)} -> 0.08 | G33: {=INDEX(G34:G37,OpScenario)} -> 0.08 | H33: {=INDEX(H34:H37,OpScenario)} -> 0.08 | I33: {=INDEX(I34:I37,OpScenario)} -> 0.08 | J33: {=INDEX(J34:J37,OpScenario)} -> 0.08 | K33: {=INDEX(K34:K37,OpScenario)} -> 0.08 | L33: {=INDEX(L34:L37,OpScenario)} -> 0.08 | M33: {=INDEX(M34:M37,OpScenario)} -> 0.08 | ... O33: {=INDEX(O34:O37,OpScenario)} -> 0.08
B34: Base | E34: 1 | F34: 0.08 | G34: 0.08 | H34: 0.08 | I34: 0.08 | J34: 0.08 | K34: =J34 -> 0.08 | L34: =K34 -> 0.08 | M34: =L34 -> 0.08 | N34: =M34 -> 0.08 | O34: =N34 -> 0.08
B35: Sponsor | E35: =E34+1 -> 2 | F35: 0.08 | G35: 0.08 | H35: 0.08 | I35: 0.08 | J35: 0.08 | K35: =J35 -> 0.08 | L35: =K35 -> 0.08 | M35: =L35 -> 0.08 | N35: =M35 -> 0.08 | O35: =N35 -> 0.08
B36: Management | E36: =E35+1 -> 3 | F36: 0.08 | G36: 0.08 | H36: 0.08 | I36: 0.08 | J36: 0.08 | K36: =J36 -> 0.08 | L36: =K36 -> 0.08 | M36: =L36 -> 0.08 | N36: =M36 -> 0.08 | O36: =N36 -> 0.08
B37: Downside | E37: =E36+1 -> 4 | F37: 0.08 | G37: 0.08 | H37: 0.08 | I37: 0.08 | J37: 0.08 | K37: =J37 -> 0.08 | L37: =K37 -> 0.08 | M37: =L37 -> 0.08 | N37: =M37 -> 0.08 | O37: =N37 -> 0.08
B39: Other Current Liabilities (% sales) | F39: {=INDEX(F40:F43,OpScenario)} -> 0.029 | G39: {=INDEX(G40:G43,OpScenario)} -> 0.029 | H39: {=INDEX(H40:H43,OpScenario)} -> 0.029 | I39: {=INDEX(I40:I43,OpScenario)} -> 0.029 | J39: {=INDEX(J40:J43,OpScenario)} -> 0.029 | K39: {=INDEX(K40:K43,OpScenario)} -> 0.029 | L39: {=INDEX(L40:L43,OpScenario)} -> 0.029 | M39: {=INDEX(M40:M43,OpScenario)} -> 0.029 | ... O39: {=INDEX(O40:O43,OpScenario)} -> 0.029
B40: Base | E40: 1 | F40: 0.029 | G40: 0.029 | H40: 0.029 | I40: 0.029 | J40: 0.029 | K40: =J40 -> 0.029 | L40: =K40 -> 0.029 | M40: =L40 -> 0.029 | N40: =M40 -> 0.029 | O40: =N40 -> 0.029
B41: Sponsor | E41: =E40+1 -> 2 | F41: 0.029 | G41: 0.029 | H41: 0.029 | I41: 0.029 | J41: 0.029 | K41: =J41 -> 0.029 | L41: =K41 -> 0.029 | M41: =L41 -> 0.029 | N41: =M41 -> 0.029 | O41: =N41 -> 0.029
B42: Management | E42: =E41+1 -> 3 | F42: 0.029 | G42: 0.029 | H42: 0.029 | I42: 0.029 | J42: 0.029 | K42: =J42 -> 0.029 | L42: =K42 -> 0.029 | M42: =L42 -> 0.029 | N42: =M42 -> 0.029 | O42: =N42 -> 0.029
B43: Downside | E43: =E42+1 -> 4 | F43: 0.029 | G43: 0.029 | H43: 0.029 | I43: 0.029 | J43: 0.029 | K43: =J43 -> 0.029 | L43: =K43 -> 0.029 | M43: =L43 -> 0.029 | N43: =M43 -> 0.029 | O43: =N43 -> 0.029
XX1000: 127155

Sheet Grading
A1: ProblemType | B1: WorksheetName | C1: Range | D1: Comparison | E1: Grade | F1: CTC | G1: CorrectFeedback | H1: IncorrectFeedback
A2: CELL | B2: Summary | C2: D9 | D2: FVContains(Index);Value | E2: 1 | G2: Correct! | H2: Did you use the Index() function on a row of financing sources? | I2: Be sure you refer to the selected financing structure alternative as the "column" to use as output
A3: CELL | B3: Summary | C3: D10 | D3: FVContains(Index);Value | E3: 1 | G3: Correct! | H3: Did you use the Index() function on a row of financing sources? | I3: Be sure you refer to the selected financing structure alternative as the "column" to use as output
A4: CELL | B4: Summary | C4: D11 | D4: FVContains(Index);Value | E4: 1 | G4: Correct! | H4: Did you use the Index() function on a row of financing sources? | I4: Be sure you refer to the selected financing structure alternative as the "column" to use as output
A5: CELL | B5: Summary | C5: D12 | D5: FVContains(Index);Value | E5: 1 | G5: Correct! | H5: Did you use the Index() function on a row of financing sources? | I5: Be sure you refer to the selected financing structure alternative as the "column" to use as output
A6: CELL | B6: Summary | C6: D13 | D6: FVContains(Index);Value | E6: 1 | G6: Correct! | H6: Did you use the Index() function on a row of financing sources? | I6: Be sure you refer to the selected financing structure alternative as the "column" to use as output
A7: CELL | B7: Summary | C7: D14 | D7: FVContains(Index);Value | E7: 1 | G7: Correct! | H7: Did you use the Index() function on a row of financing sources? | I7: Be sure you refer to the selected financing structure alternative as the "column" to use as output
A8: CELL | B8: Summary | C8: D15 | D8: FVContains(Index);Value | E8: 1 | G8: Correct! | H8: Did you use the Index() function on a row of financing sources? | I8: Be sure you refer to the selected financing structure alternative as the "column" to use as output
A9: CELL | B9: Summary | C9: D16 | D9: FVContains(Index);Value | E9: 1 | G9: Correct! | H9: Did you use the Index() function on a row of financing sources? | I9: Be sure you refer to the selected financing structure alternative as the "column" to use as output
A10: CELL | B10: Summary | C10: K9 | D10: FVContains(Index);Value | E10: 1 | G10: Correct! | H10: Did you use the Index() function on a row of financing uses? | I10: Be sure you refer to the selected financing structure alternative as the "column" to use as output
A11: CELL | B11: Summary | C11: K10 | D11: FVContains(Index);Value | E11: 1 | G11: Correct! | H11: Did you use the Index() function on a row of financing uses? | I11: Be sure you refer to the selected financing structure alternative as the "column" to use as output
A12: CELL | B12: Summary | C12: K11 | D12: FVContains(Index);Value | E12: 1 | G12: Correct! | H12: Did you use the Index() function on a row of financing uses? | I12: Be sure you refer to the selected financing structure alternative as the "column" to use as output
A13: CELL | B13: Summary | C13: K12 | D13: FVContains(Index);Value | E13: 1 | G13: Correct! | H13: Did you use the Index() function on a row of financing uses? | I13: Be sure you refer to the selected financing structure alternative as the "column" to use as output
... A23: CELL | B23: IncStmt | C23: J33:S33 | D23: Formula() OR Reference();MOEValue(.01) | E23: 1 | G23: Correct! | H23: Does the row refer to the row of interest expense for this debt tranche on the Debt Schedule? | I23: Do you have the financing alternative set to 1?
A24: CELL | B24: IncStmt | C24: J34:S34 | D24: Formula() OR Reference();MOEValue(.01) | E24: 1 | G24: Correct! | H24: Did you add interest expense from each debt tranche?
A25: CELL | B25: IncStmt | C25: J35:S35 | D25: Formula() OR Reference();MOEValue(.01) | E25: 1 | G25: Correct! | H25: Deferred financing fees are found on the "Financing" tab where you calculated the amount of annual amortization.
A26: CELL | B26: IncStmt | C26: J36:S36 | D26: Formula() OR Reference();MOEValue(.01) | E26: 1 | G26: Correct! | H26: This should be the sum of interest expense and amortized fees.
A27: CELL | B27: IncStmt | C27: J37:S37 | D27: Formula() OR Reference();MOEValue(.01) | E27: 1 | G27: Correct! | H27: Interest is earned at the Interest Income rate on this tab. | I27: Interest is earned on the average cash balance each period | J27: Look carefully at the line item description.
A28: CELL | B28: IncStmt | C28: J38:S38 | D28: Formula() OR Reference();MOEValue(.01) | E28: 1 | G28: Correct! | H28: Net interest is the Interest Expense offset by (Interest Income).
A29: CELL | B29: BalSheet | C29: G6 | D29: Formula() OR Reference();Value | E29: 1 | G29: Correct! | H29: The formula should use an IF() statement to evaluate whether the scenario involves a transaction. | I29: If a transaction is taking place, the adjustment to this cell should reflect that all cash on the balance sheet will be used as a source of funding for the acquisition.
A30: CELL | B30: BalSheet | C30: G13 | D30: FVContains(If);Value | E30: 1 | G30: Correct! | H30: The formula should use an IF() statement to evaluate whether the scenario involves a transaction. | I30: If a transaction is taking place, old Goodwill amounts should be adjusted out of the balance sheet before the new amount from your transaction is adjusted in.
A31: CELL | B31: BalSheet | C31: F13 | D31: FVContains(If);Value | E31: 1 | G31: Correct! | H31: The formula should use an IF() statement to evaluate whether the scenario involves a transaction. | I31: If a transaction is taking place, the new amount of Goodwill will be an estimate presented in the slides from Module 6.
A32: CELL | B32: BalSheet | C32: F16 | D32: Formula() OR Reference();Value | E32: 1 | G32: Correct! | H32: The formula should use an IF() statement to evaluate whether the scenario involves a transaction. | I32: If a transaction is taking place, there will be new financing that incurs deferred costs (an asset to be amortized).
A33: CELL | B33: BalSheet | C33: F24 | D33: Reference();MOEValue(.01) | E33: 1 | G33: Correct! | H33: This cell should refer to a cell on the Summary tab for which the value is conditioned on which financing structure is selected | I33: An IF() statement is not needed here because the reference is to a cell with a conditional value
A34: CELL | B34: BalSheet | C34: F25 | D34: Reference();MOEValue(.01) | E34: 1 | G34: Correct! | H34: This cell should refer to a cell on the Summary tab for which the value is conditioned on which financing structure is selected | I34: An IF() statement is not needed here because the reference is to a cell with a conditional value
A35: CELL | B35: BalSheet | C35: F26 | D35: Reference();MOEValue(.01) | E35: 1 | G35: Correct! | H35: This cell should refer to a cell on the Summary tab for which the value is conditioned on which financing structure is selected | I35: An IF() statement is not needed here because the reference is to a cell with a conditional value
A36: CELL | B36: BalSheet | C36: F28 | D36: Reference();MOEValue(.01) | E36: 1 | G36: Correct! | H36: This cell should refer to a cell on the Summary tab for which the value is conditioned on which financing structure is selected | I36: An IF() statement is not needed here because the reference is to a cell with a conditional value
A37: CELL | B37: BalSheet | C37: F29 | D37: Reference();MOEValue(.01) | E37: 1 | G37: Correct! | H37: This cell should refer to a cell on the Summary tab for which the value is conditioned on which financing structure is selected | I37: An IF() statement is not needed here because the reference is to a cell with a conditional value
A38: CELL | B38: BalSheet | C38: F31 | D38: Reference();MOEValue(.01) | E38: 1 | G38: Correct! | H38: This cell should refer to a cell on the Summary tab for which the value is conditioned on which financing structure is selected | I38: An IF() statement is not needed here because the reference is to a cell with a conditional value
A39: CELL | B39: BalSheet | C39: G27 | D39: Reference();MOEValue(.01) | E39: 1 | G39: Correct! | H39: This cell should refer to a cell on the Summary tab for which the value is conditioned on which financing structure is selected | I39: An IF() statement is not needed here because the reference is to a cell with a conditional value
A40: CELL | B40: BalSheet | C40: G30 | D40: Reference();MOEValue(.01) | E40: 1 | G40: Correct! | H40: This cell should refer to a cell on the Summary tab for which the value is conditioned on which financing structure is selected | I40: An IF() statement is not needed here because the reference is to a cell with a conditional value
A41: CELL | B41: BalSheet | C41: F38 | D41: Formula() OR Reference();MOEValue(.01) | E41: 1 | G41: Correct! | H41: This cell should refer to 3 cells (with conditional values) on the Summary tab to find the net amount of equity invested in the new transaction after considering upfront expenses.
A42: CELL | B42: BalSheet | C42: G38 | D42: FVContains(If);Value | E42: 1 | G42: Correct! | H42: This cell should conditionally adjust out the existing equity of current owners IF a transaction is taking place.
A43: CELL | B43: BalSheet | C43: H24:H31 | D43: Formula() OR Reference();MOEValue(.005) | E43: 2 | G43: Correct! | H43: This series of cells should reflect the beginning balance of each debt account given a) the original balances and b) the adjustments made as a result of a transaction.
A44: CELL | B44: BalSheet | C44: H24:R24 | D44: Formula() OR Reference();MOEValue(.005) | E44: 1 | G44: Correct! | H44: Where does your model calculate the ending balances of debt tranches?
A45: CELL | B45: BalSheet | C45: H25:R25 | D45: Formula() OR Reference();MOEValue(.005) | E45: 1 | G45: Correct! | H45: Where does your model calculate the ending balances of debt tranches?
A46: CELL | B46: BalSheet | C46: H26:R26 | D46: Formula() OR Reference();MOEValue(.005) | E46: 1 | G46: Correct! | H46: Where does your model calculate the ending balances of debt tranches?
A47: CELL | B47: BalSheet | C47: H27:R27 | D47: Formula() OR Reference();MOEValue(.005) | E47: 1 | G47: Correct! | H47: Existing debt will either be repaid (if a transaction occurs) or assumed to remain outstanding over the entire horizon
A48: CELL | B48: BalSheet | C48: H28:R28 | D48: Formula() OR Reference();MOEValue(.005) | E48: 1 | G48: Correct! | H48: Where does your model calculate the ending balances of debt tranches?
A49: CELL | B49: BalSheet | C49: H29:R29 | D49: Formula() OR Reference();MOEValue(.005) | E49: 1 | G49: Correct! | H49: Where does your model calculate the ending balances of debt tranches?
A50: CELL | B50: BalSheet | C50: H30:R30 | D50: Formula() OR Reference();MOEValue(.005) | E50: 1 | G50: Correct! | H50: Existing debt will either be repaid (if a transaction occurs) or assumed to remain outstanding over the entire horizon
A51: CELL | B51: BalSheet | C51: H31:R31 | D51: Formula() OR Reference();MOEValue(.005) | E51: 1 | G51: Correct! | H51: Where does your model calculate the ending balances of debt tranches?
A52: CELL | B52: CFStmt | C52: F29:O29 | D52: Formula() OR Reference();MOEValue(.005) | E52: 1 | G52: Correct! | H52: Where does your model calculate the amount repaid on debt tranches in each period?
A53: CELL | B53: CFStmt | C53: F30:O30 | D53: Formula() OR Reference();MOEValue(.005) | E53: 1 | G53: Correct! | H53: Where does your model calculate the amount repaid on debt tranches in each period? | I53: Have you considered all possible amounts paid on this debt in each period?
A54: CELL | B54: CFStmt | C54: F31:O31 | D54: Formula() OR Reference();MOEValue(.005) | E54: 1 | G54: Correct! | H54: Where does your model calculate the amount repaid on debt tranches in each period? | I54: Have you considered all possible amounts paid on this debt in each period?
A55: CELL | B55: CFStmt | C55: F32:O32 | D55: Formula() OR Reference();MOEValue(.005) | E55: 1 | G55: Correct! | H55: Where does your model calculate the amount repaid on debt tranches in each period?
A56: CELL | B56: CFStmt | C56: F33:O33 | D56: Formula() OR Reference();MOEValue(.005) | E56: 1 | G56: Correct! | H56: Where does your model calculate the amount repaid on debt tranches in each period?
A57: CELL | B57: CFStmt | C57: F34:O34 | D57: Formula() OR Reference();MOEValue(.005) | E57: 1 | G57: Correct! | H57: Where does your model calculate the amount repaid on debt tranches in each period?
A58: CELL | B58: DebtSched | C58: F12:O12 | D58: Formula() OR Reference();MOEValue(.01) | E58: 5 | G58: Correct! | H58: Did you included all mandatory repayment amounts from debt tranches that have them? | I58: There are 5 tranches that have required repayment amounts in at least one period.
A59: CELL | B59: DebtSched | C59: F23:O23 | D59: Formula() OR Reference();MOEValue(.01) | E59: 1 | G59: Correct! | H59: Where can we find the beginning balance of debt tranches?
A60: CELL | B60: DebtSched | C60: F24:O24 | D60: Formula() OR Reference();MOEValue(.01) | E60: 5 | G60: Correct! | H60: Use the cash available for optional debt repayments to determine the amount drawn or repaid on the revolver
A61: CELL | B61: DebtSched | C61: F25:O25 | D61: Formula() OR Reference();MOEValue(.01) | E61: 1 | G61: Correct! | H61: Total
A62: CELL | B62: DebtSched | C62: F39:O39 | D62: Formula() OR Reference();MOEValue(.01) | E62: 1 | G62: Correct! | H62: Where can we find the beginning balance of debt tranches?
A63: CELL | B63: DebtSched | C63: F40:O40 | D63: Formula() OR Reference();MOEValue(.01) | E63: 5 | G63: Correct! | H63: Recall mandatory repayments are fixed amounts…unless prepayments cause the balance to be less than the mandatory payment.
A64: CELL | B64: DebtSched | C64: F41:O41 | D64: Formula() OR Reference();MOEValue(.01) | E64: 5 | G64: Correct! | H64: Use the cash available for optional debt repayments to determine the amount drawn or repaid on the revolver | I64: Have you adjusted cash available for optional prepayments for the amount of other debt prepayments? | J64: Have you adjusted the balance for this period's mandatory payment? | K64: Did you include the cash sweep reference?
A65: CELL | B65: DebtSched | C65: F42:O42 | D65: Formula() OR Reference();MOEValue(.01) | E65: 1 | G65: Correct! | H65: Total
A66: CELL | B66: DebtSched | C66: F44:O44 | D66: Formula() OR Reference();MOEValue(.01) | E66: 3 | G66: Correct! | H66: Did you apply the LIBOR floor rate to your computation of the interest rate?
A67: CELL | B67: DebtSched | C67: F45:O45 | D67: Formula() OR Reference();MOEValue(.01) | E67: 3 | G67: Correct! | H67: Did you calculate interest based on average balances?
A68: CELL | B68: DebtSched | C68: F54:O54 | D68: Formula() OR Reference();MOEValue(.01) | E68: 5 | G68: Correct! | H68: Where can we find the beginning balance of debt tranches?
A69: CELL | B69: DebtSched | C69: F55:O55 | D69: Formula() OR Reference();MOEValue(.01) | E69: 5 | G69: Correct! | H69: Recall mandatory repayments are fixed amounts…unless prepayments cause the balance to be less than the mandatory payment.
A70: CELL | B70: DebtSched | C70: F56:O56 | D70: Formula() OR Reference();MOEValue(.01) | E70: 3 | G70: Correct! | H70: Use the cash available for optional debt repayments to determine the amount drawn or repaid on the revolver | I70: Have you adjusted cash available for optional prepayments for the amount of other debt prepayments? (This is the 3rd priority tranche of prepayable debt) | J70: Have you adjusted the balance for this period's mandatory payment? | K70: Did you include the cash sweep reference?
A71: CELL | B71: DebtSched | C71: F57:O57 | D71: Formula() OR Reference();MOEValue(.01) | E71: 3 | G71: Correct! | H71: Total
A72: CELL | B72: DebtSched | C72: F59:O59 | D72: Formula() OR Reference();MOEValue(.01) | E72: 3 | G72: Correct! | H72: Did you apply the LIBOR floor rate to your computation of the interest rate?
A73: CELL | B73: DebtSched | C73: F60:O60 | D73: Formula() OR Reference();MOEValue(.01) | E73: 3 | G73: Correct! | H73: Did you calculate interest based on average balances?
A74: CELL | B74: DebtSched | C74: F70:I70 | D74: Formula() OR Reference();MOEValue(.05) | E74: 1 | G74: Correct! | H74: The second lien debt amortizes by one third each year as a mandatory repayment.
A75: CELL | B75: DebtSched | C75: F82:O82 | D75: FVContains(IF);Formula() OR Reference();MOEValue(.05) | E75: 3 | G75: Correct! | H75: Senior notes mature all at once. | I75: Did you use an IF() statement to determine whether the present year matches the maturity date?
A76: CELL | B76: DebtSched | C76: F85:O85 | D76: Formula() OR Reference();MOEValue(.05) | E76: 1 | G76: Correct! | H76: Outstanding principal times interest rate on the notes
A77: CELL | B77: DebtSched | C77: F93:O93 | D77: FVContains(IF);Formula() OR Reference();MOEValue(.05) | E77: 3 | G77: Correct! | H77: Senior sub notes mature all at once. | I77: Did you use an IF() statement to determine whether the present year matches the maturity date?
A78: CELL | B78: DebtSched | C78: F96:O96 | D78: Formula() OR Reference();MOEValue(.05) | E78: 1 | G78: Correct! | H78: Outstanding principal times interest rate on the notes
A79: CELL | B79: RetAnalysis | C79: G8:P8 | D79: Formula() OR Reference();MOEValue(.05) | E79: 1 | G79: Correct! | H79: Reference the calculation of EBITDA from a tab where it is calculated
A80: CELL | B80: RetAnalysis | C80: G10:P10 | D80: Formula() OR Reference();MOEValue(.05) | E80: 1 | G80: Correct! | H80: Calculate the enterprise value assuming exit from the investment in each period using the assumed exit multiple
A81: CELL | B81: RetAnalysis | C81: G13:P13 | D81: Formula() OR Reference();MOEValue(.1) | E81: 1 | G81: Correct! | H81: Reference the ending balance of the tranche of debt from the source of ending balances of accounts
A82: CELL | B82: RetAnalysis | C82: G14:P14 | D82: Formula() OR Reference();MOEValue(.1) | E82: 1 | G82: Correct! | H82: Reference the ending balance of the tranche of debt from the source of ending balances of accounts
A83: CELL | B83: RetAnalysis | C83: G15:P15 | D83: Formula() OR Reference();MOEValue(.1) | E83: 1 | G83: Correct! | H83: Reference the ending balance of the tranche of debt from the source of ending balances of accounts
A84: CELL | B84: RetAnalysis | C84: G16:P16 | D84: Formula() OR Reference();MOEValue(.1) | E84: 1 | G84: Correct! | H84: Reference the ending balance of the tranche of debt from the source of ending balances of accounts
A85: CELL | B85: RetAnalysis | C85: G17:P17 | D85: Formula() OR Reference();MOEValue(.1) | E85: 1 | G85: Correct! | H85: Reference the ending balance of the tranche of debt from the source of ending balances of accounts
A86: CELL | B86: RetAnalysis | C86: G18:P18 | D86: Formula() OR Reference();MOEValue(.1) | E86: 1 | G86: Correct! | H86: Reference the ending balance of the tranche of debt from the source of ending balances of accounts
A87: CELL | B87: RetAnalysis | C87: G19:P19 | D87: Formula() OR Reference();MOEValue(.1) | E87: 1 | G87: Correct! | H87: Reference the ending balance of the tranche of debt from the source of ending balances of accounts
A88: CELL | B88: RetAnalysis | C88: G20:P20 | D88: Formula() OR Reference();MOEValue(.1) | E88: 1 | G88: Correct! | H88: Total debt above.
A89: CELL | B89: RetAnalysis | C89: G21:P21 | D89: Formula() OR Reference();MOEValue(.1) | E89: 1 | G89: Correct! | H89: Reference the ending balance of cash from the source of ending balances of accounts
... A91: CELL | B91: RetAnalysis | C91: G24:P24 | D91: Formula() OR Reference();MOEValue(.1) | E91: 1 | G91: Correct! | H91: Compute equity value from enterprise value and net debt
A92: CELL | B92: RetAnalysis | C92: G30:P40 | D92: Value OR Formula() OR Reference();MOEValue(.05) | E92: 10 | G92: Correct! | H92: Add cell references and values such that the IRR() in row 41 calculates properly | I92: Row 30 should contain the same reference in all columns | J92: Each period should contain one more horizon year than the column to the left | K92: All years beyond the investment horizon of this column should contain no values
A93: CELL | B93: RetAnalysis | C93: D47:H52 | D93: DataTable(VAR1(E9),VAR2(E6)); Value | E93: 7 | G93: Correct! | H93: This is a straightforward 2 variable table you should know how to use by this point.
A94: CELL | B94: RetAnalysis | C94: L48:P52 | D94: DataTable(VAR2(E9)); Value | E94: 10 | G94: Correct! | H94: This table is a single variable table, but uses several columns of output (references to several output cells) | I94: To create this table, highlight cells K47:P52
A95: CELL | B95: RetAnalysis | C95: D60:H63 | D95: DataTable(VAR2(D65)); Value | E95: 7 | G95: Correct! | H95: This table is a single variable table, but uses several columns of output (references to several output cells) | I95: To create this table, highlight cells D59:H63 | J95: For your model to work properly, you must use cell D65 as the input cell, but you must figure out how to make that work. This is like the modification we made in Activity 11.
A96: CELL | B96: Financing | C96: N11 | D96: Value OR Formula() OR Reference();MOEValue(.05) | E96: 1 | G96: Correct! | H96: Reference appropriate balance sheet account balance for the pre-transaction company (or, if the account is not found on the balance sheet, enter the correct value)
A97: CELL | B97: Financing | C97: N12 | D97: Value OR Formula() OR Reference();MOEValue(.05) | E97: 1 | G97: Correct! | H97: Reference appropriate balance sheet account balance for the pre-transaction company (or, if the account is not found on the balance sheet, enter the correct value)
A98: CELL | B98: Financing | C98: N13 | D98: Value OR Formula() OR Reference();MOEValue(.05) | E98: 1 | G98: Correct! | H98: Reference appropriate balance sheet account balance for the pre-transaction company (or, if the account is not found on the balance sheet, enter the correct value)
A99: CELL | B99: Financing | C99: E49:N57 | D99: FVContains(IF);Formula() OR Reference();MOEValue(.05) | E99: 10 | G99: Correct! | H99: Use an IF() function and find a formula that can be copied to all cells with the correct relative references that calculates the proper annual fee amortization amount
XX1000: 127155

Sheet Sheet1
D7: Fin | E7: 1
D8: Op | E8: 1
E10: IRR Assuming Exit after Year 5 | M10: IRR Assuming 9.5x Entry Multiple
F11: Exit Multiple | N11: Exit Year
E12: 0.18562465 | F12: 8.5 | G12: 9 | H12: 9.5 | I12: 10 | J12: 10.5 | N12: 2023 | O12: 2024 | P12: 2025 | Q12: 2026 | R12: 2027
E13: 8 | F13: 0.26030597 | G13: 0.2798797 | H13: 0.29832447 | I13: 0.315777 | J13: 0.33234987 | N13: 0.22573004 | O13: 0.20358626 | P13: 0.18562465 | Q13: 0.17271939 | R13: 0.16279435
E14: 8.5 | F14: 0.21689719 | G14: 0.23579673 | H14: 0.25360621 | I14: 0.27045762 | J14: 0.28645967 | M14: 8.5 | N14: 0.15468728 | O14: 0.15577643 | P14: 0.15090632 | Q14: 0.14622964 | R14: 0.14186155
D15: Entry | E15: 9 | F15: 0.18115224 | G15: 0.19949663 | H15: 0.21678297 | I15: 0.23313939 | J15: 0.2486714 | L15: Exit | M15: 9 | N15: 0.19126784 | O15: 0.18040733 | P15: 0.16878097 | Q15: 0.15985251 | R15: 0.15261297
D16: Multiple | E16: 9.5 | F16: 0.15090632 | G16: 0.16878097 | H16: 0.18562465 | I16: 0.20156223 | J16: 0.21669651 | L16: Multiple | M16: 9.5 | N16: 0.22573004 | O16: 0.20358626 | P16: 0.18562465 | Q16: 0.17271939 | R16: 0.16279435
E17: 10 | F17: 0.12478355 | G17: 0.14225248 | H17: 0.15871386 | I17: 0.1742897 | J17: 0.18908046 | M17: 10 | N17: 0.25835625 | O17: 0.22549847 | P17: 0.20156223 | Q17: 0.18491687 | R17: 0.17246738
E18: 10.5 | F18: 0.10185794 | G18: 0.11897082 | H18: 0.13509667 | I18: 0.15035504 | J18: 0.16484434 | M18: 10.5 | N18: 0.28937305 | O18: 0.2462946 | P18: 0.21669651 | Q18: 0.19651708 | R18: 0.18168404
D20: Fin | E20: 2
D21: Op | E21: 1
E23: IRR Assuming Exit after Year 5 | M23: IRR Assuming 9.5x Entry Multiple
F24: Exit Multiple | N24: Exit Year
E25: 0.19571235 | F25: 8.5 | G25: 9 | H25: 9.5 | I25: 10 | J25: 10.5 | N25: 2023 | O25: 2024 | P25: 2025 | Q25: 2026 | R25: 2027
E26: 8 | F26: 0.28393493 | G26: 0.30510807 | H26: 0.32499021 | I26: 0.34374598 | J26: 0.36150954 | N26: 0.24006495 | O26: 0.21546446 | P26: 0.19571235 | Q26: 0.18155881 | R26: 0.17067792
E27: 8.5 | F27: 0.2331464 | G27: 0.253482 | H27: 0.27257765 | I27: 0.29059151 | J27: 0.30765239 | M27: 8.5 | N27: 0.16340015 | O27: 0.16420272 | P27: 0.1586628 | Q27: 0.15340236 | R27: 0.1485009
D28: Entry | E28: 9 | F28: 0.19243987 | G28: 0.21210419 | H28: 0.23056949 | I28: 0.2479887 | J28: 0.2644864 | L28: Exit | M28: 9 | N28: 0.20295402 | O28: 0.19066099 | P28: 0.1777701 | Q28: 0.16790467 | R28: 0.1599073
D29: Multiple | E29: 9.5 | F29: 0.1586628 | G29: 0.1777701 | H29: 0.19571235 | I29: 0.21263815 | J29: 0.22866853 | L29: Multiple | M29: 9.5 | N29: 0.24006495 | O29: 0.21546446 | P29: 0.19571235 | Q29: 0.18155881 | R29: 0.17067792
E30: 10 | F30: 0.12991932 | G30: 0.14855262 | H30: 0.16604977 | I30: 0.18255568 | J30: 0.19818839 | M30: 10 | N30: 0.27507844 | O30: 0.23883619 | P30: 0.21263815 | Q30: 0.19446679 | R30: 0.18088489
E31: 10.5 | F31: 0.10498513 | G31: 0.12320724 | H31: 0.14031828 | I31: 0.15645995 | J31: 0.17174769 | M31: 10.5 | N31: 0.30826787 | O31: 0.26095533 | P31: 0.22866853 | Q31: 0.20671284 | R31: 0.19058845
D33: Fin | E33: 3
D34: Op | E34: 1
E36: IRR Assuming Exit after Year 5 | M36: IRR Assuming 9.5x Entry Multiple
F37: Exit Multiple | N37: Exit Year
E38: 0.20878683 | F38: 8.5 | G38: 9 | H38: 9.5 | I38: 10 | J38: 10.5 | N38: 2023 | O38: 2024 | P38: 2025 | Q38: 2026 | R38: 2027
E39: 8 | F39: 0.31591285 | G39: 0.33891379 | H39: 0.36043489 | I39: 0.38067453 | J39: 0.39979257 | N39: 0.25850375 | O39: 0.23082456 | P39: 0.20878683 | Q39: 0.19300938 | R39: 0.1809606
E40: 8.5 | F40: 0.25477246 | G40: 0.27670473 | H40: 0.29722591 | I40: 0.31652516 | J40: 0.33475494 | M40: 8.5 | N40: 0.17542721 | O40: 0.1757484 | P40: 0.16922767 | Q40: 0.16309902 | R40: 0.15751069
D41: Entry | E41: 9 | F41: 0.20749589 | G41: 0.22860181 | H41: 0.2483498 | I41: 0.26692191 | J41: 0.28446484 | L41: Exit | M41: 9 | N41: 0.21838164 | O41: 0.20423079 | P41: 0.18966469 | Q41: 0.17852843 | R41: 0.16958811
D42: Multiple | E42: 9.5 | F42: 0.16922767 | G42: 0.18966469 | H42: 0.20878683 | I42: 0.22677035 | J42: 0.2437573 | L42: Multiple | M42: 9.5 | N42: 0.25850375 | O42: 0.23082456 | P42: 0.20878683 | Q42: 0.19300938 | R42: 0.1809606
E43: 10 | F43: 0.13724872 | G43: 0.15712679 | H43: 0.17572592 | I43: 0.19321758 | J43: 0.20973993 | M43: 10 | N43: 0.29621878 | O43: 0.25579835 | P43: 0.22677035 | Q43: 0.20666138 | R43: 0.19171164
E44: 10.5 | F44: 0.10989075 | G44: 0.12929062 | H44: 0.14744232 | I44: 0.1645132 | J44: 0.18063808 | M44: 10.5 | N44: 0.33185821 | O44: 0.27936526 | P44: 0.2437573 | Q44: 0.21958215 | R44: 0.20191044
D46: Fin | E46: 4
D47: Op | E47: 1
E49: IRR Assuming Exit after Year 5 | M49: IRR Assuming 9.5x Entry Multiple
F50: Exit Multiple | N50: Exit Year
E51: 0.20671389 | F51: 8.5 | G51: 9 | H51: 9.5 | I51: 10 | J51: 10.5 | N51: 2023 | O51: 2024 | P51: 2025 | Q51: 2026 | R51: 2027
E52: 8 | F52: 0.33528863 | G52: 0.36229344 | H52: 0.38731262 | I52: 0.41064724 | J52: 0.43253282 | N52: 0.24678548 | O52: 0.22579565 | P52: 0.20671389 | Q52: 0.19262915 | R52: 0.18161933
E53: 8.5 | F53: 0.26010054 | G53: 0.28558476 | H53: 0.30919515 | I53: 0.33121582 | J53: 0.35186906 | M53: 8.5 | N53: 0.15042985 | O53: 0.1623882 | P53: 0.16146232 | Q53: 0.15862834 | R53: 0.15511755
D54: Entry | E54: 9 | F54: 0.2047975 | G54: 0.22916327 | H54: 0.25173745 | I54: 0.27279169 | J54: 0.29253849 | L54: Exit | M54: 9 | N54: 0.20054104 | O54: 0.1953527 | P54: 0.18495168 | Q54: 0.17624267 | R54: 0.16881886
D55: Multiple | E55: 9.5 | F55: 0.16146232 | G55: 0.18495168 | H55: 0.20671389 | I55: 0.22701083 | J55: 0.24604737 | L55: Multiple | M55: 9.5 | N55: 0.24678548 | O55: 0.22579565 | P55: 0.20671389 | Q55: 0.19262915 | R55: 0.18161933
E56: 10 | F56: 0.12606611 | G56: 0.14883962 | H56: 0.16993861 | I56: 0.18961699 | J56: 0.20807338 | M56: 10 | N56: 0.28983251 | O56: 0.25412582 | P56: 0.22701083 | Q56: 0.20796165 | R56: 0.19363819
E57: 10.5 | F57: 0.096292916 | G57: 0.11846429 | H57: 0.13900544 | I57: 0.15816352 | J57: 0.17613192 | M57: 10.5 | N57: 0.33018337 | O57: 0.28065659 | P57: 0.24604737 | Q57: 0.2223787 | R57: 0.20497202
