Workbook

Sheet Assumption
A2: Option Selection
A3: Operating Scenario | C3: 1
D4: Projected
D5: 2025 | E5: =D5+1 -> 2026 | F5: =E5+1 -> 2027 | G5: =F5+1 -> 2028 | H5: =G5+1 -> 2029 | I5: =H5+1 -> 2030 | J5: =I5+1 -> 2031 | K5: =J5+1 -> 2032 | L5: =K5+1 -> 2033 | M5: =L5+1 -> 2034
A8: Total Revenue Growth | D8: =DCF!D59 -> 0.04 | E8: =DCF!E59 -> 0.03871733 | F8: =DCF!F59 -> 0.038718216 | G8: =DCF!G59 -> 0.038719102 | H8: =DCF!H59 -> 0.035 | I8: =DCF!I59 -> 0.012599811 | J8: =DCF!J59 -> 0.028679582 | K8: =DCF!K59 -> 0.025553285 | ... M8: =DCF!M59 -> 0.025655781
A11: Total Medicine Theraputic | D11: {=INDEX(D12:D14,$C$3)} -> 0.04 | E11: {=INDEX(E12:E14,$C$3)} -> 0.038 | F11: {=INDEX(F12:F14,$C$3)} -> 0.038 | G11: {=INDEX(G12:G14,$C$3)} -> 0.038 | H11: {=INDEX(H12:H14,$C$3)} -> 0.035 | I11: {=INDEX(I12:I14,$C$3)} -> 0 | J11: {=INDEX(J12:J14,$C$3)} -> 0.025 | K11: {=INDEX(K12:K14,$C$3)} -> 0.02 | ... M11: {=INDEX(M12:M14,$C$3)} -> 0.02
A12: Base | D12: 0.04 | E12: 0.038 | F12: 0.038 | G12: 0.038 | H12: 0.035 | I12: 0 | J12: 0.025 | K12: 0.02 | L12: 0.02 | M12: 0.02
A13: Bull | D13: 0.043 | E13: 0.043 | F13: 0.043 | G13: 0.043 | H13: 0.043 | I13: 0.03 | J13: 0.035 | K13: 0.035 | L13: 0.035 | M13: 0.035
A14: Bear | D14: 0.033 | E14: 0.02 | F14: 0.025 | G14: 0.025 | H14: 0.025 | I14: 0.025 | J14: -0.01 | K14: 0.015 | L14: 0.015 | M14: 0.015
A17: Total MedTech Sales | D17: {=INDEX(D18:D20,$C$3)} -> 0.04 | E17: {=INDEX(E18:E20,$C$3)} -> 0.04 | F17: {=INDEX(F18:F20,$C$3)} -> 0.04 | G17: {=INDEX(G18:G20,$C$3)} -> 0.04 | H17: {=INDEX(H18:H20,$C$3)} -> 0.035 | I17: {=INDEX(I18:I20,$C$3)} -> 0.035 | J17: {=INDEX(J18:J20,$C$3)} -> 0.035 | K17: {=INDEX(K18:K20,$C$3)} -> 0.035 | ... M17: {=INDEX(M18:M20,$C$3)} -> 0.035
A18: Base | D18: 0.04 | E18: 0.04 | F18: 0.04 | G18: 0.04 | H18: 0.035 | I18: 0.035 | J18: 0.035 | K18: 0.035 | L18: 0.035 | M18: 0.035
A19: Bull | D19: 0.045 | E19: 0.045 | F19: 0.045 | G19: 0.045 | H19: 0.043 | I19: 0.043 | J19: 0.043 | K19: 0.043 | L19: 0.043 | M19: 0.043
A20: Bear | D20: 0.03 | E20: 0.035 | F20: 0.035 | G20: 0.035 | H20: 0.035 | I20: 0.03 | J20: 0.03 | K20: 0.03 | L20: 0.03 | M20: 0.03
A23: Gross Margin | D23: =1-D24 -> 0.693 | E23: =1-E24 -> 0.693 | F23: =1-F24 -> 0.693 | G23: =1-G24 -> 0.693 | H23: =1-H24 -> 0.694 | I23: =1-I24 -> 0.694 | J23: =1-J24 -> 0.695 | K23: =1-K24 -> 0.695 | ... M23: =1-M24 -> 0.695
A24: COGS | D24: {=INDEX(D25:D27,$C$3)} -> 0.307 | E24: {=INDEX(E25:E27,$C$3)} -> 0.307 | F24: {=INDEX(F25:F27,$C$3)} -> 0.307 | G24: {=INDEX(G25:G27,$C$3)} -> 0.307 | H24: {=INDEX(H25:H27,$C$3)} -> 0.306 | I24: {=INDEX(I25:I27,$C$3)} -> 0.306 | J24: {=INDEX(J25:J27,$C$3)} -> 0.305 | K24: {=INDEX(K25:K27,$C$3)} -> 0.305 | ... M24: {=INDEX(M25:M27,$C$3)} -> 0.305
A25: Base | D25: 0.307 | E25: 0.307 | F25: 0.307 | G25: 0.307 | H25: 0.306 | I25: 0.306 | J25: 0.305 | K25: 0.305 | L25: 0.305 | M25: 0.305
A26: Bull | D26: 0.295 | E26: 0.29 | F26: 0.29 | G26: 0.2875 | H26: 0.285 | I26: 0.2825 | J26: 0.2825 | K26: 0.2825 | L26: 0.2825 | M26: 0.2825
A27: Bear | D27: 0.315 | E27: 0.3175 | F27: 0.32 | G27: 0.32 | H27: 0.32 | I27: 0.32 | J27: 0.32 | K27: 0.32 | L27: 0.32 | M27: 0.32
A30: Operating Expense
A32: SG&A | D32: {=INDEX(D33:D35,$C$3)} -> 0.255 | E32: {=INDEX(E33:E35,$C$3)} -> 0.255 | F32: {=INDEX(F33:F35,$C$3)} -> 0.255 | G32: {=INDEX(G33:G35,$C$3)} -> 0.25 | H32: {=INDEX(H33:H35,$C$3)} -> 0.25 | I32: {=INDEX(I33:I35,$C$3)} -> 0.245 | J32: {=INDEX(J33:J35,$C$3)} -> 0.245 | K32: {=INDEX(K33:K35,$C$3)} -> 0.24 | ... M32: {=INDEX(M33:M35,$C$3)} -> 0.24
A33: Base | D33: 0.255 | E33: 0.255 | F33: 0.255 | G33: 0.25 | H33: 0.25 | I33: 0.245 | J33: 0.245 | K33: 0.24 | L33: 0.24 | M33: 0.24
A34: Bull | D34: 0.2475 | E34: 0.245 | F34: 0.245 | G34: 0.24 | H34: 0.24 | I34: 0.24 | J34: 0.24 | K34: 0.2375 | L34: 0.2375 | M34: 0.2375
A35: Bear | D35: 0.2625 | E35: 0.265 | F35: 0.2675 | G35: 0.2675 | H35: 0.2675 | I35: 0.2675 | J35: 0.2675 | K35: 0.2675 | L35: 0.2675 | M35: 0.2675
A37: R&D | D37: {=INDEX(D38:D40,$C$3)} -> 0.2 | E37: {=INDEX(E38:E40,$C$3)} -> 0.2 | F37: {=INDEX(F38:F40,$C$3)} -> 0.2 | G37: {=INDEX(G38:G40,$C$3)} -> 0.2 | H37: {=INDEX(H38:H40,$C$3)} -> 0.2 | I37: {=INDEX(I38:I40,$C$3)} -> 0.2 | J37: {=INDEX(J38:J40,$C$3)} -> 0.2 | K37: {=INDEX(K38:K40,$C$3)} -> 0.18 | ... M37: {=INDEX(M38:M40,$C$3)} -> 0.18
A38: Base | D38: 0.2 | E38: 0.2 | F38: 0.2 | G38: 0.2 | H38: 0.2 | I38: 0.2 | J38: 0.2 | K38: 0.18 | L38: 0.18 | M38: 0.18
A39: Bull | D39: 0.18 | E39: 0.18 | F39: 0.18 | G39: 0.18 | H39: 0.18 | I39: 0.18 | J39: 0.18 | K39: 0.18 | L39: 0.18 | M39: 0.18
A40: Bear | D40: 0.21 | E40: 0.2125 | F40: 0.215 | G40: 0.215 | H40: 0.215 | I40: 0.215 | J40: 0.215 | K40: 0.215 | L40: 0.215 | M40: 0.215
A43: Capex | D43: {=INDEX(D44:D46,$C$3)} -> 0.035 | E43: {=INDEX(E44:E46,$C$3)} -> 0.035 | F43: {=INDEX(F44:F46,$C$3)} -> 0.035 | G43: {=INDEX(G44:G46,$C$3)} -> 0.035 | H43: {=INDEX(H44:H46,$C$3)} -> 0.035 | I43: {=INDEX(I44:I46,$C$3)} -> 0.035 | J43: {=INDEX(J44:J46,$C$3)} -> 0.035 | K43: {=INDEX(K44:K46,$C$3)} -> 0.035 | ... M43: {=INDEX(M44:M46,$C$3)} -> 0.035
A44: Base | D44: 0.035 | E44: 0.035 | F44: 0.035 | G44: 0.035 | H44: 0.035 | I44: 0.035 | J44: 0.035 | K44: 0.035 | L44: 0.035 | M44: 0.035
A45: Bull | D45: 0.0275 | E45: 0.0275 | F45: 0.0275 | G45: 0.0275 | H45: 0.0275 | I45: 0.0275 | J45: 0.0275 | K45: 0.0275 | L45: 0.0275 | M45: 0.0275
A46: Bear | D46: 0.0425 | E46: 0.0425 | F46: 0.0425 | G46: 0.0425 | H46: 0.0425 | I46: 0.0425 | J46: 0.0425 | K46: 0.0425 | L46: 0.0425 | M46: 0.0425
A48: Other Income | D48: {=INDEX(D49:D51,$C$3)} -> 0 | E48: 0 | F48: {=INDEX(F49:F51,$C$3)} -> 0 | G48: {=INDEX(G49:G51,$C$3)} -> 0 | H48: {=INDEX(H49:H51,$C$3)} -> 0 | I48: {=INDEX(I49:I51,$C$3)} -> 0 | J48: {=INDEX(J49:J51,$C$3)} -> 0 | K48: {=INDEX(K49:K51,$C$3)} -> 0 | L48: {=INDEX(L49:L51,$C$3)} -> 0 | M48: {=INDEX(M49:M51,$C$3)} -> 0
A49: Base | D49: 0 | E49: 0 | F49: 0 | G49: 0 | H49: 0 | I49: 0 | J49: 0 | K49: 0 | L49: 0 | M49: 0
A50: Bull | D50: 0 | E50: 0 | F50: 0 | G50: 0 | H50: 0 | I50: 0 | J50: 0 | K50: 0 | L50: 0 | M50: 0
A51: Bear
A53: Income Tax
A54: Base
A55: Bull
A56: Bear

Sheet DCF
A1: Johnsoon & Johnson Services Inc.,
A2: Discounted Cash Flow Analysis
A3: For the Years Ended
A4: Millions of Dollars
N5: Terminal
B6: =2023 -> 2023 | C6: =+B6+1 -> 2024 | D6: =+C6+1 -> 2025 | E6: =+D6+1 -> 2026 | F6: =+E6+1 -> 2027 | G6: =+F6+1 -> 2028 | H6: =+G6+1 -> 2029 | I6: =+H6+1 -> 2030 | J6: =+I6+1 -> 2031 | ... M6: =+L6+1 -> 2034 | N6: Value
B7: -------------- | C7: -------------- | D7: -------------- | E7: -------------- | F7: -------------- | G7: -------------- | H7: -------------- | I7: -------------- | J7: -------------- | K7: -------------- | L7: -------------- | M7: -------------- | N7: --------------
A8: Revenue | B8: 85159 | C8: 88821 | D8: =SUM(D9:D10) -> 92373.84 | E8: =SUM(E9:E10) -> 95950.308 | F8: =SUM(F9:F10) -> 99665.333 | G8: =SUM(G9:G10) -> 103524.29 | H8: =SUM(H9:H10) -> 107147.64 | I8: =SUM(I9:I10) -> 108497.68 | J8: =SUM(J9:J10) -> 111609.34 | K8: =SUM(K9:K10) -> 114461.33 | ... M8: =SUM(M9:M10) -> 120403.83
A9: Total Medicine Theraputic | B9: 54759 | C9: 56964 | D9: =C9*(1+D60) -> 59242.56 | E9: =D9*(1+E60) -> 61493.777 | F9: =E9*(1+F60) -> 63830.541 | G9: =F9*(1+G60) -> 66256.101 | H9: =G9*(1+H60) -> 68575.065 | I9: =H9*(1+I60) -> 68575.065 | J9: =I9*(1+J60) -> 70289.442 | K9: =J9*(1+K60) -> 71695.23 | ... M9: =L9*(1+M60) -> 74591.718
A10: Total MedTech Sales | B10: 30400 | C10: 31857 | D10: =C10*(1+D61) -> 33131.28 | E10: =D10*(1+E61) -> 34456.531 | F10: =E10*(1+F61) -> 35834.792 | G10: =F10*(1+G61) -> 37268.184 | H10: =G10*(1+H61) -> 38572.571 | I10: =H10*(1+I61) -> 39922.611 | J10: =I10*(1+J61) -> 41319.902 | K10: =J10*(1+K61) -> 42766.098 | ... M10: =L10*(1+M61) -> 45812.114
A11: Cost of Goods Sold | B11: 26553 | C11: 27471 | D11: =D8*D62 -> 28358.769 | E11: =E8*E62 -> 29456.745 | F11: =F8*F62 -> 30597.257 | G11: =G8*G62 -> 31781.956 | H11: =H8*H62 -> 32787.176 | I11: =I8*I62 -> 33200.289 | J11: =J8*J62 -> 34040.85 | K11: =K8*K62 -> 34910.705 | ... M11: =M8*M62 -> 36723.169
B12: -------------- | C12: -------------- | D12: -------------- | E12: -------------- | F12: -------------- | G12: -------------- | H12: -------------- | I12: -------------- | J12: -------------- | K12: -------------- | L12: -------------- | M12: --------------
A13: Gross Margin | B13: =+B8-B11 -> 58606 | C13: =+C8-C11 -> 61350 | D13: =D8-D11 -> 64015.071 | E13: =E8-E11 -> 66493.564 | F13: =F8-F11 -> 69068.076 | G13: =G8-G11 -> 71742.33 | H13: =H8-H11 -> 74360.459 | I13: =I8-I11 -> 75297.387 | J13: =J8-J11 -> 77568.494 | K13: =K8-K11 -> 79550.624 | ... M13: =M8-M11 -> 83680.663
A15: Operating Expenses:
A16: SG&A | B16: 21512 | C16: 22869 | D16: =D8*D67 -> 23555.329 | E16: =E8*E67 -> 24467.329 | F16: =F8*F67 -> 25414.66 | G16: =G8*G67 -> 25881.071 | H16: =H8*H67 -> 26786.909 | I16: =I8*I67 -> 26581.93 | J16: =J8*J67 -> 27344.289 | K16: =K8*K67 -> 27470.719 | ... M16: =M8*M67 -> 28896.92
A17: R&D | B17: 15085 | C17: 17232 | D17: =D8*D68 -> 18474.768 | E17: =E8*E68 -> 19190.062 | F17: =F8*F68 -> 19933.067 | G17: =G8*G68 -> 20704.857 | H17: =H8*H68 -> 21429.527 | I17: =I8*I68 -> 21699.535 | J17: =J8*J68 -> 22321.869 | K17: =K8*K68 -> 20603.039 | ... M17: =M8*M68 -> 21672.69
A18: Lease | B18: 200 | C18: 200 | D18: 200 | E18: 200 | F18: 200 | G18: 200 | H18: 200 | I18: 200 | J18: 200 | K18: 200 | L18: 200 | M18: 200
B19: -------------- | C19: -------------- | D19: -------------- | E19: -------------- | F19: -------------- | G19: -------------- | H19: -------------- | I19: -------------- | J19: -------------- | K19: -------------- | L19: -------------- | M19: --------------
A20: Total Operating Expenses | B20: =SUM(B16:B19) -> 36797 | C20: =SUM(C16:C19) -> 40301 | D20: =SUM(D16:D18) -> 42230.097 | E20: =SUM(E16:E18) -> 43857.39 | F20: =SUM(F16:F18) -> 45547.727 | G20: =SUM(G16:G18) -> 46785.928 | H20: =SUM(H16:H18) -> 48416.436 | I20: =SUM(I16:I18) -> 48481.466 | J20: =SUM(J16:J18) -> 49866.158 | K20: =SUM(K16:K18) -> 48273.758 | ... M20: =SUM(M16:M18) -> 50769.609
B21: -------------- | C21: -------------- | D21: -------------- | E21: -------------- | F21: -------------- | G21: -------------- | H21: -------------- | I21: -------------- | J21: -------------- | K21: -------------- | L21: -------------- | M21: --------------
A22: Operating Income | B22: =+B13-B20 -> 21809 | C22: =+C13-C20 -> 21049 | D22: =D13-D20 -> 21784.974 | E22: =E13-E20 -> 22636.173 | F22: =F13-F20 -> 23520.349 | G22: =G13-G20 -> 24956.401 | H22: =H13-H20 -> 25944.023 | I22: =I13-I20 -> 26815.921 | J22: =J13-J20 -> 27702.336 | K22: =K13-K20 -> 31276.865 | ... M22: =M13-M20 -> 32911.054
A24: Other Income/(Expense) | B24: =+B8*B75 -> 0 | C24: =+C8*C75 -> 0 | D24: =D75*D8 -> 0 | E24: =E75*E8 -> 0 | F24: =F75*F8 -> 0 | G24: =G75*G8 -> 0 | H24: =H75*H8 -> 0 | I24: =I75*I8 -> 0 | J24: =J75*J8 -> 0 | K24: =K75*K8 -> 0 | ... M24: =M75*M8 -> 0
B25: -------------- | C25: -------------- | D25: -------------- | E25: -------------- | F25: -------------- | G25: -------------- | H25: -------------- | I25: -------------- | J25: -------------- | K25: -------------- | L25: -------------- | M25: --------------
A26: Pretax Income | B26: =+B22+SUM(B24:B25) -> 21809 | C26: =+C22+SUM(C24:C25) -> 21049 | D26: =SUM(D22:D24) -> 21784.974 | E26: =SUM(E22:E24) -> 22636.173 | F26: =SUM(F22:F24) -> 23520.349 | G26: =SUM(G22:G24) -> 24956.401 | H26: =SUM(H22:H24) -> 25944.023 | I26: =SUM(I22:I24) -> 26815.921 | J26: =SUM(J22:J24) -> 27702.336 | K26: =SUM(K22:K24) -> 31276.865 | ... M26: =SUM(M22:M24) -> 32911.054
A27: Income Taxes | B27: =+B26*B78 -> 3009.642 | C27: =+C26*C78 -> 3304.693 | D27: =D26*D78 -> 3594.5207 | E27: =E26*E78 -> 3734.9686 | F27: =F26*F78 -> 3880.8576 | G27: =G26*G78 -> 4117.8062 | H27: =H26*H78 -> 4280.7638 | I27: =I26*I78 -> 4424.627 | J27: =J26*J78 -> 4570.8854 | K27: =K26*K78 -> 5160.6828 | ... M27: =M26*M78 -> 5430.3239
B28: -------------- | C28: -------------- | D28: -------------- | E28: -------------- | F28: -------------- | G28: -------------- | H28: -------------- | I28: -------------- | J28: -------------- | K28: -------------- | L28: -------------- | M28: --------------
A29: Net Income | B29: =+B26-B27 -> 18799.358 | C29: =+C26-C27 -> 17744.307 | D29: =D26-D27 -> 18190.453 | E29: =E26-E27 -> 18901.205 | F29: =F26-F27 -> 19639.492 | G29: =G26-G27 -> 20838.595 | H29: =H26-H27 -> 21663.259 | I29: =I26-I27 -> 22391.294 | J29: =J26-J27 -> 23131.45 | K29: =K26-K27 -> 26116.183 | ... M29: =M26-M27 -> 27480.73
A31: + Depreciation & Amortization | B31: =B121 -> 7286 | C31: =C121 -> 7139 | D31: =D121 -> 5722.9753 | E31: =E121 -> 5175.4407 | F31: =F121 -> 4635.1299 | G31: =G121 -> 4102.3225 | H31: =H121 -> 4176.5606 | I31: =I121 -> 4253.4237 | ... M31: =M121 -> 4618.9681
A32: - Capital Expenditures | B32: -4543 | C32: -4424 | D32: =-D8*D84 -> -3233.0844 | E32: =-E8*E84 -> -3358.2608 | F32: =-F8*F84 -> -3488.2867 | G32: =-G8*G84 -> -3623.35 | H32: =-H8*H84 -> -3750.1672 | I32: =-I8*I84 -> -3797.4186 | J32: =-J8*J84 -> -3906.327 | K32: =-K8*K84 -> -4006.1465 | ... M32: =-M8*M84 -> -4214.1341
A33: - Working Capital Additions | B33: -6000 | C33: -3300 | D33: =(C8-D8)*$B$86 -> -532.926 | E33: =(D8-E8)*$B$86 -> -536.47027 | F33: =(E8-F8)*$B$86 -> -557.25372 | G33: =(F8-G8)*$B$86 -> -578.84284 | H33: =(G8-H8)*$B$86 -> -543.5025 | I33: =(H8-I8)*$B$86 -> -202.506 | J33: =(I8-J8)*$B$86 -> -466.7502 | K33: =(J8-K8)*$B$86 -> -427.79781 | ... M33: =(L8-M8)*$B$86 -> -451.76769
B34: -------------- | C34: -------------- | D34: -------------- | E34: -------------- | F34: -------------- | G34: -------------- | H34: -------------- | I34: -------------- | J34: -------------- | K34: -------------- | L34: -------------- | M34: --------------
A35: Free Cash Flow | B35: =+B29+SUM(B31:B34) -> 15542.358 | C35: =+C29+SUM(C31:C34) -> 17159.307 | D35: =(D29+SUM(D31:D33))*0.75 -> 15110.564 | E35: =E29+SUM(E31:E33) -> 20181.914 | F35: =F29+SUM(F31:F33) -> 20229.081 | G35: =G29+SUM(G31:G33) -> 20738.725 | H35: =H29+SUM(H31:H33) -> 21546.15 | I35: =I29+SUM(I31:I33) -> 22644.793 | J35: =J29+SUM(J31:J33) -> 23094.711 | K35: =K29+SUM(K31:K33) -> 26107.035 | L35: =L29+SUM(L31:L33) -> 26759.774 | M35: =M29+SUM(M31:M33) -> 27433.796 | N35: =M29*(1-0.01/0.1337)/(B96-0.01) -> 487621.71
A36: Present Value Factor | D36: =1/(1+$B$96)^(D97/12) -> 0.99249243 | E36: =1/(1+$B$96)^(E97/12) -> 0.95579162 | F36: =1/(1+$B$96)^(F97/12) -> 0.89987221 | G36: =1/(1+$B$96)^(G97/12) -> 0.84722441 | H36: =1/(1+$B$96)^(H97/12) -> 0.79765682 | I36: =1/(1+$B$96)^(I97/12) -> 0.75098922 | J36: =1/(1+$B$96)^(J97/12) -> 0.70705195 | K36: =1/(1+$B$96)^(K97/12) -> 0.66568527 | ... N36: =1/(1+$B$96)^(N97/12) -> 0.57254945
D37: -------------- | E37: -------------- | F37: -------------- | G37: -------------- | H37: -------------- | I37: -------------- | J37: -------------- | K37: -------------- | L37: -------------- | M37: -------------- | N37: --------------
A38: PV Free Cash Flow | D38: =D35*D36 -> 14997.12 | E38: =E35*E36 -> 19289.705 | F38: =+F35*F36 -> 18203.588 | G38: =+G35*G36 -> 17570.354 | H38: =+H35*H36 -> 17186.434 | I38: =+I35*I36 -> 17005.996 | J38: =+J35*J36 -> 16329.16 | K38: =+K35*K36 -> 17379.069 | L38: =+L35*L36 -> 16771.388 | M38: =+M35*M36 -> 16187.885 | N38: =+N35*N36 -> 279187.54
D39: --------------
A40: Value of Firm | D40: =SUM(D38:N38) -> 450108.24
A41: Less: Debt Outstanding | D41: -37834
A42: Plus: Cash | D42: 24522
D43: --------------
A44: Equity Value | D44: =SUM(D40:D42) -> 436796.24
A45: Shares Outstanding | D45: 2409.8
D46: --------------
A47: Value Per Share | D47: =D44/D45 -> 181.2583
D48: ========
A50: Share Price (2/12/25) | D50: 155
A52: Johnsoon & Johnson Services Inc.,
A53: Discounted Cash Flow Analysis
A54: For the Years Ended
A55: Assumptions
B57: =2023 -> 2023 | C57: =+B57+1 -> 2024 | D57: =+C57+1 -> 2025 | E57: =+D57+1 -> 2026 | F57: =+E57+1 -> 2027 | G57: =+F57+1 -> 2028 | H57: =+G57+1 -> 2029 | I57: =+H57+1 -> 2030 | J57: =+I57+1 -> 2031 | ... M57: =+L57+1 -> 2034
B58: -------------- | C58: -------------- | D58: -------------- | E58: -------------- | F58: -------------- | G58: -------------- | H58: -------------- | I58: -------------- | J58: -------------- | K58: -------------- | L58: -------------- | M58: --------------
A59: Revenue Growth | B59: 0.0646 | C59: =+C8/B8-1 -> 0.043001914 | D59: =(D8/C8)-1 -> 0.04 | E59: =(E8/D8)-1 -> 0.03871733 | F59: =(F8/E8)-1 -> 0.038718216 | G59: =(G8/F8)-1 -> 0.038719102 | H59: =(H8/G8)-1 -> 0.035 | I59: =(I8/H8)-1 -> 0.012599811 | J59: =(J8/I8)-1 -> 0.028679582 | K59: =(K8/J8)-1 -> 0.025553285 | ... M59: =(M8/L8)-1 -> 0.025655781
A60: Total Medicine Theraputic | D60: =Assumption!D11 -> 0.04 | E60: =Assumption!E11 -> 0.038 | F60: =Assumption!F11 -> 0.038 | G60: =Assumption!G11 -> 0.038 | H60: =Assumption!H11 -> 0.035 | I60: =Assumption!I11 -> 0 | J60: =Assumption!J11 -> 0.025 | K60: =Assumption!K11 -> 0.02 | ... M60: =Assumption!M11 -> 0.02
A61: Total MedTech Sales | D61: =Assumption!D17 -> 0.04 | E61: =Assumption!E17 -> 0.04 | F61: =Assumption!F17 -> 0.04 | G61: =Assumption!G17 -> 0.04 | H61: =Assumption!H17 -> 0.035 | I61: =Assumption!I17 -> 0.035 | J61: =Assumption!J17 -> 0.035 | K61: =Assumption!K17 -> 0.035 | ... M61: =Assumption!M17 -> 0.035
A62: Cost of Goods Sold | B62: =+B11/B8 -> 0.31180498 | C62: =+C11/C8 -> 0.30928497 | D62: =Assumption!D25 -> 0.307 | E62: =Assumption!E25 -> 0.307 | F62: =Assumption!F25 -> 0.307 | G62: =Assumption!G25 -> 0.307 | H62: =Assumption!H25 -> 0.306 | I62: =Assumption!I25 -> 0.306 | J62: =Assumption!J25 -> 0.305 | K62: =Assumption!K25 -> 0.305 | ... M62: =Assumption!M25 -> 0.305
B63: -------------- | C63: -------------- | D63: -------------- | E63: -------------- | F63: -------------- | G63: -------------- | H63: -------------- | I63: -------------- | J63: -------------- | K63: -------------- | L63: -------------- | M63: --------------
A64: Gross Margin | B64: =+B13/B8 -> 0.68819502 | C64: =+C13/C8 -> 0.69071503 | D64: =Assumption!D23 -> 0.693 | E64: =Assumption!E23 -> 0.693 | F64: =Assumption!F23 -> 0.693 | G64: =Assumption!G23 -> 0.693 | H64: =Assumption!H23 -> 0.694 | I64: =Assumption!I23 -> 0.694 | J64: =Assumption!J23 -> 0.695 | K64: =Assumption!K23 -> 0.695 | ... M64: =Assumption!M23 -> 0.695
A66: Operating Expenses:
A67: SG&A | B67: =+B16/B8 -> 0.25260982 | C67: =+C16/C8 -> 0.25747289 | D67: =Assumption!D32 -> 0.255 | E67: =Assumption!E32 -> 0.255 | F67: =Assumption!F32 -> 0.255 | G67: =Assumption!G32 -> 0.25 | H67: =Assumption!H32 -> 0.25 | I67: =Assumption!I32 -> 0.245 | J67: =Assumption!J32 -> 0.245 | K67: =Assumption!K32 -> 0.24 | ... M67: =Assumption!M32 -> 0.24
A68: R&D | B68: =+B17/B8 -> 0.17713923 | C68: =+C17/C8 -> 0.19400817 | D68: =Assumption!D37 -> 0.2 | E68: =Assumption!E37 -> 0.2 | F68: =Assumption!F37 -> 0.2 | G68: =Assumption!G37 -> 0.2 | H68: =Assumption!H37 -> 0.2 | I68: =Assumption!I37 -> 0.2 | J68: =Assumption!J37 -> 0.2 | K68: =Assumption!K37 -> 0.18 | ... M68: =Assumption!M37 -> 0.18
A69: Lease | B69: =+B18/B8 -> 0.002348548 | C69: =+C18/C8 -> 0.0022517198 | D69: =+D18/D8 -> 0.0021651151 | E69: =+E18/E8 -> 0.0020844123 | F69: =+F18/F8 -> 0.0020067158 | G69: =+G18/G8 -> 0.0019319138 | H69: =+H18/H8 -> 0.0018665834 | I69: =+I18/I8 -> 0.0018433575 | ... M69: =+M18/M8 -> 0.0016610767
B70: -------------- | C70: -------------- | D70: -------------- | E70: -------------- | F70: -------------- | G70: -------------- | H70: -------------- | I70: -------------- | J70: -------------- | K70: -------------- | L70: -------------- | M70: --------------
A71: Total Operating Expenses | B71: =+B20/B8 -> 0.43209761 | C71: =+C20/C8 -> 0.45373279 | D71: =+D20/D8 -> 0.45716512 | E71: =+E20/E8 -> 0.45708441 | F71: =+F20/F8 -> 0.45700672 | G71: =+G20/G8 -> 0.45193191 | H71: =+H20/H8 -> 0.45186658 | I71: =+I20/I8 -> 0.44684336 | ... M71: =+M20/M8 -> 0.42166108
B72: -------------- | C72: -------------- | D72: -------------- | E72: -------------- | F72: -------------- | G72: -------------- | H72: -------------- | I72: -------------- | J72: -------------- | K72: -------------- | L72: -------------- | M72: --------------
A73: Operating Income | B73: =+B22/B8 -> 0.25609742 | C73: =+C22/C8 -> 0.23698225 | D73: =D22/D13 -> 0.34031008 | E73: =E22/E13 -> 0.34042653 | F73: =F22/F13 -> 0.34053865 | G73: =G22/G13 -> 0.3478616 | H73: =H22/H13 -> 0.34889541 | I73: =I22/I13 -> 0.35613349 | J73: =J22/J13 -> 0.35713386 | K73: =K22/K13 -> 0.39316933 | ... M73: =M22/M13 -> 0.39329341
A75: Other Income/(Expense) | B75: 0 | C75: 0 | D75: =Assumption!D48 -> 0 | E75: =Assumption!E48 -> 0 | F75: =Assumption!F48 -> 0 | G75: =Assumption!G48 -> 0 | H75: =Assumption!H48 -> 0 | I75: =Assumption!I48 -> 0 | J75: =Assumption!J48 -> 0 | K75: =Assumption!K48 -> 0 | ... M75: =Assumption!M48 -> 0
B76: -------------- | C76: -------------- | D76: -------------- | E76: -------------- | F76: -------------- | G76: -------------- | H76: -------------- | I76: -------------- | J76: -------------- | K76: -------------- | L76: -------------- | M76: --------------
A77: Pretax Income | B77: =+B26/B8 -> 0.25609742 | C77: =+C26/C8 -> 0.23698225 | D77: =D26/D8 -> 0.23583488 | E77: =E26/E8 -> 0.23591559 | F77: =F26/F8 -> 0.23599328 | G77: =G26/G8 -> 0.24106809 | H77: =H26/H8 -> 0.24213342 | I77: =I26/I8 -> 0.24715664 | J77: =J26/J8 -> 0.24820804 | K77: =K26/K8 -> 0.27325268 | ... M77: =M26/M8 -> 0.27333892
A78: Income Tax Rate | B78: 0.138 | C78: 0.157 | D78: 0.165 | E78: 0.165 | F78: 0.165 | G78: 0.165 | H78: 0.165 | I78: 0.165 | J78: 0.165 | K78: 0.165 | L78: 0.165 | M78: 0.165
B79: -------------- | C79: -------------- | D79: -------------- | E79: -------------- | F79: -------------- | G79: -------------- | H79: -------------- | I79: -------------- | J79: -------------- | K79: -------------- | L79: -------------- | M79: --------------
A80: Net Income | B80: =+B29/B8 -> 0.22075597 | C80: =+C29/C8 -> 0.19977603 | D80: =D29/D8 -> 0.19692213 | E80: =E29/E8 -> 0.19698952 | F80: =F29/F8 -> 0.19705439 | G80: =G29/G8 -> 0.20129185 | H80: =H29/H8 -> 0.2021814 | I80: =I29/I8 -> 0.2063758 | J80: =J29/J8 -> 0.20725371 | K80: =K29/K8 -> 0.22816599 | ... M80: =M29/M8 -> 0.228238
A82: Net PP&E | B82: 19898 | C82: 20518 | D82: =C82-D118-D32 -> 21828.109 | E82: =D82-E118-E32 -> 23210.929 | F82: =E82-F118-F32 -> 24664.086 | G82: =F82-G118-G32 -> 26185.113 | H82: =G82-H118-H32 -> 27758.72 | I82: =H82-I118-I32 -> 29302.715 | J82: =I82-J118-J32 -> 30872.705 | K82: =J82-K118-K32 -> 32454.055 | ... M82: =L82-M118-M32 -> 35638.988
A83: Revenue/Net PP&E | B83: =+B8/B82 -> 4.2797769 | C83: =+C8/C82 -> 4.3289307 | D83: =D8/D82 -> 4.2318755 | E83: =E8/E82 -> 4.1338418 | F83: =F8/F82 -> 4.0409093 | G83: =G8/G82 -> 3.953555 | H83: =H8/H82 -> 3.8599631 | I83: =I8/I82 -> 3.7026492 | J83: =J8/J82 -> 3.6151463 | K83: =K8/K82 -> 3.526873 | ... M83: =M8/M82 -> 3.3784301
A84: Capital Expenditure % of Rev | B84: =-B32/B8 -> 0.053347268 | C84: =-C32/C8 -> 0.049808041 | D84: =Assumption!D43 -> 0.035 | E84: =Assumption!E43 -> 0.035 | F84: =Assumption!F43 -> 0.035 | G84: =Assumption!G43 -> 0.035 | H84: =Assumption!H43 -> 0.035 | I84: =Assumption!I43 -> 0.035 | J84: =Assumption!J43 -> 0.035 | K84: =Assumption!K43 -> 0.035 | ... M84: =Assumption!M43 -> 0.035
A85: Depreciation/Revenue | B85: =+B118/B8 -> 0.035063822 | C85: =+C118/C8 -> 0.031963162 | D85: =D118/D8 -> 0.020817314 | E85: =E118/E8 -> 0.020588165 | F85: =F118/F8 -> 0.020419636 | G85: =G118/G8 -> 0.02030753 | H85: =H118/H8 -> 0.020313659 | I85: =I118/I8 -> 0.020769327 | J85: =J118/J8 -> 0.020933169 | K85: =K118/K8 -> 0.021184416 | ... M85: =M118/M8 -> 0.021751535
A86: Working Capital/Revenue | B86: 0.15
A88: Discount Rate:
A89: Risk-Free Rate | B89: 0.042
A90: Risk Premium | B90: 0.045
A91: Beta | B91: 0.5
A92: K(e) | B92: =B89+B91*B90 -> 0.0645
A93: K(d) | B93: 0.049
A94: Tax Rate | B94: 0.165
A95: Debt/Capital | B95: 0.1
A96: WACC | B96: =(B93*(1-B94)*B95+B92*(1-B95)) -> 0.0621415
B97: 0 | C97: 0 | D97: 1.5 | E97: 9 | F97: =+E97+12 -> 21 | G97: =+F97+12 -> 33 | H97: =+G97+12 -> 45 | I97: =+H97+12 -> 57 | J97: =+I97+12 -> 69 | K97: =+J97+12 -> 81 | L97: =+K97+12 -> 93 | M97: =+L97+12 -> 105 | N97: =+M97+6 -> 111
A99: Johnsoon & Johnson Services Inc.,
A100: Discounted Cash Flow Analysis
A101: For the Years Ended
A102: Depreciation Schedule
B104: =2023 -> 2023 | C104: =+B104+1 -> 2024 | D104: =+C104+1 -> 2025 | E104: =+D104+1 -> 2026 | F104: =+E104+1 -> 2027 | G104: =+F104+1 -> 2028 | H104: =+G104+1 -> 2029 | I104: =+H104+1 -> 2030 | J104: =+I104+1 -> 2031 | ... M104: =+L104+1 -> 2034
B105: -------------- | C105: -------------- | D105: -------------- | E105: -------------- | F105: -------------- | G105: -------------- | H105: -------------- | I105: -------------- | J105: -------------- | K105: -------------- | L105: -------------- | M105: --------------
A106: 2024 Net PP&E | D106: =$C$82*(2038-D104)/153 -> 1743.3595 | E106: =$C$82*(2038-E104)/153 -> 1609.2549 | F106: =$C$82*(2038-F104)/153 -> 1475.1503 | G106: =$C$82*(2038-G104)/153 -> 1341.0458 | H106: =$C$82*(2038-H104)/153 -> 1206.9412 | I106: =$C$82*(2038-I104)/153 -> 1072.8366 | J106: =$C$82*(2038-J104)/153 -> 938.73203 | K106: =$C$82*(2038-K104)/153 -> 804.62745 | ... M106: =$C$82*(2038-M104)/153 -> 536.4183
A107: 2025 Capital Expenditures | D107: =-$D$32/18 -> 179.6158 | E107: =-$D$32/18 -> 179.6158 | F107: =-$D$32/18 -> 179.6158 | G107: =-$D$32/18 -> 179.6158 | H107: =-$D$32/18 -> 179.6158 | I107: =-$D$32/18 -> 179.6158 | J107: =-$D$32/18 -> 179.6158 | K107: =-$D$32/18 -> 179.6158 | ... M107: =-$D$32/18 -> 179.6158
A108: 2026 Capital Expenditures | E108: =-$E$32/18 -> 186.57004 | F108: =-$E$32/18 -> 186.57004 | G108: =-$E$32/18 -> 186.57004 | H108: =-$E$32/18 -> 186.57004 | I108: =-$E$32/18 -> 186.57004 | J108: =-$E$32/18 -> 186.57004 | K108: =-$E$32/18 -> 186.57004 | L108: =-$E$32/18 -> 186.57004 | M108: =-$E$32/18 -> 186.57004
A109: 2027 Capital Expenditures | F109: =-$F$32/18 -> 193.7937 | G109: =-$F$32/18 -> 193.7937 | H109: =-$F$32/18 -> 193.7937 | I109: =-$F$32/18 -> 193.7937 | J109: =-$F$32/18 -> 193.7937 | K109: =-$F$32/18 -> 193.7937 | L109: =-$F$32/18 -> 193.7937 | M109: =-$F$32/18 -> 193.7937
A110: 2028 Capital Expenditures | G110: =-$G$32/18 -> 201.29722 | H110: =-$G$32/18 -> 201.29722 | I110: =-$G$32/18 -> 201.29722 | J110: =-$G$32/18 -> 201.29722 | K110: =-$G$32/18 -> 201.29722 | L110: =-$G$32/18 -> 201.29722 | M110: =-$G$32/18 -> 201.29722
A111: 2029 Capital Expenditures | H111: =-$H$32/18 -> 208.34262 | I111: =-$H$32/18 -> 208.34262 | J111: =-$H$32/18 -> 208.34262 | K111: =-$H$32/18 -> 208.34262 | L111: =-$H$32/18 -> 208.34262 | M111: =-$H$32/18 -> 208.34262
A112: 2030 Capital Expenditures | I112: =-$I$32/18 -> 210.9677 | J112: =-$I$32/18 -> 210.9677 | K112: =-$I$32/18 -> 210.9677 | L112: =-$I$32/18 -> 210.9677 | M112: =-$I$32/18 -> 210.9677
...
