Workbook

Sheet Lowe's FY2024
F1: Adjustments
D2: Reported ($) | E2: % | F2: Depriciation Expense | G2: Canadian Store Sales | H2: Normalized | I2: % | L2: Name | M2: Email
C3: Revenue | D3: 83674 | E3: =D3/$D$3 -> 1 | H3: =D3+SUM(F3:G3) -> 83674 | I3: =H3/$H$3 -> 1
C4: CoGS | D4: 55797 | E4: =D4/$D$3 -> 0.66683797 | F4: =1729-1972 -> -243 | H4: =D4+SUM(F4:G4) -> 55554 | I4: =H4/$H$3 -> 0.66393384 | L4: Sharang Mantri | M4: smantri3@illinois.edu
C6: Gross Margin | D6: =D3-D4 -> 27877 | E6: =D6/$D$3 -> 0.33316203 | H6: =H3-H4 -> 28120 | I6: =H6/$H$3 -> 0.33606616 | L6: Mike Feistel | M6: feistel2@illinois.edu
I7: =H7/$H$3 -> 0
C8: SG&A | D8: 15682 | E8: =D8/$D$3 -> 0.18741784 | G8: =63+43+54+80 -> 240 | H8: =D8+SUM(F8:G8) -> 15922 | I8: =H8/$H$3 -> 0.19028611 | L8: Shreya Ahuja | M8: shreyaa8@illinois.edu
C9: Depreciation & Amortization | D9: 1729 | E9: =D9/$D$3 -> 0.020663527 | F9: =-F4 -> 243 | H9: =D9+SUM(F9:G9) -> 1972 | I9: =H9/$H$3 -> 0.023567655
I10: =H10/$H$3 -> 0 | L10: Priyanka Chandramohan | M10: pc45@illinois.edu
C11: Total Operating Expenses | D11: =SUM(D8:D9) -> 17411 | E11: =D11/$D$3 -> 0.20808136 | H11: =SUM(H8:H9) -> 17894 | I11: =H11/$H$3 -> 0.21385377
I12: =H12/$H$3 -> 0
C13: Operating Income | D13: =D6-D11 -> 10466 | E13: =D13/$D$3 -> 0.12508067 | H13: =H6-H11 -> 10226 | I13: =H13/$H$3 -> 0.1222124
C15: Pretax Income | D15: 9153 | H15: =H13-1313 -> 8913
C16: Income Taxes | D16: 2196 | G16: =1-43 -> -42 | H16: =D16+G16 -> 2154
C17: Adjusted Net Income | D17: =D15-D16 -> 6957 | H17: =H15-H16 -> 6759
C18: Effective tax rate | D18: =D16/D15 -> 0.23992134 | H18: =H16/H15 -> 0.24166947

Sheet Lowe's Fy2023
F1: Adjustments
D2: Reported ($) | E2: % | F2: Depriciation Expense | G2: Canadian Store Sales | H2: Normalized | I2: %
C3: Revenue | D3: 86377 | E3: =D3/$D$3 -> 1 | H3: =D3+SUM(F3:G3) -> 86377 | I3: =H3/$H$3 -> 1
C4: CoGS | D4: 57533 | E4: =D4/$D$3 -> 0.66606851 | F4: =1717-1923 -> -206 | H4: =D4+SUM(F4:G4) -> 57327 | I4: =H4/$H$3 -> 0.66368362
C6: Gross Margin | D6: =D3-D4 -> 28844 | E6: =D6/$D$3 -> 0.33393149 | H6: =H3-H4 -> 29050 | I6: =H6/$H$3 -> 0.33631638
I7: =H7/$H$3 -> 0
C8: SG&A | D8: 15570 | E8: =D8/$D$3 -> 0.18025632 | G8: =63 -> 63 | H8: =D8+SUM(F8:G8) -> 15633 | I8: =H8/$H$3 -> 0.18098568
C9: Depreciation & Amortization | D9: 1717 | E9: =D9/$D$3 -> 0.019877977 | F9: =-F4 -> 206 | H9: =D9+SUM(F9:G9) -> 1923 | I9: =H9/$H$3 -> 0.022262871
I10: =H10/$H$3 -> 0
C11: Total Operating Expenses | D11: =SUM(D8:D9) -> 17287 | E11: =D11/$D$3 -> 0.2001343 | H11: =SUM(H8:H9) -> 17556 | I11: =H11/$H$3 -> 0.20324855
I12: =H12/$H$3 -> 0
C13: Operating Income | D13: =D6-D11 -> 11557 | E13: =D13/$D$3 -> 0.13379719 | H13: =H6-H11 -> 11494 | I13: =H13/$H$3 -> 0.13306783
C15: Pretax Income | D15: =D13-1382 -> 10175 | H15: =H13-1382 -> 10112
C16: Income Taxes | D16: 2449 | G16: =1 -> 1 | H16: =D16+G16 -> 2450
C17: Adjusted Net Income | D17: =D15-D16 -> 7726 | H17: =H15-H16 -> 7662
C18: Effective tax rate | D18: =D16/D15 -> 0.24068796 | H18: =H16/H15 -> 0.24228639

Sheet RoIC Lowe FY24
D1: FY 24 | F1: FY23
B2: Total Current Assets | D2: 20358 | F2: 19071
B3: Total Current Liabilities | D3: 18757 | F3: 15568
B4: Current Debt | D4: 2586 | F4: 537
B5: Total Assets | D5: 43102 | F5: 41795
B7: Long Term Assets | D7: =D5-D2 -> 22744 | F7: =F5-F2 -> 22724
B8: NWC | D8: =D2-(D3-D4) -> 4187 | F8: =F2-(F3-F4) -> 4040
B9: Revenue | D9: ='Lowe''s FY2024'!H3 -> 83674
B10: Net Income Available to all Stakeholders | D10: ='Lowe''s FY2024'!H13*(1-'Lowe''s FY2024'!H18) -> 7754.688
B11: Invested Capital | D11: =D8+D7 -> 26931 | F11: =F8+F7 -> 26764
B12: Average Invested Capital | D12: =AVERAGE(D11,F11) -> 26847.5
B14: Profit Margin | D14: =D10/D9 -> 0.092677391
B15: Asset Turnover | D15: =D9/D12 -> 3.1166403
B17: RoIC | D17: =D14*D15 -> 0.28884209

Sheet Home Depot FY2024
D2: Reported ($) | E2: % | F2: Depriciation Expense | G2: Intangible Amortization | H2: Normalized | I2: %
C3: Revenue | D3: 159514 | E3: =D3/$D$3 -> 1 | H3: =D3+F3+G3 -> 159514 | I3: =H3/$H$3 -> 1
C4: CoGS | D4: 106206 | E4: =D4/$D$3 -> 0.6658099 | F4: =3034-3336 -> -302 | H4: =D4+F4+G4 -> 105904 | I4: =H4/$H$3 -> 0.66391665 | K4: =I4-'Home Depot FY2023'!I4 -> 0.0014704397
C6: Gross Margin | D6: =D3-D4 -> 53308 | E6: =D6/$D$3 -> 0.3341901 | H6: =H3-H4 -> 53610 | I6: =H6/$H$3 -> 0.33608335 | K6: =I6-'Home Depot FY2023'!I6 -> -0.0014704397
C8: SG&A | D8: 28748 | E8: =D8/$D$3 -> 0.18022243 | H8: =D8+SUM(F8:G8) -> 28748 | I8: =H8/$H$3 -> 0.18022243 | K8: =I8-'Home Depot FY2023'!I8 -> 0.0060023809
C9: Depreciation & Amortization | D9: 3034 | E9: =D9/$D$3 -> 0.019020274 | F9: =-F4 -> 302 | H9: =D9+SUM(F9:G9) -> 3336 | I9: =H9/$H$3 -> 0.020913525 | K9: =I9-'Home Depot FY2023'!I9 -> -0.00035470906
C11: Total Operating Expenses | D11: =D8+D9 -> 31782 | E11: =D11/$D$3 -> 0.1992427 | H11: =SUM(H8:H9) -> 32084 | I11: =H11/$H$3 -> 0.20113595 | K11: =I11-'Home Depot FY2023'!I11 -> 0.0056476719
C13: Operating Income | D13: =D6-D11 -> 21526 | E13: =D13/$D$3 -> 0.1349474 | G13: 425 | H13: =H6-H11+G13 -> 21951 | I13: =H13/$H$3 -> 0.13761175 | K13: =I13-'Home Depot FY2023'!I13 -> -0.0044537686
C15: Pretax Income | D15: =D13-2120 -> 19406 | H15: =H13-2120 -> 19831
C16: Income Taxes | D16: 4600 | G16: -107 | H16: =D16+G16+F16 -> 4493
C17: Adjusted Net Income | D17: =D15-D16 -> 14806 | H17: =H15-H16 -> 15338
C18: Effective tax rate | D18: =D16/D15 -> 0.23704009 | H18: =H16/H15 -> 0.22656447

Sheet Home Depot FY2023
D2: Reported ($) | E2: % | F2: Depriciation Expense | G2: Debt Adjustments | H2: Normalized | I2: %
C3: Revenue | D3: 152669 | E3: =D3/$D$3 -> 1 | H3: =D3+F3+G3 -> 152669 | I3: =H3/$H$3 -> 1
C4: CoGS | D4: 101709 | E4: =D4/$D$3 -> 0.66620598 | F4: =2673-3247 -> -574 | H4: =D4+F4+G4 -> 101135 | I4: =H4/$H$3 -> 0.66244621
C6: Gross Margin | D6: =D3-D4 -> 50960 | E6: =D6/$D$3 -> 0.33379402 | H6: =H3-H4 -> 51534 | I6: =H6/$H$3 -> 0.33755379
C8: SG&A | D8: 26598 | E8: =D8/$D$3 -> 0.17422004 | H8: =D8+SUM(F8:G8) -> 26598 | I8: =H8/$H$3 -> 0.17422004
C9: Depreciation & Amortization | D9: 2673 | E9: =D9/$D$3 -> 0.017508466 | F9: =-F4 -> 574 | H9: =D9+SUM(F9:G9) -> 3247 | I9: =H9/$H$3 -> 0.021268234
C11: Total Operating Expenses | D11: =D8+D9 -> 29271 | E11: =D11/$D$3 -> 0.19172851 | H11: =SUM(H8:H9) -> 29845 | I11: =H11/$H$3 -> 0.19548828
C13: Operating Income | D13: =D6-D11 -> 21689 | E13: =D13/$D$3 -> 0.14206551 | H13: =H6-H11 -> 21689 | I13: =H13/$H$3 -> 0.14206551
C15: Pretax Income | D15: =D13-1765 -> 19924 | G15: -58 | H15: =H13-2120-G15 -> 19627
C16: Income Taxes | D16: 4781 | G16: 14 | H16: =D16+G16+F16 -> 4795
C17: Adjusted Net Income | D17: =D15-D16 -> 15143 | H17: =H15-H16 -> 14832
C18: Effective tax rate | D18: =D16/D15 -> 0.23996186 | H18: =H16/H15 -> 0.24430631

Sheet RoIC Home Depot FY24
D1: FY 24 | F1: FY23
B2: Total Current Assets | D2: 31683 | F2: 29775
B3: Total Current Liabilities | D3: 28661 | F3: 22015
B4: Current Debt | D4: 4898 | F4: 1368
B5: Total Assets | D5: 96119 | F5: 76530
B7: Long Term Assets | D7: =D5-D2 -> 64436 | F7: =F5-F2 -> 46755
B8: NWC | D8: =D2-(D3-D4) -> 7920 | F8: =F2-(F3-F4) -> 9128
B9: Revenue | D9: ='Home Depot FY2024'!H3 -> 159514
B10: Net Income Available to all Stakeholders | D10: ='Home Depot FY2024'!H13*(1-'Home Depot FY2024'!H18) -> 16977.683
B11: Invested Capital | D11: =D8+D7 -> 72356 | F11: =F8+F7 -> 55883
B12: Average Invested Capital | D12: =AVERAGE(D11,F11) -> 64119.5
B14: Profit Margin | D14: =D10/D9 -> 0.10643381
B15: Asset Turnover | D15: =D9/D12 -> 2.4877611
B17: RoIC | D17: =D14*D15 -> 0.2647819
