Workbook

Sheet Assumption
A2: Option Selection
A3: Operating Scenario | C3: 3
D4: Projected
D5: 2025 | E5: =D5+1 -> 2026 | F5: =E5+1 -> 2027 | G5: =F5+1 -> 2028 | H5: =G5+1 -> 2029 | I5: =H5+1 -> 2030 | J5: =I5+1 -> 2031 | K5: =J5+1 -> 2032 | L5: =K5+1 -> 2033 | M5: =L5+1 -> 2034
A8: Total Revenue Growth | D8: =CHOOSE($C$3,D9,D10,D11) -> 0.27 | E8: =CHOOSE($C$3,E9,E10,E11) -> 0.24 | F8: =CHOOSE($C$3,F9,F10,F11) -> 0.22 | G8: =CHOOSE($C$3,G9,G10,G11) -> 0.22 | H8: =CHOOSE($C$3,H9,H10,H11) -> 0.22 | I8: =CHOOSE($C$3,I9,I10,I11) -> 0.2 | J8: =CHOOSE($C$3,J9,J10,J11) -> 0.2 | K8: =CHOOSE($C$3,K9,K10,K11) -> 0.18 | ... M8: =CHOOSE($C$3,M9,M10,M11) -> 0.18
A9: Base | D9: 0.3 | E9: 0.27 | F9: 0.25 | G9: 0.25 | H9: 0.25 | I9: 0.23 | J9: 0.23 | K9: 0.21 | L9: 0.21 | M9: 0.21
A10: Bull | D10: 0.325 | E10: 0.3 | F10: 0.28 | G10: 0.28 | H10: 0.28 | I10: 0.26 | J10: 0.26 | K10: 0.24 | L10: 0.24 | M10: 0.24
A11: Bear | D11: 0.27 | E11: 0.24 | F11: 0.22 | G11: 0.22 | H11: 0.22 | I11: 0.2 | J11: 0.2 | K11: 0.18 | L11: 0.18 | M11: 0.18
A13: Gross Margin | D13: =1-D14 -> 0.57 | E13: =1-E14 -> 0.56 | F13: =1-F14 -> 0.56 | G13: =1-G14 -> 0.5625 | H13: =1-H14 -> 0.5625 | I13: =1-I14 -> 0.565 | J13: =1-J14 -> 0.565 | K13: =1-K14 -> 0.57 | ... M13: =1-M14 -> 0.57
A14: COGS | D14: {=INDEX(D15:D17,$C$3)} -> 0.43 | E14: {=INDEX(E15:E17,$C$3)} -> 0.44 | F14: {=INDEX(F15:F17,$C$3)} -> 0.44 | G14: {=INDEX(G15:G17,$C$3)} -> 0.4375 | H14: {=INDEX(H15:H17,$C$3)} -> 0.4375 | I14: {=INDEX(I15:I17,$C$3)} -> 0.435 | J14: {=INDEX(J15:J17,$C$3)} -> 0.435 | K14: {=INDEX(K15:K17,$C$3)} -> 0.43 | ... M14: {=INDEX(M15:M17,$C$3)} -> 0.43
A15: Base | D15: 0.4083 | E15: 0.425 | F15: 0.425 | G15: 0.42 | H15: 0.42 | I15: 0.415 | J15: 0.415 | K15: 0.415 | L15: 0.415 | M15: 0.415
A16: Bull | D16: 0.3925 | E16: 0.4125 | F16: 0.4125 | G16: 0.4075 | H16: 0.4075 | I16: 0.4025 | J16: 0.4025 | K16: 0.4025 | L16: 0.4025 | M16: 0.4025
A17: Bear | D17: 0.43 | E17: 0.44 | F17: 0.44 | G17: 0.4375 | H17: 0.4375 | I17: 0.435 | J17: 0.435 | K17: 0.43 | L17: 0.43 | M17: 0.43
A20: Operating Expense
A22: SG&A | D22: {=INDEX(D23:D25,$C$3)} -> 0.03 | E22: {=INDEX(E23:E25,$C$3)} -> 0.033 | F22: {=INDEX(F23:F25,$C$3)} -> 0.035 | G22: {=INDEX(G23:G25,$C$3)} -> 0.035 | H22: {=INDEX(H23:H25,$C$3)} -> 0.035 | I22: {=INDEX(I23:I25,$C$3)} -> 0.035 | J22: {=INDEX(J23:J25,$C$3)} -> 0.035 | K22: {=INDEX(K23:K25,$C$3)} -> 0.035 | ... M22: {=INDEX(M23:M25,$C$3)} -> 0.035
A23: Base | D23: 0.0271 | E23: 0.028 | F23: 0.03 | G23: 0.03 | H23: 0.03 | I23: 0.03 | J23: 0.03 | K23: 0.03 | L23: 0.03 | M23: 0.03
A24: Bull | D24: 0.025 | E24: 0.0255 | F24: 0.0325 | G24: 0.0325 | H24: 0.0325 | I24: 0.0325 | J24: 0.0325 | K24: 0.0325 | L24: 0.0325 | M24: 0.0325
A25: Bear | D25: 0.03 | E25: 0.033 | F25: 0.035 | G25: 0.035 | H25: 0.035 | I25: 0.035 | J25: 0.035 | K25: 0.035 | L25: 0.035 | M25: 0.035
A27: R&D | D27: {=INDEX(D28:D30,$C$3)} -> 0.08 | E27: {=INDEX(E28:E30,$C$3)} -> 0.085 | F27: {=INDEX(F28:F30,$C$3)} -> 0.0865 | G27: {=INDEX(G28:G30,$C$3)} -> 0.0815 | H27: {=INDEX(H28:H30,$C$3)} -> 0.0815 | I27: {=INDEX(I28:I30,$C$3)} -> 0.0815 | J27: {=INDEX(J28:J30,$C$3)} -> 0.0815 | K27: {=INDEX(K28:K30,$C$3)} -> 0.0815 | ... M27: {=INDEX(M28:M30,$C$3)} -> 0.0815
A28: Base | D28: 0.075 | E28: 0.08 | F28: 0.082 | G28: 0.077 | H28: 0.077 | I28: 0.077 | J28: 0.077 | K28: 0.077 | L28: 0.077 | M28: 0.077
A29: Bull | D29: 0.0725 | E29: 0.0775 | F29: 0.0795 | G29: 0.0755 | H29: 0.0755 | I29: 0.0755 | J29: 0.0755 | K29: 0.0755 | L29: 0.0755 | M29: 0.0755
A30: Bear | D30: 0.08 | E30: 0.085 | F30: 0.0865 | G30: 0.0815 | H30: 0.0815 | I30: 0.0815 | J30: 0.0815 | K30: 0.0815 | L30: 0.0815 | M30: 0.0815
A33: Capex | D33: {=INDEX(D34:D36,$C$3)} -> 0.4025 | E33: {=INDEX(E34:E36,$C$3)} -> 0.3725 | F33: {=INDEX(F34:F36,$C$3)} -> 0.3725 | G33: {=INDEX(G34:G36,$C$3)} -> 0.3525 | H33: {=INDEX(H34:H36,$C$3)} -> 0.3525 | I33: {=INDEX(I34:I36,$C$3)} -> 0.3425 | J33: {=INDEX(J34:J36,$C$3)} -> 0.3425 | K33: {=INDEX(K34:K36,$C$3)} -> 0.3425 | ... M33: {=INDEX(M34:M36,$C$3)} -> 0.3425
A34: Base | D34: 0.4 | E34: 0.37 | F34: 0.37 | G34: 0.35 | H34: 0.35 | I34: 0.34 | J34: 0.34 | K34: 0.34 | L34: 0.34 | M34: 0.34
A35: Bull | D35: 0.3975 | E35: 0.3675 | F35: 0.3675 | G35: 0.3475 | H35: 0.3475 | I35: 0.3375 | J35: 0.3375 | K35: 0.3375 | L35: 0.3375 | M35: 0.3375
A36: Bear | D36: 0.4025 | E36: 0.3725 | F36: 0.3725 | G36: 0.3525 | H36: 0.3525 | I36: 0.3425 | J36: 0.3425 | K36: 0.3425 | L36: 0.3425 | M36: 0.3425
A38: Other Income | D38: {=INDEX(D39:D41,$C$3)} -> 0 | E38: 0 | F38: {=INDEX(F39:F41,$C$3)} -> 0 | G38: {=INDEX(G39:G41,$C$3)} -> 0 | H38: {=INDEX(H39:H41,$C$3)} -> 0 | I38: {=INDEX(I39:I41,$C$3)} -> 0 | J38: {=INDEX(J39:J41,$C$3)} -> 0 | K38: {=INDEX(K39:K41,$C$3)} -> 0 | L38: {=INDEX(L39:L41,$C$3)} -> 0 | M38: {=INDEX(M39:M41,$C$3)} -> 0
A39: Base | D39: 0 | E39: 0 | F39: 0 | G39: 0 | H39: 0 | I39: 0 | J39: 0 | K39: 0 | L39: 0 | M39: 0
A40: Bull | D40: 0 | E40: 0 | F40: 0 | G40: 0 | H40: 0 | I40: 0 | J40: 0 | K40: 0 | L40: 0 | M40: 0
A41: Bear | D41: 0 | E41: 0 | F41: 0 | G41: 0 | H41: 0 | I41: 0 | J41: 0 | K41: 0 | L41: 0 | M41: 0

Sheet DCF
A1: TSM
A2: Discounted Cash Flow Analysis
A3: For the Years Ended December 31
A4: Millions of New Taiwan Dollars
N5: Terminal
B6: =2023 -> 2023 | C6: =+B6+1 -> 2024 | D6: 2025E | E6: 2026E | F6: 2027E | G6: 2028E | H6: 2029E | I6: 2030E | J6: 2031E | K6: 2032E | L6: 2033E | M6: 2034E | N6: Value
B7: -------------- | C7: -------------- | D7: -------------- | E7: -------------- | F7: -------------- | G7: -------------- | H7: -------------- | I7: -------------- | J7: -------------- | K7: -------------- | L7: -------------- | M7: -------------- | N7: --------------
A8: Revenue | B8: 2161735.8 | C8: 2894307.7 | D8: =C8*(1+D57) -> 3675770.8 | E8: =D8*(1+E57) -> 4557955.8 | F8: =E8*(1+F57) -> 5560706 | G8: =F8*(1+G57) -> 6784061.4 | H8: =G8*(1+H57) -> 8276554.9 | I8: =H8*(1+I57) -> 9931865.8 | J8: =I8*(1+J57) -> 11918239 | K8: =J8*(1+K57) -> 14063522 | ... M8: =L8*(1+M57) -> 19582048
A9: Cost of Goods Sold | B9: 986625.2 | C9: 1269954.1 | D9: =D8*D58 -> 1580581.4 | E9: =E8*E58 -> 2005500.5 | F9: =F8*F58 -> 2446710.7 | G9: =G8*G58 -> 2968026.8 | H9: =H8*H58 -> 3620992.8 | I9: =I8*I58 -> 4320361.6 | J9: =J8*J58 -> 5184434 | K9: =K8*K58 -> 6047314.5 | ... M9: =M8*M58 -> 8420280.7
B10: -------------- | C10: -------------- | D10: -------------- | E10: -------------- | F10: -------------- | G10: -------------- | H10: -------------- | I10: -------------- | J10: -------------- | K10: -------------- | L10: -------------- | M10: --------------
A11: Gross Margin | B11: =+B8-B9 -> 1175110.6 | C11: =+C8-C9 -> 1624353.6 | D11: =D8-D9 -> 2095189.3 | E11: =E8-E9 -> 2552455.2 | F11: =F8-F9 -> 3113995.4 | G11: =G8-G9 -> 3816034.5 | H11: =H8-H9 -> 4655562.1 | I11: =I8-I9 -> 5611504.2 | J11: =J8-J9 -> 6733805 | K11: =K8-K9 -> 8016207.6 | ... M11: =M8-M9 -> 11161767
A13: Operating Expenses:
A14: SG&A | B14: 60872.8 | C14: 83745 | D14: =D8*D63 -> 110273.12 | E14: =E8*E63 -> 150412.54 | F14: =F8*F63 -> 194624.71 | G14: =G8*G63 -> 237442.15 | H14: =H8*H63 -> 289679.42 | I14: =I8*I63 -> 347615.3 | J14: =J8*J63 -> 417138.37 | K14: =K8*K63 -> 492223.27 | ... M14: =M8*M63 -> 685371.68
A15: R&D | B15: 182370.2 | C15: 204181.8 | D15: =D8*D64 -> 294061.66 | E15: =E8*E64 -> 387426.24 | F15: =F8*F64 -> 481001.07 | G15: =G8*G64 -> 552901 | H15: =H8*H64 -> 674539.22 | I15: =I8*I64 -> 809447.07 | J15: =J8*J64 -> 971336.48 | K15: =K8*K64 -> 1146177 | ... M15: =M8*M64 -> 1595936.9
A16: Marketing | B16: 10590.7 | C16: 13143.6 | D16: =D8*D65 -> 16540.969 | E16: =E8*E65 -> 20510.801 | F16: =F8*F65 -> 25023.177 | G16: =G8*G65 -> 30528.276 | H16: =H8*H65 -> 37244.497 | I16: =I8*I65 -> 44693.396 | J16: =J8*J65 -> 53632.076 | K16: =K8*K65 -> 63285.849 | ... M16: =M8*M65 -> 88119.216
B17: -------------- | C17: -------------- | D17: -------------- | E17: -------------- | F17: -------------- | G17: -------------- | H17: -------------- | I17: -------------- | J17: -------------- | K17: -------------- | L17: -------------- | M17: --------------
A18: Total Operating Expenses | B18: =SUM(B14:B17) -> 253833.7 | C18: =SUM(C14:C17) -> 301070.4 | D18: =SUM(D14:D16) -> 420875.75 | E18: =SUM(E14:E16) -> 558349.58 | F18: =SUM(F14:F16) -> 700648.96 | G18: =SUM(G14:G16) -> 820871.42 | H18: =SUM(H14:H16) -> 1001463.1 | I18: =SUM(I14:I16) -> 1201755.8 | J18: =SUM(J14:J16) -> 1442106.9 | K18: =SUM(K14:K16) -> 1701686.2 | ... M18: =SUM(M14:M16) -> 2369427.8
B19: -------------- | C19: -------------- | D19: -------------- | E19: -------------- | F19: -------------- | G19: -------------- | H19: -------------- | I19: -------------- | J19: -------------- | K19: -------------- | L19: -------------- | M19: --------------
A20: Operating Income | B20: =+B11-B18 -> 921276.9 | C20: =+C11-C18 -> 1323283.2 | D20: =D11-D18 -> 1674313.6 | E20: =E11-E18 -> 1994105.6 | F20: =F11-F18 -> 2413346.4 | G20: =G11-G18 -> 2995163.1 | H20: =H11-H18 -> 3654099 | I20: =I11-I18 -> 4409748.4 | J20: =J11-J18 -> 5291698.1 | K20: =K11-K18 -> 6314521.4 | ... M20: =M11-M18 -> 8792339.6
A22: Other Income/(Expense) | B22: =+B8*B71 -> 0 | C22: =+C8*C71 -> 0 | D22: =D71*D8 -> 0 | E22: =E71*E8 -> 0 | F22: =F71*F8 -> 0 | G22: =G71*G8 -> 0 | H22: =H71*H8 -> 0 | I22: =I71*I8 -> 0 | J22: =J71*J8 -> 0 | K22: =K71*K8 -> 0 | ... M22: =M71*M8 -> 0
B23: -------------- | C23: -------------- | D23: -------------- | E23: -------------- | F23: -------------- | G23: -------------- | H23: -------------- | I23: -------------- | J23: -------------- | K23: -------------- | L23: -------------- | M23: --------------
A24: Pretax Income | B24: =+B20+SUM(B22:B23) -> 921276.9 | C24: =+C20+SUM(C22:C23) -> 1323283.2 | D24: =SUM(D20:D22) -> 1674313.6 | E24: =SUM(E20:E22) -> 1994105.6 | F24: =SUM(F20:F22) -> 2413346.4 | G24: =SUM(G20:G22) -> 2995163.1 | H24: =SUM(H20:H22) -> 3654099 | I24: =SUM(I20:I22) -> 4409748.4 | J24: =SUM(J20:J22) -> 5291698.1 | K24: =SUM(K20:K22) -> 6314521.4 | ... M24: =SUM(M20:M22) -> 8792339.6
A25: Income Taxes | B25: =+B24*B74 -> 184255.38 | C25: =+C24*C74 -> 264656.64 | D25: =D24*D74 -> 334862.72 | E25: =E24*E74 -> 398821.13 | F25: =F24*F74 -> 482669.28 | G25: =G24*G74 -> 599032.62 | H25: =H24*H74 -> 730819.79 | I25: =I24*I74 -> 881949.69 | J25: =J24*J74 -> 1058339.6 | K25: =K24*K74 -> 1262904.3 | ... M25: =M24*M74 -> 1758467.9
B26: -------------- | C26: -------------- | D26: -------------- | E26: -------------- | F26: -------------- | G26: -------------- | H26: -------------- | I26: -------------- | J26: -------------- | K26: -------------- | L26: -------------- | M26: --------------
A27: Net Income | B27: =+B24-B25 -> 737021.52 | C27: =+C24-C25 -> 1058626.6 | D27: =D24-D25 -> 1339450.9 | E27: =E24-E25 -> 1595284.5 | F27: =F24-F25 -> 1930677.1 | G27: =G24-G25 -> 2396130.5 | H27: =H24-H25 -> 2923279.2 | I27: =I24-I25 -> 3527798.7 | J27: =J24-J25 -> 4233358.5 | K27: =K24-K25 -> 5051617.1 | ... M27: =M24-M25 -> 7033871.7
A29: + Depreciation & Amortization | B29: =B117 -> 532190.92 | C29: =C117 -> 662796.64 | D29: =D117 -> 1167747 | E29: =E117 -> 1291649.4 | F29: =F117 -> 1490256.6 | G29: =G117 -> 1752867.6 | H29: =H117 -> 2120699.4 | I29: =I117 -> 2505132.7 | ... M29: =M117 -> 4947394.3
A30: - Capital Expenditures | B30: -949817 | C30: -956006.54 | D30: =-D8*D80 -> -1479497.7 | E30: =-E8*E80 -> -1697838.5 | F30: =-F8*F80 -> -2071363 | G30: =-G8*G80 -> -2391381.6 | H30: =-H8*H80 -> -2917485.6 | I30: =-I8*I80 -> -3401664 | J30: =-J8*J80 -> -4081996.9 | K30: =-K8*K80 -> -4816756.3 | ... M30: =-M8*M80 -> -6706851.5
A31: - Working Capital Additions | B31: =56852.1 -> 56852.1 | C31: =-13350.8 -> -13350.8 | D31: =(C8-D8)*$B$82 -> -437619.32 | E31: =(D8-E8)*$B$82 -> -494023.59 | F31: =(E8-F8)*$B$82 -> -561540.15 | G31: =(F8-G8)*$B$82 -> -685078.98 | H31: =(G8-H8)*$B$82 -> -835796.36 | I31: =(H8-I8)*$B$82 -> -926974.14 | J31: =(I8-J8)*$B$82 -> -1112369 | K31: =(J8-K8)*$B$82 -> -1201358.5 | ... M31: =(L8-M8)*$B$82 -> -1672771.6
B32: -------------- | C32: -------------- | D32: -------------- | E32: -------------- | F32: -------------- | G32: -------------- | H32: -------------- | I32: -------------- | J32: -------------- | K32: -------------- | L32: -------------- | M32: --------------
A33: Free Cash Flow | B33: =+B27+SUM(B29:B32) -> 376247.54 | C33: =+C27+SUM(C29:C32) -> 752065.86 | D33: =(D27+SUM(D29:D31))*0.25 -> 147520.2 | E33: =E27+SUM(E29:E31) -> 695071.77 | F33: =F27+SUM(F29:F31) -> 788030.62 | G33: =G27+SUM(G29:G31) -> 1072537.5 | H33: =H27+SUM(H29:H31) -> 1290696.6 | I33: =I27+SUM(I29:I31) -> 1704293.2 | J33: =J27+SUM(J29:J31) -> 2020957 | K33: =K27+SUM(K29:K31) -> 2564545.3 | L33: =L27+SUM(L29:L31) -> 2465556.8 | M33: =M27+SUM(M29:M31) -> 3601643 | N33: =M27*(1-0.01/0.1846)/(B92-0.01) -> 70531395
A34: Present Value Factor | D34: =1/(1+$B$92)^(D93/12) -> 0.98767239 | E34: =1/(1+$B$92)^(E93/12) -> 0.92827674 | F34: =1/(1+$B$92)^(F93/12) -> 0.84058331 | G34: =1/(1+$B$92)^(G93/12) -> 0.76117419 | H34: =1/(1+$B$92)^(H93/12) -> 0.68926678 | I34: =1/(1+$B$92)^(I93/12) -> 0.62415239 | J34: =1/(1+$B$92)^(J93/12) -> 0.5651893 | K34: =1/(1+$B$92)^(K93/12) -> 0.5117964 | ... N34: =1/(1+$B$92)^(N93/12) -> 0.39935163
D35: -------------- | E35: -------------- | F35: -------------- | G35: -------------- | H35: -------------- | I35: -------------- | J35: -------------- | K35: -------------- | L35: -------------- | M35: -------------- | N35: --------------
A36: PV Free Cash Flow | D36: =D33*D34 -> 145701.63 | E36: =E33*E34 -> 645218.96 | F36: =+F33*F34 -> 662405.39 | G36: =+G33*G34 -> 816387.85 | H36: =+H33*H34 -> 889634.31 | I36: =+I33*I34 -> 1063738.7 | J36: =+J33*J34 -> 1142223.3 | K36: =+K33*K34 -> 1312525.1 | L36: =+L33*L34 -> 1142656.1 | M36: =+M33*M34 -> 1511487.2 | N36: =+N33*N34 -> 28166827
D37: --------------
A38: Value of Firm | D38: =SUM(D36:N36) -> 37498806
A39: Less: Debt Outstanding | D39: -2318529
A40: Plus: Cash | D40: 2470759
D41: --------------
A42: Equity Value | D42: =SUM(D38:D40) -> 37651036
A43: Shares Outstanding | D43: 25932.6
D44: --------------
A45: Value Per Share | D45: =D42/D43 -> 1451.8805 | F45: adr | G45: =D45/J45*5 -> 233.4213 | I45: fx | J45: 31.1 | L45: % of change | M45: =(G45-G48)/G48 -> -0.1804603
D46: ======== | G46: ========
A48: Share Price (11/14/25) | D48: 1430 | G48: 284.82
A50: TSM
A51: Discounted Cash Flow Analysis
A52: For the Years Ended
A53: Assumptions
B55: =2023 -> 2023 | C55: =+B55+1 -> 2024 | D55: =+C55+1 -> 2025 | E55: =+D55+1 -> 2026 | F55: =+E55+1 -> 2027 | G55: =+F55+1 -> 2028 | H55: =+G55+1 -> 2029 | I55: =+H55+1 -> 2030 | J55: =+I55+1 -> 2031 | ... M55: =+L55+1 -> 2034
B56: -------------- | C56: -------------- | D56: -------------- | E56: -------------- | F56: -------------- | G56: -------------- | H56: -------------- | I56: -------------- | J56: -------------- | K56: -------------- | L56: -------------- | M56: --------------
A57: Revenue Growth | B57: -0.0451 | C57: =+C8/B8-1 -> 0.33888133 | D57: =Assumption!D8 -> 0.27 | E57: =Assumption!E8 -> 0.24 | F57: =Assumption!F8 -> 0.22 | G57: =Assumption!G8 -> 0.22 | H57: =Assumption!H8 -> 0.22 | I57: =Assumption!I8 -> 0.2 | J57: =Assumption!J8 -> 0.2 | K57: =Assumption!K8 -> 0.18 | ... M57: =Assumption!M8 -> 0.18
A58: Cost of Goods Sold | B58: =+B9/B8 -> 0.45640415 | C58: =+C9/C8 -> 0.43877646 | D58: =Assumption!D14 -> 0.43 | E58: =Assumption!E14 -> 0.44 | F58: =Assumption!F14 -> 0.44 | G58: =Assumption!G14 -> 0.4375 | H58: =Assumption!H14 -> 0.4375 | I58: =Assumption!I14 -> 0.435 | J58: =Assumption!J14 -> 0.435 | K58: =Assumption!K14 -> 0.43 | ... M58: =Assumption!M14 -> 0.43
B59: -------------- | C59: -------------- | D59: -------------- | E59: -------------- | F59: -------------- | G59: -------------- | H59: -------------- | I59: -------------- | J59: -------------- | K59: -------------- | L59: -------------- | M59: --------------
A60: Gross Margin | B60: =+B11/B8 -> 0.54359585 | C60: =+C11/C8 -> 0.56122354 | D60: =Assumption!D13 -> 0.57 | E60: =Assumption!E13 -> 0.56 | F60: =Assumption!F13 -> 0.56 | G60: =Assumption!G13 -> 0.5625 | H60: =Assumption!H13 -> 0.5625 | I60: =Assumption!I13 -> 0.565 | J60: =Assumption!J13 -> 0.565 | K60: =Assumption!K13 -> 0.57 | ... M60: =Assumption!M13 -> 0.57
A62: Operating Expenses:
A63: SG&A | B63: =B14/B8 -> 0.028159223 | C63: =C14/C8 -> 0.02893438 | D63: =Assumption!D22 -> 0.03 | E63: =Assumption!E22 -> 0.033 | F63: =Assumption!F22 -> 0.035 | G63: =Assumption!G22 -> 0.035 | H63: =Assumption!H22 -> 0.035 | I63: =Assumption!I22 -> 0.035 | J63: =Assumption!J22 -> 0.035 | K63: =Assumption!K22 -> 0.035 | ... M63: =Assumption!M22 -> 0.035
A64: R&D | B64: =B15/B8 -> 0.084362853 | C64: =C15/C8 -> 0.070545989 | D64: =Assumption!D27 -> 0.08 | E64: =Assumption!E27 -> 0.085 | F64: =Assumption!F27 -> 0.0865 | G64: =Assumption!G27 -> 0.0815 | H64: =Assumption!H27 -> 0.0815 | I64: =Assumption!I27 -> 0.0815 | J64: =Assumption!J27 -> 0.0815 | K64: =Assumption!K27 -> 0.0815 | ... M64: =Assumption!M27 -> 0.0815
A65: Marketing | B65: =+B16/B8 -> 0.0048991648 | C65: =+C16/C8 -> 0.0045411896 | D65: 0.0045 | E65: 0.0045 | F65: 0.0045 | G65: 0.0045 | H65: 0.0045 | I65: 0.0045 | J65: 0.0045 | K65: 0.0045 | L65: 0.0045 | M65: 0.0045
B66: -------------- | C66: -------------- | D66: -------------- | E66: -------------- | F66: -------------- | G66: -------------- | H66: -------------- | I66: -------------- | J66: -------------- | K66: -------------- | L66: -------------- | M66: --------------
A67: Total Operating Expenses | B67: =+B18/B8 -> 0.11742124 | C67: =+C18/C8 -> 0.10402156 | D67: =+D18/D8 -> 0.1145 | E67: =+E18/E8 -> 0.1225 | F67: =+F18/F8 -> 0.126 | G67: =+G18/G8 -> 0.121 | H67: =+H18/H8 -> 0.121 | I67: =+I18/I8 -> 0.121 | ... M67: =+M18/M8 -> 0.121
B68: -------------- | C68: -------------- | D68: -------------- | E68: -------------- | F68: -------------- | G68: -------------- | H68: -------------- | I68: -------------- | J68: -------------- | K68: -------------- | L68: -------------- | M68: --------------
A69: Operating Income | B69: =+B20/B8 -> 0.4261746 | C69: =+C20/C8 -> 0.45720198 | D69: =D20/D11 -> 0.79912281 | E69: =E20/E11 -> 0.78125 | F69: =F20/F11 -> 0.775 | G69: =G20/G11 -> 0.78488889 | H69: =H20/H11 -> 0.78488889 | I69: =I20/I11 -> 0.78584071 | J69: =J20/J11 -> 0.78584071 | K69: =K20/K11 -> 0.7877193 | ... M69: =M20/M11 -> 0.7877193
A71: Other Income/(Expense) | B71: 0 | C71: 0 | D71: =Assumption!D38 -> 0 | E71: =Assumption!E38 -> 0 | F71: =Assumption!F38 -> 0 | G71: =Assumption!G38 -> 0 | H71: =Assumption!H38 -> 0 | I71: =Assumption!I38 -> 0 | J71: =Assumption!J38 -> 0 | K71: =Assumption!K38 -> 0 | ... M71: =Assumption!M38 -> 0
B72: -------------- | C72: -------------- | D72: -------------- | E72: -------------- | F72: -------------- | G72: -------------- | H72: -------------- | I72: -------------- | J72: -------------- | K72: -------------- | L72: -------------- | M72: --------------
A73: Pretax Income | B73: =+B24/B8 -> 0.4261746 | C73: =+C24/C8 -> 0.45720198 | D73: =D24/D8 -> 0.4555 | E73: =E24/E8 -> 0.4375 | F73: =F24/F8 -> 0.434 | G73: =G24/G8 -> 0.4415 | H73: =H24/H8 -> 0.4415 | I73: =I24/I8 -> 0.444 | J73: =J24/J8 -> 0.444 | K73: =K24/K8 -> 0.449 | ... M73: =M24/M8 -> 0.449
A74: Income Tax Rate | B74: 0.2 | C74: 0.2 | D74: 0.2 | E74: 0.2 | F74: 0.2 | G74: 0.2 | H74: 0.2 | I74: 0.2 | J74: 0.2 | K74: 0.2 | L74: 0.2 | M74: 0.2
B75: -------------- | C75: -------------- | D75: -------------- | E75: -------------- | F75: -------------- | G75: -------------- | H75: -------------- | I75: -------------- | J75: -------------- | K75: -------------- | L75: -------------- | M75: --------------
A76: Net Income | B76: =+B27/B8 -> 0.34093968 | C76: =+C27/C8 -> 0.36576158 | D76: =D27/D8 -> 0.3644 | E76: =E27/E8 -> 0.35 | F76: =F27/F8 -> 0.3472 | G76: =G27/G8 -> 0.3532 | H76: =H27/H8 -> 0.3532 | I76: =I27/I8 -> 0.3552 | J76: =J27/J8 -> 0.3552 | K76: =K27/K8 -> 0.3592 | ... M76: =M27/M8 -> 0.3592
A78: Net PP&E | B78: 3064475 | C78: 3234980.1 | D78: =C78-D114-D30 -> 3555916.9 | E78: =D78-E114-E30 -> 3971292.2 | F78: =E78-F114-F30 -> 4561584.6 | G78: =F78-G114-G30 -> 5209284.8 | H78: =G78-H114-H30 -> 6015257.1 | I78: =H78-I114-I30 -> 6920974.5 | J78: =I78-J114-J30 -> 8030193.2 | K78: =J78-K114-K30 -> 9325092.6 | ... M78: =L78-M114-M30 -> 13180670
A79: Revenue/Net PP&E | B79: =+B8/B78 -> 0.70541799 | C79: =+C8/C78 -> 0.89469104 | D79: =D8/D78 -> 1.0337055 | E79: =E8/E78 -> 1.1477261 | F79: =F8/F78 -> 1.2190295 | G79: =G8/G78 -> 1.3023019 | H79: =H8/H78 -> 1.375927 | I79: =I8/I78 -> 1.4350386 | J79: =J8/J78 -> 1.4841784 | K79: =K8/K78 -> 1.5081375 | ... M79: =M8/M78 -> 1.485664
A80: Capital Expenditure % of Rev | B80: =-B30/B8 -> 0.439377 | C80: =-C30/C8 -> 0.33030577 | D80: =Assumption!D33 -> 0.4025 | E80: =Assumption!E33 -> 0.3725 | F80: =Assumption!F33 -> 0.3725 | G80: =Assumption!G33 -> 0.3525 | H80: =Assumption!H33 -> 0.3525 | I80: =Assumption!I33 -> 0.3425 | J80: =Assumption!J33 -> 0.3425 | K80: =Assumption!K33 -> 0.3425 | ... M80: =Assumption!M33 -> 0.3425
A81: Depreciation/Revenue | B81: =+B114/B8 -> 0.24190408 | C81: =+C114/C8 -> 0.22582621 | D81: =D114/D8 -> 0.31518856 | E81: =E114/E8 -> 0.28136808 | F81: =F114/F8 -> 0.26634577 | G81: =G114/G8 -> 0.2570262 | H81: =H114/H8 -> 0.25511983 | I81: =I114/I8 -> 0.25130691 | J81: =J114/J8 -> 0.249431 | K81: =K114/K8 -> 0.25042496 | ... M81: =M114/M8 -> 0.25218037
A82: Working Capital/Revenue | B82: 0.56
A84: Discount Rate:
A85: Risk-Free Rate | B85: 0.043
A86: Risk Premium | B86: 0.045
A87: Beta | B87: 1.496
A88: K(e) | B88: =B85+B87*B86 -> 0.11032
A89: K(d) | B89: 0.01799
A90: Tax Rate | B90: 0.2
A91: Debt/Capital | B91: 0.0625
A92: WACC | B92: =(B89*(1-B90)*B91+B88*(1-B91)) -> 0.1043245
B93: 0 | C93: 0 | D93: 1.5 | E93: 9 | F93: =+E93+12 -> 21 | G93: =+F93+12 -> 33 | H93: =+G93+12 -> 45 | I93: =+H93+12 -> 57 | J93: =+I93+12 -> 69 | K93: =+J93+12 -> 81 | L93: =+K93+12 -> 93 | M93: =+L93+12 -> 105 | N93: =+M93+6 -> 111
A95: TSM
A96: Discounted Cash Flow Analysis
A97: For the Years Ended
A98: Depreciation Schedule
B100: =2023 -> 2023 | C100: =+B100+1 -> 2024 | D100: =+C100+1 -> 2025 | E100: =+D100+1 -> 2026 | F100: =+E100+1 -> 2027 | G100: =+F100+1 -> 2028 | H100: =+G100+1 -> 2029 | I100: =+H100+1 -> 2030 | J100: =+I100+1 -> 2031 | ... M100: =+L100+1 -> 2034
B101: -------------- | C101: -------------- | D101: -------------- | E101: -------------- | F101: -------------- | G101: -------------- | H101: -------------- | I101: -------------- | J101: -------------- | K101: -------------- | L101: -------------- | M101: --------------
A102: 2024 Net PP&E | D102: =$C$78*(2029-D100)/15 -> 862661.36 | E102: =$C$78*(2029-E100)/15 -> 646996.02 | F102: =$C$78*(2029-F100)/15 -> 431330.68 | G102: =$C$78*(2029-G100)/15 -> 215665.34 | H102: =$C$78*(2029-H100)/15 -> 0 | I102: 0 | J102: 0 | K102: 0 | L102: 0 | M102: 0
A103: 2025 Capital Expenditures | D103: =-$D$30/5 -> 295899.55 | E103: =-$D$30/5 -> 295899.55 | F103: =-$D$30/5 -> 295899.55 | G103: =-$D$30/5 -> 295899.55 | H103: =-$D$30/5 -> 295899.55 | I103: 0 | J103: 0 | K103: 0 | L103: 0 | M103: 0
A104: 2026 Capital Expenditures | E104: =-$E$30/5 -> 339567.7 | F104: =-$E$30/5 -> 339567.7 | G104: =-$E$30/5 -> 339567.7 | H104: =-$E$30/5 -> 339567.7 | I104: =-$E$30/5 -> 339567.7 | J104: 0 | K104: 0 | L104: 0 | M104: 0
A105: 2027 Capital Expenditures | F105: =-$F$30/5 -> 414272.6 | G105: =-$F$30/5 -> 414272.6 | H105: =-$F$30/5 -> 414272.6 | I105: =-$F$30/5 -> 414272.6 | J105: =-$F$30/5 -> 414272.6 | K105: 0 | L105: 0 | M105: 0
A106: 2028 Capital Expenditures | G106: =-$G$30/5 -> 478276.33 | H106: =-$G$30/5 -> 478276.33 | I106: =-$G$30/5 -> 478276.33 | J106: =-$G$30/5 -> 478276.33 | K106: =-$G$30/5 -> 478276.33 | L106: 0 | M106: 0
A107: 2029 Capital Expenditures | H107: =-$H$30/5 -> 583497.12 | I107: =-$H$30/5 -> 583497.12 | J107: =-$H$30/5 -> 583497.12 | K107: =-$H$30/5 -> 583497.12 | L107: 0 | M107: 0
A108: 2030 Capital Expenditures | I108: =-$I$30/5 -> 680332.81 | J108: =-$I$30/5 -> 680332.81 | K108: =-$I$30/5 -> 680332.81 | L108: =-$I$30/5 -> 680332.81 | M108: =-$I$30/5 -> 680332.81
A109: 2031 Capital Expenditures | J109: =-$J$30/5 -> 816399.37 | K109: =-$J$30/5 -> 816399.37 | L109: =-$J$30/5 -> 816399.37 | M109: =-$J$30/5 -> 816399.37
A110: 2032 Capital Expenditures | K110: =-$K$30/5 -> 963351.26 | L110: =-$K$30/5 -> 963351.26 | M110: =-$K$30/5 -> 963351.26
A111: 2033 Capital Expenditures | L111: =-$L$30/5 -> 1136754.5 | M111: =-$L$30/5 -> 1136754.5
A112: 2034 Capital Expenditures | M112: =-$M$30/5 -> 1341370.3
...

Sheet Sheet1
A1: FY2026 Assumption
A2: Case | B2: Revenue Growth | C2: Gross Margins | D2: Operating Expenses | E2: Capex
A3: Base | B3: 0.3 | C3: 0.5917 | D3: 0.1021 | E3: 0.4
A4: Bull | B4: 0.325 | C4: 0.6075 | D4: 0.0975 | E4: 0.3975
A5: Bear | B5: 0.27 | C5: 0.57 | D5: 0.11 | E5: 0.4025

Sheet working_capital
B1: 2020 | C1: 2021 | D1: 2022 | E1: 2023 | F1: 2024 | G1: 2025e
A2: working capital | B2: 475034.3 | C2: 867569.5 | D2: 1108669.9 | E2: 1280449.6 | F2: 1823327.2 | G2: 2490320.5
A3: change in working capital | C3: =C2-B2 -> 392535.2 | D3: =D2-C2 -> 241100.4 | E3: =E2-D2 -> 171779.7 | F3: =F2-E2 -> 542877.6 | G3: =G2-F2 -> 666993.3
A5: rev | B5: 1339255 | C5: 1587420 | D5: 2263891.3 | E5: 2161735.8 | F5: 2894308 | G5: 3775464.6
A6: working capital/rev | B6: =B2/B5 -> 0.35470041 | C6: =C2/C5 -> 0.54652801 | D6: =D2/D5 -> 0.4897187 | E6: =E2/E5 -> 0.59232474 | F6: =F2/F5 -> 0.62997 | G6: =G2/G5 -> 0.65960637
A11: 11/14 market cap | B11: 37083640
A12: 11/14 total debt | B12: 2318519
A14: 11/14 debt/capital | B14: =B12/B11 -> 0.062521344
A19: r&d (% of rev) | B19: 8.18 | C19: 7.86 | D19: 7.21 | E19: 8.44 | F19: 7.05
A23: rev yoy | B23: 25.17 | C23: 18.53 | D23: 42.61 | E23: -4.51 | F23: 33.89
A25: cogs ( % rev) | B25: 46.9 | C25: 48.37 | D25: 40.44 | E25: 45.64 | F25: 43.88
